Workbook
Name BG: #REF!
Name BG: #REF!
Name csDesignMode: 1
Name DATA: #REF!
Name DATA: #REF!

Sheet VAC+13th (2)
B1: VACATION ACCRUAL LOCAL EMPLOYEES-FCH 2025 | AG1: 9 | AH1: =+AG1+1 -> 10 | AI1: =+AH1+1 -> 11 | AJ1: =+AI1+1 -> 12 | AK1: =+AJ1+1 -> 13 | AL1: =+AK1+1 -> 14 | AM1: =+AL1+1 -> 15 | AN1: =+AM1+1 -> 16 | AO1: =+AN1+1 -> 17 | ... AS1: =+AR1+1 -> 21
B2: FILL ALL THE CELLS IN GREEN ONLY
A3: 1 | B3: =+A3+1 -> 2 | C3: =+B3+1 -> 3 | D3: 4 | E3: =+D3+1 -> 5 | G3: =+E3+1 -> 6 | H3: =+G3+1 -> 7 | I3: =+H3+1 -> 8 | J3: =+I3+1 -> 9 | K3: =+J3+1 -> 10 | L3: =+K3+1 -> 11 | M3: =+L3+1 -> 12 | N3: =+M3+1 -> 13 | O3: =+N3+1 -> 14 | ... AD3: =+AC3+1 -> 29 | AF3: =+AD3+1 -> 30 | AG3: =+AF3+1 -> 31 | AH3: =+AG3+1 -> 32 | AI3: =+AH3+1 -> 33 | AJ3: =+AI3+1 -> 34 | AK3: =+AJ3+1 -> 35 | AL3: =+AK3+1 -> 36 | AM3: =+AL3+1 -> 37 | AN3: =+AM3+1 -> 38 | ... CJ3: =+CI3+1 -> 86
A4: 1 | B4: -Add new employee names & information | H4: 45647 | R4: DAYS OF THE Month | S4: =+DAY(S6-S5) -> 30 | T4: =+DAY(T6-T5) -> 30 | U4: =+DAY(U6-U5) -> 27 | V4: =+DAY(V6-V5) -> 30 | W4: =+DAY(W6-W5) -> 29 | X4: =+DAY(X6-X5) -> 30 | Y4: =+DAY(Y6-Y5) -> 29 | Z4: =+DAY(Z6-Z5) -> 30 | ... AD4: =+DAY(AD6-AD5) -> 29 | AW4: =+MONTH(AW5) -> 12 | AX4: =+MONTH(AX5) -> 1 | AY4: =+MONTH(AY5) -> 2 | AZ4: =+MONTH(AZ5) -> 3 | BA4: =+MONTH(BA5) -> 4 | BB4: =+MONTH(BB5) -> 5 | BC4: =+MONTH(BC5) -> 6 | BD4: =+MONTH(BD5) -> 7 | ... BH4: =+MONTH(BH5) -> 11 | BJ4: =+MONTH(BJ5) -> 12 | BK4: =+MONTH(BK5) -> 1 | BL4: =+MONTH(BL5) -> 2 | BM4: =+MONTH(BM5) -> 3 | BN4: =+MONTH(BN5) -> 4 | BO4: =+MONTH(BO5) -> 5 | BP4: =+MONTH(BP5) -> 6 | BQ4: =+MONTH(BQ5) -> 7 | ... BU4: =+MONTH(BU5) -> 11
B5: -Don’t' delete names of employee who have left, Just fill the leaving date in cell F | H5: 45677 | S5: 45647 | T5: 45678 | U5: 45709 | V5: 45737 | W5: 45768 | X5: 45798 | Y5: 45829 | Z5: 45859 | AA5: 45890 | AB5: 45921 | AC5: 45951 | AD5: 45982 | AG5: =S5 -> 45647 | AH5: =T5 -> 45678 | AI5: =U5 -> 45709 | AJ5: 45737 | AK5: =W5 -> 45768 | AL5: =X5 -> 45798 | AM5: =Y5 -> 45829 | AN5: =Z5 -> 45859 | AO5: =AA5 -> 45890 | AP5: =AB5 -> 45921 | AQ5: =AC5 -> 45951 | AR5: =AD5 -> 45982 | AW5: =S5 -> 45647 | AX5: =T5 -> 45678 | AY5: =U5 -> 45709 | AZ5: =V5 -> 45737 | BA5: =W5 -> 45768 | BB5: =X5 -> 45798 | BC5: =Y5 -> 45829 | BD5: =Z5 -> 45859 | ... BH5: =AD5 -> 45982 | BJ5: =S5 -> 45647 | BK5: =T5 -> 45678 | BL5: =U5 -> 45709 | BM5: =V5 -> 45737 | BN5: =W5 -> 45768 | BO5: =X5 -> 45798 | BP5: =Y5 -> 45829 | BQ5: =Z5 -> 45859 | ... BU5: =AD5 -> 45982 | BX5: 45658 | BY5: 45689 | BZ5: 45717 | CA5: 45748 | CB5: 45778 | CC5: 45809 | CD5: 45839 | CE5: 45870 | CF5: 45901 | CG5: 45931 | CH5: 45962 | CI5: 45992
A6: ADD | B6: ADD | C6: ADD | E6: ADD | G6: ADD | L6: ADD | O6: ADD | P6: 45658 | S6: 45677 | T6: 45708 | U6: 45736 | V6: 45767 | W6: 45797 | X6: 45828 | Y6: 45858 | Z6: 45889 | AA6: 45920 | AB6: 45950 | AC6: 45981 | AD6: 46011 | AG6: =S6 -> 45677 | AH6: =T6 -> 45708 | AI6: =U6 -> 45736 | AJ6: 43941 | AK6: =W6 -> 45797 | AL6: =X6 -> 45828 | AM6: =Y6 -> 45858 | AN6: =Z6 -> 45889 | AO6: =AA6 -> 45920 | AP6: =AB6 -> 45950 | AQ6: =AC6 -> 45981 | AR6: =AD6 -> 46011 | AU6: 231330 | AW6: =S6 -> 45677 | AX6: =T6 -> 45708 | AY6: =U6 -> 45736 | AZ6: =V6 -> 45767 | BA6: =W6 -> 45797 | BB6: =X6 -> 45828 | BC6: =Y6 -> 45858 | BD6: =Z6 -> 45889 | ... BH6: =AD6 -> 46011 | BI6: 231330 | BJ6: =S6 -> 45677 | BK6: =T6 -> 45708 | BL6: =U6 -> 45736 | BM6: =V6 -> 45767 | BN6: =W6 -> 45797 | BO6: =X6 -> 45828 | BP6: =Y6 -> 45858 | BQ6: =Z6 -> 45889 | ... BU6: =AD6 -> 46011 | BX6: 45688 | BY6: 45716 | BZ6: 45747 | CA6: 45777 | CB6: 45808 | CC6: 45838 | CD6: 45869 | CE6: 45900 | CF6: 45930 | CG6: 45961 | CH6: 45991 | CI6: 46022 | CJ6: 231120
A7: ID | B7: Nom | C7: POSITION | D7: CC | E7: Salaire de base Mensuel | G7: Starting date | H7: Current YEAR Date Prov. | I7: Type | J7: CDI Date | K7: Change Date1 | L7: New Base1 | M7: Change Date2 | N7: New Base2 | O7: Leaving date | P7: 1Day Ancienneté/5Years in Current Year | Q7: VACATION BALANCE 2024 (Days) | R7: TOTAL VACATION ACCRUAL 2025 (Days) | S7: Jan | T7: Feb | U7: Mar | V7: Apr | W7: May | X7: Jun | Y7: Jul | Z7: Aug | AA7: Sep | AB7: Oct | AC7: Nov | AD7: Dec | AE7: 1 | AF7: TOTAL DAYS PAID/FINANCE (25) | AG7: Jan | AH7: Feb | AI7: Mar | AJ7: Apr | AK7: May | AL7: Jun | AM7: Jul | AN7: Aug | AO7: Sep | AP7: Oct | AQ7: Nov | AR7: Dec | AS7: TOTAL BALANCE Days TO PAY 2025 | AU7: TOTAL VACATION BALANCE 2024 ($) | AV7: TOTAL VACATION ACCRUAL 2025($) | AW7: Jan | AX7: Feb | AY7: Mar | AZ7: Apr | BA7: May | BB7: Jun | BC7: Jul | BD7: Aug | BE7: Sep | BF7: Oct | BG7: Nov | BH7: Dec | BI7: $ TAKEN (Reversal) | BJ7: Jan | BK7: Feb | BL7: Mar | BM7: Apr | BN7: May | BO7: Jun | BP7: Jul | BQ7: Aug | BR7: Sep | BS7: Oct | BT7: Nov | BU7: Dec | BV7: TOTAL BALANCE $ 2025 231330 | BW7: 1 | BX7: Jan | BY7: Feb | BZ7: Mar | CA7: Apr | CB7: May | CC7: Jun | CD7: Jul | CE7: Aug | CF7: Sep | CG7: Oct | CH7: Nov | CI7: Dec | CJ7: TOTAL 13th Month BALANCE 2025 ($) | CK7: DAYS/YEAR | CM7: Salaire de base
A8: 03035 | B8: KIWIDI SALABISALA CHRISTIAN | C8: Income Auditor | D8: =+VLOOKUP(A8,'[1]BDD-Avk Tx'!B:CE,82,0) -> 620 | E8: 634.4 | G8: 41563 | H8: =+IF(YEAR(G8)<YEAR($H$5),$H$4,G8) -> 45647 | I8: =+VLOOKUP(A8,'[1]BDD-Avk Tx'!B:BZ,77,0) -> CDI | J8: =+IF(I8="CDI",H8,H8+0) -> 45647 | P8: =DATEDIF(G8,$AD$6,"m")/12 -> 12.166667 | Q8: 64 | R8: =SUM(S8:AD8) -> 20 | S8: =+IF(AND(AND($O8="",$P8>=10,MONTH($G8)=MONTH(S$5))),1.5+2,+IF(AND(AND($O8="",$P8>=5,MONTH($G8)=MONTH(S$5))),1.5+1,+IF(AND(AND($P8=5,$O8="",MONTH($G8)=MONTH(S$5))),1.5,+IF(AND($H8>S$5,MONTH($H8)=MONTH(S$5)),1.5/30*(S$4-DAY($H8)),+IF(AND(MONTH($H8)<MONTH(S$5),$O8=""),1.5,+IF(AND($H8=$S$5,$O8=""),1.5,IF($O8<S$5,0,IF(MONTH($O8)=MONTH(S$5),1.5/30*($O8-S$5),1.5)))))))) -> 1.5 | T8: =+IF(AND(AND($O8="",$P8>=10,MONTH($G8)=MONTH(T$5))),1.5+2,+IF(AND(AND($O8="",$P8>=5,MONTH($G8)=MONTH(T$5))),1.5+1,+IF(AND(AND($P8=5,$O8="",MONTH($G8)=MONTH(T$5))),1.5,+IF(AND($H8>T$5,MONTH($H8)=MONTH(T$5)),1.5/30*(T$4-DAY($H8)),+IF(AND(MONTH($H8)<MONTH(T$5),$O8=""),1.5,+IF(AND($H8=$S$5,$O8=""),1.5,IF($O8<T$5,0,IF(MONTH($O8)=MONTH(T$5),1.5/30*($O8-T$5),1.5)))))))) -> 1.5 | U8: =+IF(AND(AND($O8="",$P8>=10,MONTH($G8)=MONTH(U$5))),1.5+2,+IF(AND(AND($O8="",$P8>=5,MONTH($G8)=MONTH(U$5))),1.5+1,+IF(AND(AND($P8=5,$O8="",MONTH($G8)=MONTH(U$5))),1.5,+IF(AND($H8>U$5,MONTH($H8)=MONTH(U$5)),1.5/30*(U$4-DAY($H8)),+IF(AND(MONTH($H8)<MONTH(U$5),$O8=""),1.5,+IF(AND($H8=$S$5,$O8=""),1.5,IF($O8<U$5,0,IF(MONTH($O8)=MONTH(U$5),1.5/30*($O8-U$5),1.5)))))))) -> 1.5 | V8: =+IF(AND(AND($O8="",$P8>=10,MONTH($G8)=MONTH(V$5))),1.5+2,+IF(AND(AND($O8="",$P8>=5,MONTH($G8)=MONTH(V$5))),1.5+1,+IF(AND(AND($P8=5,$O8="",MONTH($G8)=MONTH(V$5))),1.5,+IF(AND($H8>V$5,MONTH($H8)=MONTH(V$5)),1.5/30*(V$4-DAY($H8)),+IF(AND(MONTH($H8)<MONTH(V$5),$O8=""),1.5,+IF(AND($H8=$S$5,$O8=""),1.5,IF($O8<V$5,0,IF(MONTH($O8)=MONTH(V$5),1.5/30*($O8-V$5),1.5)))))))) -> 1.5 | W8: =+IF(AND(AND($O8="",$P8>=10,MONTH($G8)=MONTH(W$5))),1.5+2,+IF(AND(AND($O8="",$P8>=5,MONTH($G8)=MONTH(W$5))),1.5+1,+IF(AND(AND($P8=5,$O8="",MONTH($G8)=MONTH(W$5))),1.5,+IF(AND($H8>W$5,MONTH($H8)=MONTH(W$5)),1.5/30*(W$4-DAY($H8)),+IF(AND(MONTH($H8)<MONTH(W$5),$O8=""),1.5,+IF(AND($H8=$S$5,$O8=""),1.5,IF($O8<W$5,0,IF(MONTH($O8)=MONTH(W$5),1.5/30*($O8-W$5),1.5)))))))) -> 1.5 | X8: =+IF(AND(AND($O8="",$P8>=10,MONTH($G8)=MONTH(X$5))),1.5+2,+IF(AND(AND($O8="",$P8>=5,MONTH($G8)=MONTH(X$5))),1.5+1,+IF(AND(AND($P8=5,$O8="",MONTH($G8)=MONTH(X$5))),1.5,+IF(AND($H8>X$5,MONTH($H8)=MONTH(X$5)),1.5/30*(X$4-DAY($H8)),+IF(AND(MONTH($H8)<MONTH(X$5),$O8=""),1.5,+IF(AND($H8=$S$5,$O8=""),1.5,IF($O8<X$5,0,IF(MONTH($O8)=MONTH(X$5),1.5/30*($O8-X$5),1.5)))))))) -> 1.5 | Y8: =+IF(AND(AND($O8="",$P8>=10,MONTH($G8)=MONTH(Y$5))),1.5+2,+IF(AND(AND($O8="",$P8>=5,MONTH($G8)=MONTH(Y$5))),1.5+1,+IF(AND(AND($P8=5,$O8="",MONTH($G8)=MONTH(Y$5))),1.5,+IF(AND($H8>Y$5,MONTH($H8)=MONTH(Y$5)),1.5/30*(Y$4-DAY($H8)),+IF(AND(MONTH($H8)<MONTH(Y$5),$O8=""),1.5,+IF(AND($H8=$S$5,$O8=""),1.5,IF($O8<Y$5,0,IF(MONTH($O8)=MONTH(Y$5),1.5/30*($O8-Y$5),1.5)))))))) -> 1.5 | Z8: =+IF(AND(AND($O8="",$P8>=10,MONTH($G8)=MONTH(Z$5))),1.5+2,+IF(AND(AND($O8="",$P8>=5,MONTH($G8)=MONTH(Z$5))),1.5+1,+IF(AND(AND($P8=5,$O8="",MONTH($G8)=MONTH(Z$5))),1.5,+IF(AND($H8>Z$5,MONTH($H8)=MONTH(Z$5)),1.5/30*(Z$4-DAY($H8)),+IF(AND(MONTH($H8)<MONTH(Z$5),$O8=""),1.5,+IF(AND($H8=$S$5,$O8=""),1.5,IF($O8<Z$5,0,IF(MONTH($O8)=MONTH(Z$5),1.5/30*($O8-Z$5),1.5)))))))) -> 1.5 | ... AD8: =+IF(AND(AND($O8="",$P8>=10,MONTH($G8)=MONTH(AD$5))),1.5+2,+IF(AND(AND($O8="",$P8>=5,MONTH($G8)=MONTH(AD$5))),1.5+1,+IF(AND(AND($P8=5,$O8="",MONTH($G8)=MONTH(AD$5))),1.5,+IF(AND($H8>AD$5,MONTH($H8)=MONTH(AD$5)),1.5/30*(AD$4-DAY($H8)),+IF(AND(MONTH($H8)<MONTH(AD$5),$O8=""),1.5,+IF(AND($H8=$S$5,$O8=""),1.5,IF($O8<AD$5,0,IF(MONTH($O8)=MONTH(AD$5),1.5/30*($O8-AD$5),1.5)))))))) -> 1.5 | AF8: =SUM(AG8:AR8) -> 0 | AG8: 0 | AH8: 0 | AI8: 0 | AS8: =+Q8+R8-AF8 -> 84 | AU8: 1223.4385 | AV8: =SUM(AW8:BH8) -> 488 | AW8: =+IF($K8="",$E8/26*S8,IF(MONTH($K8)=MONTH(AW$5),$L8/26*S8,IF(AND($K8<AW$5,(MONTH($K8)<>MONTH(AW$5))),$L8/26*S8,$E8/26*S8))) -> 36.6 | AX8: =+IF($K8="",$E8/26*T8,IF(MONTH($K8)=MONTH(AX$5),$L8/26*T8,IF(AND($K8<AX$5,(MONTH($K8)<>MONTH(AX$5))),$L8/26*T8,$E8/26*T8))) -> 36.6 | AY8: =+IF($K8="",$E8/26*U8,IF(MONTH($K8)=MONTH(AY$5),$L8/26*U8,IF(AND($K8<AY$5,(MONTH($K8)<>MONTH(AY$5))),$L8/26*U8,$E8/26*U8))) -> 36.6 | AZ8: =+IF($K8="",$E8/26*V8,IF(MONTH($K8)=MONTH(AZ$5),$L8/26*V8,IF(AND($K8<AZ$5,(MONTH($K8)<>MONTH(AZ$5))),$L8/26*V8,$E8/26*V8))) -> 36.6 | BA8: =+IF($K8="",$E8/26*W8,IF(MONTH($K8)=MONTH(BA$5),$L8/26*W8,IF(AND($K8<BA$5,(MONTH($K8)<>MONTH(BA$5))),$L8/26*W8,$E8/26*W8))) -> 36.6 | BB8: =+IF($K8="",$E8/26*X8,IF(MONTH($K8)=MONTH(BB$5),$L8/26*X8,IF(AND($K8<BB$5,(MONTH($K8)<>MONTH(BB$5))),$L8/26*X8,$E8/26*X8))) -> 36.6 | BC8: =+IF($K8="",$E8/26*Y8,IF(MONTH($K8)=MONTH(BC$5),$L8/26*Y8,IF(AND($K8<BC$5,(MONTH($K8)<>MONTH(BC$5))),$L8/26*Y8,$E8/26*Y8))) -> 36.6 | BD8: =+IF($K8="",$E8/26*Z8,IF(MONTH($K8)=MONTH(BD$5),$L8/26*Z8,IF(AND($K8<BD$5,(MONTH($K8)<>MONTH(BD$5))),$L8/26*Z8,$E8/26*Z8))) -> 36.6 | ... BH8: =+IF($K8="",$E8/26*AD8,IF(MONTH($K8)=MONTH(BH$5),$L8/26*AD8,IF(AND($K8<BH$5,(MONTH($K8)<>MONTH(BH$5))),$L8/26*AD8,$E8/26*AD8))) -> 36.6 | BI8: =SUM(BJ8:BU8) -> 0 | BJ8: =(+IF($K8="",$E8/26*AG8,IF(MONTH($K8)=MONTH(BJ$5),$L8/26*AG8,IF(AND($K8<BJ$5,(MONTH($K8)<>MONTH(BJ$5))),$L8/26*AG8,$E8/26*AG8))))*-1 -> 0 | BK8: =(+IF($K8="",$E8/26*AH8,IF(MONTH($K8)=MONTH(BK$5),$L8/26*AH8,IF(AND($K8<BK$5,(MONTH($K8)<>MONTH(BK$5))),$L8/26*AH8,$E8/26*AH8))))*-1 -> 0 | BL8: =(+IF($K8="",$E8/26*AI8,IF(MONTH($K8)=MONTH(BL$5),$L8/26*AI8,IF(AND($K8<BL$5,(MONTH($K8)<>MONTH(BL$5))),$L8/26*AI8,$E8/26*AI8))))*-1 -> 0 | BM8: =(+IF($K8="",$E8/26*AJ8,IF(MONTH($K8)=MONTH(BM$5),$L8/26*AJ8,IF(AND($K8<BM$5,(MONTH($K8)<>MONTH(BM$5))),$L8/26*AJ8,$E8/26*AJ8))))*-1 -> 0 | BN8: =(+IF($K8="",$E8/26*AK8,IF(MONTH($K8)=MONTH(BN$5),$L8/26*AK8,IF(AND($K8<BN$5,(MONTH($K8)<>MONTH(BN$5))),$L8/26*AK8,$E8/26*AK8))))*-1 -> 0 | BO8: =(+IF($K8="",$E8/26*AL8,IF(MONTH($K8)=MONTH(BO$5),$L8/26*AL8,IF(AND($K8<BO$5,(MONTH($K8)<>MONTH(BO$5))),$L8/26*AL8,$E8/26*AL8))))*-1 -> 0 | BP8: =(+IF($K8="",$E8/26*AM8,IF(MONTH($K8)=MONTH(BP$5),$L8/26*AM8,IF(AND($K8<BP$5,(MONTH($K8)<>MONTH(BP$5))),$L8/26*AM8,$E8/26*AM8))))*-1 -> 0 | BQ8: =(+IF($K8="",$E8/26*AN8,IF(MONTH($K8)=MONTH(BQ$5),$L8/26*AN8,IF(AND($K8<BQ$5,(MONTH($K8)<>MONTH(BQ$5))),$L8/26*AN8,$E8/26*AN8))))*-1 -> 0 | ... BU8: =(+IF($K8="",$E8/26*AR8,IF(MONTH($K8)=MONTH(BU$5),$L8/26*AR8,IF(AND($K8<BU$5,(MONTH($K8)<>MONTH(BU$5))),$L8/26*AR8,$E8/26*AR8))))*-1 -> 0 | BV8: =+AU8+AV8+BI8 -> 1711.4385 | BX8: =+IF(AND($J8>BX$5,MONTH($J8<>BX$5)),0,+IF(AND($J8>BX$5,MONTH($J8=BX$5)),$E8/$R8*DAY($J8),IF(AND($O8<>"",$O8<BX$5),0,IF($K8="",$E8/$R8*S8,IF(MONTH($K8)=MONTH(BX$5),$L8/$R8*S8,IF(AND($K8<BX$5,(MONTH($K8)<>MONTH(BX$5))),$L8/$R8*S8,$E8/$R8*S8)))))) -> 47.58 | BY8: =+IF(AND($J8>BY$5,MONTH($J8<>BY$5)),0,+IF(AND($J8>BY$5,MONTH($J8=BY$5)),$E8/$R8*DAY($J8),IF(AND($O8<>"",$O8<BY$5),0,IF($K8="",$E8/$R8*T8,IF(MONTH($K8)=MONTH(BY$5),$L8/$R8*T8,IF(AND($K8<BY$5,(MONTH($K8)<>MONTH(BY$5))),$L8/$R8*T8,$E8/$R8*T8)))))) -> 47.58 | BZ8: =+IF(AND($J8>BZ$5,MONTH($J8<>BZ$5)),0,+IF(AND($J8>BZ$5,MONTH($J8=BZ$5)),$E8/$R8*DAY($J8),IF(AND($O8<>"",$O8<BZ$5),0,IF($K8="",$E8/$R8*U8,IF(MONTH($K8)=MONTH(BZ$5),$L8/$R8*U8,IF(AND($K8<BZ$5,(MONTH($K8)<>MONTH(BZ$5))),$L8/$R8*U8,$E8/$R8*U8)))))) -> 47.58 | CA8: =+IF(AND($J8>CA$5,MONTH($J8<>CA$5)),0,+IF(AND($J8>CA$5,MONTH($J8=CA$5)),$E8/$R8*DAY($J8),IF(AND($O8<>"",$O8<CA$5),0,IF($K8="",$E8/$R8*V8,IF(MONTH($K8)=MONTH(CA$5),$L8/$R8*V8,IF(AND($K8<CA$5,(MONTH($K8)<>MONTH(CA$5))),$L8/$R8*V8,$E8/$R8*V8)))))) -> 47.58 | CB8: =+IF(AND($J8>CB$5,MONTH($J8<>CB$5)),0,+IF(AND($J8>CB$5,MONTH($J8=CB$5)),$E8/$R8*DAY($J8),IF(AND($O8<>"",$O8<CB$5),0,IF($K8="",$E8/$R8*W8,IF(MONTH($K8)=MONTH(CB$5),$L8/$R8*W8,IF(AND($K8<CB$5,(MONTH($K8)<>MONTH(CB$5))),$L8/$R8*W8,$E8/$R8*W8)))))) -> 47.58 | CC8: =+IF(AND($J8>CC$5,MONTH($J8<>CC$5)),0,+IF(AND($J8>CC$5,MONTH($J8=CC$5)),$E8/$R8*DAY($J8),IF(AND($O8<>"",$O8<CC$5),0,IF($K8="",$E8/$R8*X8,IF(MONTH($K8)=MONTH(CC$5),$L8/$R8*X8,IF(AND($K8<CC$5,(MONTH($K8)<>MONTH(CC$5))),$L8/$R8*X8,$E8/$R8*X8)))))) -> 47.58 | CD8: =+IF(AND($J8>CD$5,MONTH($J8<>CD$5)),0,+IF(AND($J8>CD$5,MONTH($J8=CD$5)),$E8/$R8*DAY($J8),IF(AND($O8<>"",$O8<CD$5),0,IF($K8="",$E8/$R8*Y8,IF(MONTH($K8)=MONTH(CD$5),$L8/$R8*Y8,IF(AND($K8<CD$5,(MONTH($K8)<>MONTH(CD$5))),$L8/$R8*Y8,$E8/$R8*Y8)))))) -> 47.58 | CE8: =+IF(AND($J8>CE$5,MONTH($J8<>CE$5)),0,+IF(AND($J8>CE$5,MONTH($J8=CE$5)),$E8/$R8*DAY($J8),IF(AND($O8<>"",$O8<CE$5),0,IF($K8="",$E8/$R8*Z8,IF(MONTH($K8)=MONTH(CE$5),$L8/$R8*Z8,IF(AND($K8<CE$5,(MONTH($K8)<>MONTH(CE$5))),$L8/$R8*Z8,$E8/$R8*Z8)))))) -> 47.58 | ... CI8: =+IF(AND($J8>CI$5,MONTH($J8<>CI$5)),0,+IF(AND($J8>CI$5,MONTH($J8=CI$5)),$E8/$R8*DAY($J8),IF(AND($O8<>"",$O8<CI$5),0,IF($K8="",$E8/$R8*AD8,IF(MONTH($K8)=MONTH(CI$5),$L8/$R8*AD8,IF(AND($K8<CI$5,(MONTH($K8)<>MONTH(CI$5))),$L8/$R8*AD8,$E8/$R8*AD8)))))) -> 47.58 | CJ8: =SUM(BX8:CI8) -> 634.4 | CK8: =+IF(P8<5,18,IF(AND(P8>=5,P8<10),19,IF(AND(P8>=10,P8<15),20,IF(AND(P8>=15,P8<20),21,0)))) -> 20 | CL8: =+CM8-CJ8 -> 0 | CM8: =IF(L8=0,E8,(L8-E8+E8)) -> 634.4
A9: 03047 | B9: KITENGIE KAPENGA GAUTHIER | C9: Credit Manager | D9: =+VLOOKUP(A9,'[1]BDD-Avk Tx'!B:CE,82,0) -> 620 | E9: 1323 | G9: 42065 | H9: =+IF(YEAR(G9)<YEAR($H$5),$H$4,G9) -> 45647 | I9: =+VLOOKUP(A9,'[1]BDD-Avk Tx'!B:BZ,77,0) -> CDI | J9: =+IF(I9="CDI",H9,H9+0) -> 45647 | P9: =DATEDIF(G9,$AD$6,"m")/12 -> 10.75 | Q9: 38 | R9: =SUM(S9:AD9) -> 20 | S9: =+IF(AND(AND($O9="",$P9>=10,MONTH($G9)=MONTH(S$5))),1.5+2,+IF(AND(AND($O9="",$P9>=5,MONTH($G9)=MONTH(S$5))),1.5+1,+IF(AND(AND($P9=5,$O9="",MONTH($G9)=MONTH(S$5))),1.5,+IF(AND($H9>S$5,MONTH($H9)=MONTH(S$5)),1.5/30*(S$4-DAY($H9)),+IF(AND(MONTH($H9)<MONTH(S$5),$O9=""),1.5,+IF(AND($H9=$S$5,$O9=""),1.5,IF($O9<S$5,0,IF(MONTH($O9)=MONTH(S$5),1.5/30*($O9-S$5),1.5)))))))) -> 1.5 | T9: =+IF(AND(AND($O9="",$P9>=10,MONTH($G9)=MONTH(T$5))),1.5+2,+IF(AND(AND($O9="",$P9>=5,MONTH($G9)=MONTH(T$5))),1.5+1,+IF(AND(AND($P9=5,$O9="",MONTH($G9)=MONTH(T$5))),1.5,+IF(AND($H9>T$5,MONTH($H9)=MONTH(T$5)),1.5/30*(T$4-DAY($H9)),+IF(AND(MONTH($H9)<MONTH(T$5),$O9=""),1.5,+IF(AND($H9=$S$5,$O9=""),1.5,IF($O9<T$5,0,IF(MONTH($O9)=MONTH(T$5),1.5/30*($O9-T$5),1.5)))))))) -> 1.5 | U9: =+IF(AND(AND($O9="",$P9>=10,MONTH($G9)=MONTH(U$5))),1.5+2,+IF(AND(AND($O9="",$P9>=5,MONTH($G9)=MONTH(U$5))),1.5+1,+IF(AND(AND($P9=5,$O9="",MONTH($G9)=MONTH(U$5))),1.5,+IF(AND($H9>U$5,MONTH($H9)=MONTH(U$5)),1.5/30*(U$4-DAY($H9)),+IF(AND(MONTH($H9)<MONTH(U$5),$O9=""),1.5,+IF(AND($H9=$S$5,$O9=""),1.5,IF($O9<U$5,0,IF(MONTH($O9)=MONTH(U$5),1.5/30*($O9-U$5),1.5)))))))) -> 1.5 | V9: =+IF(AND(AND($O9="",$P9>=10,MONTH($G9)=MONTH(V$5))),1.5+2,+IF(AND(AND($O9="",$P9>=5,MONTH($G9)=MONTH(V$5))),1.5+1,+IF(AND(AND($P9=5,$O9="",MONTH($G9)=MONTH(V$5))),1.5,+IF(AND($H9>V$5,MONTH($H9)=MONTH(V$5)),1.5/30*(V$4-DAY($H9)),+IF(AND(MONTH($H9)<MONTH(V$5),$O9=""),1.5,+IF(AND($H9=$S$5,$O9=""),1.5,IF($O9<V$5,0,IF(MONTH($O9)=MONTH(V$5),1.5/30*($O9-V$5),1.5)))))))) -> 3.5 | W9: =+IF(AND(AND($O9="",$P9>=10,MONTH($G9)=MONTH(W$5))),1.5+2,+IF(AND(AND($O9="",$P9>=5,MONTH($G9)=MONTH(W$5))),1.5+1,+IF(AND(AND($P9=5,$O9="",MONTH($G9)=MONTH(W$5))),1.5,+IF(AND($H9>W$5,MONTH($H9)=MONTH(W$5)),1.5/30*(W$4-DAY($H9)),+IF(AND(MONTH($H9)<MONTH(W$5),$O9=""),1.5,+IF(AND($H9=$S$5,$O9=""),1.5,IF($O9<W$5,0,IF(MONTH($O9)=MONTH(W$5),1.5/30*($O9-W$5),1.5)))))))) -> 1.5 | X9: =+IF(AND(AND($O9="",$P9>=10,MONTH($G9)=MONTH(X$5))),1.5+2,+IF(AND(AND($O9="",$P9>=5,MONTH($G9)=MONTH(X$5))),1.5+1,+IF(AND(AND($P9=5,$O9="",MONTH($G9)=MONTH(X$5))),1.5,+IF(AND($H9>X$5,MONTH($H9)=MONTH(X$5)),1.5/30*(X$4-DAY($H9)),+IF(AND(MONTH($H9)<MONTH(X$5),$O9=""),1.5,+IF(AND($H9=$S$5,$O9=""),1.5,IF($O9<X$5,0,IF(MONTH($O9)=MONTH(X$5),1.5/30*($O9-X$5),1.5)))))))) -> 1.5 | Y9: =+IF(AND(AND($O9="",$P9>=10,MONTH($G9)=MONTH(Y$5))),1.5+2,+IF(AND(AND($O9="",$P9>=5,MONTH($G9)=MONTH(Y$5))),1.5+1,+IF(AND(AND($P9=5,$O9="",MONTH($G9)=MONTH(Y$5))),1.5,+IF(AND($H9>Y$5,MONTH($H9)=MONTH(Y$5)),1.5/30*(Y$4-DAY($H9)),+IF(AND(MONTH($H9)<MONTH(Y$5),$O9=""),1.5,+IF(AND($H9=$S$5,$O9=""),1.5,IF($O9<Y$5,0,IF(MONTH($O9)=MONTH(Y$5),1.5/30*($O9-Y$5),1.5)))))))) -> 1.5 | Z9: =+IF(AND(AND($O9="",$P9>=10,MONTH($G9)=MONTH(Z$5))),1.5+2,+IF(AND(AND($O9="",$P9>=5,MONTH($G9)=MONTH(Z$5))),1.5+1,+IF(AND(AND($P9=5,$O9="",MONTH($G9)=MONTH(Z$5))),1.5,+IF(AND($H9>Z$5,MONTH($H9)=MONTH(Z$5)),1.5/30*(Z$4-DAY($H9)),+IF(AND(MONTH($H9)<MONTH(Z$5),$O9=""),1.5,+IF(AND($H9=$S$5,$O9=""),1.5,IF($O9<Z$5,0,IF(MONTH($O9)=MONTH(Z$5),1.5/30*($O9-Z$5),1.5)))))))) -> 1.5 | ... AD9: =+IF(AND(AND($O9="",$P9>=10,MONTH($G9)=MONTH(AD$5))),1.5+2,+IF(AND(AND($O9="",$P9>=5,MONTH($G9)=MONTH(AD$5))),1.5+1,+IF(AND(AND($P9=5,$O9="",MONTH($G9)=MONTH(AD$5))),1.5,+IF(AND($H9>AD$5,MONTH($H9)=MONTH(AD$5)),1.5/30*(AD$4-DAY($H9)),+IF(AND(MONTH($H9)<MONTH(AD$5),$O9=""),1.5,+IF(AND($H9=$S$5,$O9=""),1.5,IF($O9<AD$5,0,IF(MONTH($O9)=MONTH(AD$5),1.5/30*($O9-AD$5),1.5)))))))) -> 1.5 | AF9: =SUM(AG9:AR9) -> 0 | AG9: 0 | AH9: 0 | AI9: 0 | AS9: =+Q9+R9-AF9 -> 58 | AU9: 1933.6154 | AV9: =SUM(AW9:BH9) -> 1017.6923 | AW9: =+IF($K9="",$E9/26*S9,IF(MONTH($K9)=MONTH(AW$5),$L9/26*S9,IF(AND($K9<AW$5,(MONTH($K9)<>MONTH(AW$5))),$L9/26*S9,$E9/26*S9))) -> 76.326923 | AX9: =+IF($K9="",$E9/26*T9,IF(MONTH($K9)=MONTH(AX$5),$L9/26*T9,IF(AND($K9<AX$5,(MONTH($K9)<>MONTH(AX$5))),$L9/26*T9,$E9/26*T9))) -> 76.326923 | AY9: =+IF($K9="",$E9/26*U9,IF(MONTH($K9)=MONTH(AY$5),$L9/26*U9,IF(AND($K9<AY$5,(MONTH($K9)<>MONTH(AY$5))),$L9/26*U9,$E9/26*U9))) -> 76.326923 | AZ9: =+IF($K9="",$E9/26*V9,IF(MONTH($K9)=MONTH(AZ$5),$L9/26*V9,IF(AND($K9<AZ$5,(MONTH($K9)<>MONTH(AZ$5))),$L9/26*V9,$E9/26*V9))) -> 178.09615 | BA9: =+IF($K9="",$E9/26*W9,IF(MONTH($K9)=MONTH(BA$5),$L9/26*W9,IF(AND($K9<BA$5,(MONTH($K9)<>MONTH(BA$5))),$L9/26*W9,$E9/26*W9))) -> 76.326923 | BB9: =+IF($K9="",$E9/26*X9,IF(MONTH($K9)=MONTH(BB$5),$L9/26*X9,IF(AND($K9<BB$5,(MONTH($K9)<>MONTH(BB$5))),$L9/26*X9,$E9/26*X9))) -> 76.326923 | BC9: =+IF($K9="",$E9/26*Y9,IF(MONTH($K9)=MONTH(BC$5),$L9/26*Y9,IF(AND($K9<BC$5,(MONTH($K9)<>MONTH(BC$5))),$L9/26*Y9,$E9/26*Y9))) -> 76.326923 | BD9: =+IF($K9="",$E9/26*Z9,IF(MONTH($K9)=MONTH(BD$5),$L9/26*Z9,IF(AND($K9<BD$5,(MONTH($K9)<>MONTH(BD$5))),$L9/26*Z9,$E9/26*Z9))) -> 76.326923 | ... BH9: =+IF($K9="",$E9/26*AD9,IF(MONTH($K9)=MONTH(BH$5),$L9/26*AD9,IF(AND($K9<BH$5,(MONTH($K9)<>MONTH(BH$5))),$L9/26*AD9,$E9/26*AD9))) -> 76.326923 | BI9: =SUM(BJ9:BU9) -> 0 | BJ9: =(+IF($K9="",$E9/26*AG9,IF(MONTH($K9)=MONTH(BJ$5),$L9/26*AG9,IF(AND($K9<BJ$5,(MONTH($K9)<>MONTH(BJ$5))),$L9/26*AG9,$E9/26*AG9))))*-1 -> 0 | BK9: =(+IF($K9="",$E9/26*AH9,IF(MONTH($K9)=MONTH(BK$5),$L9/26*AH9,IF(AND($K9<BK$5,(MONTH($K9)<>MONTH(BK$5))),$L9/26*AH9,$E9/26*AH9))))*-1 -> 0 | BL9: =(+IF($K9="",$E9/26*AI9,IF(MONTH($K9)=MONTH(BL$5),$L9/26*AI9,IF(AND($K9<BL$5,(MONTH($K9)<>MONTH(BL$5))),$L9/26*AI9,$E9/26*AI9))))*-1 -> 0 | BM9: =(+IF($K9="",$E9/26*AJ9,IF(MONTH($K9)=MONTH(BM$5),$L9/26*AJ9,IF(AND($K9<BM$5,(MONTH($K9)<>MONTH(BM$5))),$L9/26*AJ9,$E9/26*AJ9))))*-1 -> 0 | BN9: =(+IF($K9="",$E9/26*AK9,IF(MONTH($K9)=MONTH(BN$5),$L9/26*AK9,IF(AND($K9<BN$5,(MONTH($K9)<>MONTH(BN$5))),$L9/26*AK9,$E9/26*AK9))))*-1 -> 0 | BO9: =(+IF($K9="",$E9/26*AL9,IF(MONTH($K9)=MONTH(BO$5),$L9/26*AL9,IF(AND($K9<BO$5,(MONTH($K9)<>MONTH(BO$5))),$L9/26*AL9,$E9/26*AL9))))*-1 -> 0 | BP9: =(+IF($K9="",$E9/26*AM9,IF(MONTH($K9)=MONTH(BP$5),$L9/26*AM9,IF(AND($K9<BP$5,(MONTH($K9)<>MONTH(BP$5))),$L9/26*AM9,$E9/26*AM9))))*-1 -> 0 | BQ9: =(+IF($K9="",$E9/26*AN9,IF(MONTH($K9)=MONTH(BQ$5),$L9/26*AN9,IF(AND($K9<BQ$5,(MONTH($K9)<>MONTH(BQ$5))),$L9/26*AN9,$E9/26*AN9))))*-1 -> 0 | ... BU9: =(+IF($K9="",$E9/26*AR9,IF(MONTH($K9)=MONTH(BU$5),$L9/26*AR9,IF(AND($K9<BU$5,(MONTH($K9)<>MONTH(BU$5))),$L9/26*AR9,$E9/26*AR9))))*-1 -> 0 | BV9: =+AU9+AV9+BI9 -> 2951.3077 | BX9: =+IF(AND($J9>BX$5,MONTH($J9<>BX$5)),0,+IF(AND($J9>BX$5,MONTH($J9=BX$5)),$E9/$R9*DAY($J9),IF(AND($O9<>"",$O9<BX$5),0,IF($K9="",$E9/$R9*S9,IF(MONTH($K9)=MONTH(BX$5),$L9/$R9*S9,IF(AND($K9<BX$5,(MONTH($K9)<>MONTH(BX$5))),$L9/$R9*S9,$E9/$R9*S9)))))) -> 99.225 | BY9: =+IF(AND($J9>BY$5,MONTH($J9<>BY$5)),0,+IF(AND($J9>BY$5,MONTH($J9=BY$5)),$E9/$R9*DAY($J9),IF(AND($O9<>"",$O9<BY$5),0,IF($K9="",$E9/$R9*T9,IF(MONTH($K9)=MONTH(BY$5),$L9/$R9*T9,IF(AND($K9<BY$5,(MONTH($K9)<>MONTH(BY$5))),$L9/$R9*T9,$E9/$R9*T9)))))) -> 99.225 | BZ9: =+IF(AND($J9>BZ$5,MONTH($J9<>BZ$5)),0,+IF(AND($J9>BZ$5,MONTH($J9=BZ$5)),$E9/$R9*DAY($J9),IF(AND($O9<>"",$O9<BZ$5),0,IF($K9="",$E9/$R9*U9,IF(MONTH($K9)=MONTH(BZ$5),$L9/$R9*U9,IF(AND($K9<BZ$5,(MONTH($K9)<>MONTH(BZ$5))),$L9/$R9*U9,$E9/$R9*U9)))))) -> 99.225 | CA9: =+IF(AND($J9>CA$5,MONTH($J9<>CA$5)),0,+IF(AND($J9>CA$5,MONTH($J9=CA$5)),$E9/$R9*DAY($J9),IF(AND($O9<>"",$O9<CA$5),0,IF($K9="",$E9/$R9*V9,IF(MONTH($K9)=MONTH(CA$5),$L9/$R9*V9,IF(AND($K9<CA$5,(MONTH($K9)<>MONTH(CA$5))),$L9/$R9*V9,$E9/$R9*V9)))))) -> 231.525 | CB9: =+IF(AND($J9>CB$5,MONTH($J9<>CB$5)),0,+IF(AND($J9>CB$5,MONTH($J9=CB$5)),$E9/$R9*DAY($J9),IF(AND($O9<>"",$O9<CB$5),0,IF($K9="",$E9/$R9*W9,IF(MONTH($K9)=MONTH(CB$5),$L9/$R9*W9,IF(AND($K9<CB$5,(MONTH($K9)<>MONTH(CB$5))),$L9/$R9*W9,$E9/$R9*W9)))))) -> 99.225 | CC9: =+IF(AND($J9>CC$5,MONTH($J9<>CC$5)),0,+IF(AND($J9>CC$5,MONTH($J9=CC$5)),$E9/$R9*DAY($J9),IF(AND($O9<>"",$O9<CC$5),0,IF($K9="",$E9/$R9*X9,IF(MONTH($K9)=MONTH(CC$5),$L9/$R9*X9,IF(AND($K9<CC$5,(MONTH($K9)<>MONTH(CC$5))),$L9/$R9*X9,$E9/$R9*X9)))))) -> 99.225 | CD9: =+IF(AND($J9>CD$5,MONTH($J9<>CD$5)),0,+IF(AND($J9>CD$5,MONTH($J9=CD$5)),$E9/$R9*DAY($J9),IF(AND($O9<>"",$O9<CD$5),0,IF($K9="",$E9/$R9*Y9,IF(MONTH($K9)=MONTH(CD$5),$L9/$R9*Y9,IF(AND($K9<CD$5,(MONTH($K9)<>MONTH(CD$5))),$L9/$R9*Y9,$E9/$R9*Y9)))))) -> 99.225 | CE9: =+IF(AND($J9>CE$5,MONTH($J9<>CE$5)),0,+IF(AND($J9>CE$5,MONTH($J9=CE$5)),$E9/$R9*DAY($J9),IF(AND($O9<>"",$O9<CE$5),0,IF($K9="",$E9/$R9*Z9,IF(MONTH($K9)=MONTH(CE$5),$L9/$R9*Z9,IF(AND($K9<CE$5,(MONTH($K9)<>MONTH(CE$5))),$L9/$R9*Z9,$E9/$R9*Z9)))))) -> 99.225 | ... CI9: =+IF(AND($J9>CI$5,MONTH($J9<>CI$5)),0,+IF(AND($J9>CI$5,MONTH($J9=CI$5)),$E9/$R9*DAY($J9),IF(AND($O9<>"",$O9<CI$5),0,IF($K9="",$E9/$R9*AD9,IF(MONTH($K9)=MONTH(CI$5),$L9/$R9*AD9,IF(AND($K9<CI$5,(MONTH($K9)<>MONTH(CI$5))),$L9/$R9*AD9,$E9/$R9*AD9)))))) -> 99.225 | CJ9: =SUM(BX9:CI9) -> 1323 | CK9: =+IF(P9<5,18,IF(AND(P9>=5,P9<10),19,IF(AND(P9>=10,P9<15),20,IF(AND(P9>=15,P9<20),21,0)))) -> 20 | CL9: =+CM9-CJ9 -> 0 | CM9: =IF(L9=0,E9,(L9-E9+E9)) -> 1323
A10: 04209 | B10: NGANI ANGONO STEPHANIE | C10: Payroll Accountant | D10: =+VLOOKUP(A10,'[1]BDD-Avk Tx'!B:CE,82,0) -> 620 | E10: 1128.4 | G10: 41201 | H10: =+IF(YEAR(G10)<YEAR($H$5),$H$4,G10) -> 45647 | I10: =+VLOOKUP(A10,'[1]BDD-Avk Tx'!B:BZ,77,0) -> CDI | J10: =+IF(I10="CDI",H10,H10+0) -> 45647 | P10: =DATEDIF(G10,$AD$6,"m")/12 -> 13.166667 | Q10: 6 | R10: =SUM(S10:AD10) -> 20 | S10: =+IF(AND(AND($O10="",$P10>=10,MONTH($G10)=MONTH(S$5))),1.5+2,+IF(AND(AND($O10="",$P10>=5,MONTH($G10)=MONTH(S$5))),1.5+1,+IF(AND(AND($P10=5,$O10="",MONTH($G10)=MONTH(S$5))),1.5,+IF(AND($H10>S$5,MONTH($H10)=MONTH(S$5)),1.5/30*(S$4-DAY($H10)),+IF(AND(MONTH($H10)<MONTH(S$5),$O10=""),1.5,+IF(AND($H10=$S$5,$O10=""),1.5,IF($O10<S$5,0,IF(MONTH($O10)=MONTH(S$5),1.5/30*($O10-S$5),1.5)))))))) -> 1.5 | T10: =+IF(AND(AND($O10="",$P10>=10,MONTH($G10)=MONTH(T$5))),1.5+2,+IF(AND(AND($O10="",$P10>=5,MONTH($G10)=MONTH(T$5))),1.5+1,+IF(AND(AND($P10=5,$O10="",MONTH($G10)=MONTH(T$5))),1.5,+IF(AND($H10>T$5,MONTH($H10)=MONTH(T$5)),1.5/30*(T$4-DAY($H10)),+IF(AND(MONTH($H10)<MONTH(T$5),$O10=""),1.5,+IF(AND($H10=$S$5,$O10=""),1.5,IF($O10<T$5,0,IF(MONTH($O10)=MONTH(T$5),1.5/30*($O10-T$5),1.5)))))))) -> 1.5 | U10: =+IF(AND(AND($O10="",$P10>=10,MONTH($G10)=MONTH(U$5))),1.5+2,+IF(AND(AND($O10="",$P10>=5,MONTH($G10)=MONTH(U$5))),1.5+1,+IF(AND(AND($P10=5,$O10="",MONTH($G10)=MONTH(U$5))),1.5,+IF(AND($H10>U$5,MONTH($H10)=MONTH(U$5)),1.5/30*(U$4-DAY($H10)),+IF(AND(MONTH($H10)<MONTH(U$5),$O10=""),1.5,+IF(AND($H10=$S$5,$O10=""),1.5,IF($O10<U$5,0,IF(MONTH($O10)=MONTH(U$5),1.5/30*($O10-U$5),1.5)))))))) -> 1.5 | V10: =+IF(AND(AND($O10="",$P10>=10,MONTH($G10)=MONTH(V$5))),1.5+2,+IF(AND(AND($O10="",$P10>=5,MONTH($G10)=MONTH(V$5))),1.5+1,+IF(AND(AND($P10=5,$O10="",MONTH($G10)=MONTH(V$5))),1.5,+IF(AND($H10>V$5,MONTH($H10)=MONTH(V$5)),1.5/30*(V$4-DAY($H10)),+IF(AND(MONTH($H10)<MONTH(V$5),$O10=""),1.5,+IF(AND($H10=$S$5,$O10=""),1.5,IF($O10<V$5,0,IF(MONTH($O10)=MONTH(V$5),1.5/30*($O10-V$5),1.5)))))))) -> 1.5 | W10: =+IF(AND(AND($O10="",$P10>=10,MONTH($G10)=MONTH(W$5))),1.5+2,+IF(AND(AND($O10="",$P10>=5,MONTH($G10)=MONTH(W$5))),1.5+1,+IF(AND(AND($P10=5,$O10="",MONTH($G10)=MONTH(W$5))),1.5,+IF(AND($H10>W$5,MONTH($H10)=MONTH(W$5)),1.5/30*(W$4-DAY($H10)),+IF(AND(MONTH($H10)<MONTH(W$5),$O10=""),1.5,+IF(AND($H10=$S$5,$O10=""),1.5,IF($O10<W$5,0,IF(MONTH($O10)=MONTH(W$5),1.5/30*($O10-W$5),1.5)))))))) -> 1.5 | X10: =+IF(AND(AND($O10="",$P10>=10,MONTH($G10)=MONTH(X$5))),1.5+2,+IF(AND(AND($O10="",$P10>=5,MONTH($G10)=MONTH(X$5))),1.5+1,+IF(AND(AND($P10=5,$O10="",MONTH($G10)=MONTH(X$5))),1.5,+IF(AND($H10>X$5,MONTH($H10)=MONTH(X$5)),1.5/30*(X$4-DAY($H10)),+IF(AND(MONTH($H10)<MONTH(X$5),$O10=""),1.5,+IF(AND($H10=$S$5,$O10=""),1.5,IF($O10<X$5,0,IF(MONTH($O10)=MONTH(X$5),1.5/30*($O10-X$5),1.5)))))))) -> 1.5 | Y10: =+IF(AND(AND($O10="",$P10>=10,MONTH($G10)=MONTH(Y$5))),1.5+2,+IF(AND(AND($O10="",$P10>=5,MONTH($G10)=MONTH(Y$5))),1.5+1,+IF(AND(AND($P10=5,$O10="",MONTH($G10)=MONTH(Y$5))),1.5,+IF(AND($H10>Y$5,MONTH($H10)=MONTH(Y$5)),1.5/30*(Y$4-DAY($H10)),+IF(AND(MONTH($H10)<MONTH(Y$5),$O10=""),1.5,+IF(AND($H10=$S$5,$O10=""),1.5,IF($O10<Y$5,0,IF(MONTH($O10)=MONTH(Y$5),1.5/30*($O10-Y$5),1.5)))))))) -> 1.5 | Z10: =+IF(AND(AND($O10="",$P10>=10,MONTH($G10)=MONTH(Z$5))),1.5+2,+IF(AND(AND($O10="",$P10>=5,MONTH($G10)=MONTH(Z$5))),1.5+1,+IF(AND(AND($P10=5,$O10="",MONTH($G10)=MONTH(Z$5))),1.5,+IF(AND($H10>Z$5,MONTH($H10)=MONTH(Z$5)),1.5/30*(Z$4-DAY($H10)),+IF(AND(MONTH($H10)<MONTH(Z$5),$O10=""),1.5,+IF(AND($H10=$S$5,$O10=""),1.5,IF($O10<Z$5,0,IF(MONTH($O10)=MONTH(Z$5),1.5/30*($O10-Z$5),1.5)))))))) -> 1.5 | ... AD10: =+IF(AND(AND($O10="",$P10>=10,MONTH($G10)=MONTH(AD$5))),1.5+2,+IF(AND(AND($O10="",$P10>=5,MONTH($G10)=MONTH(AD$5))),1.5+1,+IF(AND(AND($P10=5,$O10="",MONTH($G10)=MONTH(AD$5))),1.5,+IF(AND($H10>AD$5,MONTH($H10)=MONTH(AD$5)),1.5/30*(AD$4-DAY($H10)),+IF(AND(MONTH($H10)<MONTH(AD$5),$O10=""),1.5,+IF(AND($H10=$S$5,$O10=""),1.5,IF($O10<AD$5,0,IF(MONTH($O10)=MONTH(AD$5),1.5/30*($O10-AD$5),1.5)))))))) -> 1.5 | AF10: =SUM(AG10:AR10) -> 5 | AG10: 0 | AH10: 4 | AI10: 1 | AS10: =+Q10+R10-AF10 -> 21 | AU10: 239.92308 | AV10: =SUM(AW10:BH10) -> 868 | AW10: =+IF($K10="",$E10/26*S10,IF(MONTH($K10)=MONTH(AW$5),$L10/26*S10,IF(AND($K10<AW$5,(MONTH($K10)<>MONTH(AW$5))),$L10/26*S10,$E10/26*S10))) -> 65.1 | AX10: =+IF($K10="",$E10/26*T10,IF(MONTH($K10)=MONTH(AX$5),$L10/26*T10,IF(AND($K10<AX$5,(MONTH($K10)<>MONTH(AX$5))),$L10/26*T10,$E10/26*T10))) -> 65.1 | AY10: =+IF($K10="",$E10/26*U10,IF(MONTH($K10)=MONTH(AY$5),$L10/26*U10,IF(AND($K10<AY$5,(MONTH($K10)<>MONTH(AY$5))),$L10/26*U10,$E10/26*U10))) -> 65.1 | AZ10: =+IF($K10="",$E10/26*V10,IF(MONTH($K10)=MONTH(AZ$5),$L10/26*V10,IF(AND($K10<AZ$5,(MONTH($K10)<>MONTH(AZ$5))),$L10/26*V10,$E10/26*V10))) -> 65.1 | BA10: =+IF($K10="",$E10/26*W10,IF(MONTH($K10)=MONTH(BA$5),$L10/26*W10,IF(AND($K10<BA$5,(MONTH($K10)<>MONTH(BA$5))),$L10/26*W10,$E10/26*W10))) -> 65.1 | BB10: =+IF($K10="",$E10/26*X10,IF(MONTH($K10)=MONTH(BB$5),$L10/26*X10,IF(AND($K10<BB$5,(MONTH($K10)<>MONTH(BB$5))),$L10/26*X10,$E10/26*X10))) -> 65.1 | BC10: =+IF($K10="",$E10/26*Y10,IF(MONTH($K10)=MONTH(BC$5),$L10/26*Y10,IF(AND($K10<BC$5,(MONTH($K10)<>MONTH(BC$5))),$L10/26*Y10,$E10/26*Y10))) -> 65.1 | BD10: =+IF($K10="",$E10/26*Z10,IF(MONTH($K10)=MONTH(BD$5),$L10/26*Z10,IF(AND($K10<BD$5,(MONTH($K10)<>MONTH(BD$5))),$L10/26*Z10,$E10/26*Z10))) -> 65.1 | ... BH10: =+IF($K10="",$E10/26*AD10,IF(MONTH($K10)=MONTH(BH$5),$L10/26*AD10,IF(AND($K10<BH$5,(MONTH($K10)<>MONTH(BH$5))),$L10/26*AD10,$E10/26*AD10))) -> 65.1 | BI10: =SUM(BJ10:BU10) -> -217 | BJ10: =(+IF($K10="",$E10/26*AG10,IF(MONTH($K10)=MONTH(BJ$5),$L10/26*AG10,IF(AND($K10<BJ$5,(MONTH($K10)<>MONTH(BJ$5))),$L10/26*AG10,$E10/26*AG10))))*-1 -> 0 | BK10: =(+IF($K10="",$E10/26*AH10,IF(MONTH($K10)=MONTH(BK$5),$L10/26*AH10,IF(AND($K10<BK$5,(MONTH($K10)<>MONTH(BK$5))),$L10/26*AH10,$E10/26*AH10))))*-1 -> -173.6 | BL10: =(+IF($K10="",$E10/26*AI10,IF(MONTH($K10)=MONTH(BL$5),$L10/26*AI10,IF(AND($K10<BL$5,(MONTH($K10)<>MONTH(BL$5))),$L10/26*AI10,$E10/26*AI10))))*-1 -> -43.4 | BM10: =(+IF($K10="",$E10/26*AJ10,IF(MONTH($K10)=MONTH(BM$5),$L10/26*AJ10,IF(AND($K10<BM$5,(MONTH($K10)<>MONTH(BM$5))),$L10/26*AJ10,$E10/26*AJ10))))*-1 -> 0 | BN10: =(+IF($K10="",$E10/26*AK10,IF(MONTH($K10)=MONTH(BN$5),$L10/26*AK10,IF(AND($K10<BN$5,(MONTH($K10)<>MONTH(BN$5))),$L10/26*AK10,$E10/26*AK10))))*-1 -> 0 | BO10: =(+IF($K10="",$E10/26*AL10,IF(MONTH($K10)=MONTH(BO$5),$L10/26*AL10,IF(AND($K10<BO$5,(MONTH($K10)<>MONTH(BO$5))),$L10/26*AL10,$E10/26*AL10))))*-1 -> 0 | BP10: =(+IF($K10="",$E10/26*AM10,IF(MONTH($K10)=MONTH(BP$5),$L10/26*AM10,IF(AND($K10<BP$5,(MONTH($K10)<>MONTH(BP$5))),$L10/26*AM10,$E10/26*AM10))))*-1 -> 0 | BQ10: =(+IF($K10="",$E10/26*AN10,IF(MONTH($K10)=MONTH(BQ$5),$L10/26*AN10,IF(AND($K10<BQ$5,(MONTH($K10)<>MONTH(BQ$5))),$L10/26*AN10,$E10/26*AN10))))*-1 -> 0 | ... BU10: =(+IF($K10="",$E10/26*AR10,IF(MONTH($K10)=MONTH(BU$5),$L10/26*AR10,IF(AND($K10<BU$5,(MONTH($K10)<>MONTH(BU$5))),$L10/26*AR10,$E10/26*AR10))))*-1 -> 0 | BV10: =+AU10+AV10+BI10 -> 890.92308 | BX10: =+IF(AND($J10>BX$5,MONTH($J10<>BX$5)),0,+IF(AND($J10>BX$5,MONTH($J10=BX$5)),$E10/$R10*DAY($J10),IF(AND($O10<>"",$O10<BX$5),0,IF($K10="",$E10/$R10*S10,IF(MONTH($K10)=MONTH(BX$5),$L10/$R10*S10,IF(AND($K10<BX$5,(MONTH($K10)<>MONTH(BX$5))),$L10/$R10*S10,$E10/$R10*S10)))))) -> 84.63 | BY10: =+IF(AND($J10>BY$5,MONTH($J10<>BY$5)),0,+IF(AND($J10>BY$5,MONTH($J10=BY$5)),$E10/$R10*DAY($J10),IF(AND($O10<>"",$O10<BY$5),0,IF($K10="",$E10/$R10*T10,IF(MONTH($K10)=MONTH(BY$5),$L10/$R10*T10,IF(AND($K10<BY$5,(MONTH($K10)<>MONTH(BY$5))),$L10/$R10*T10,$E10/$R10*T10)))))) -> 84.63 | BZ10: =+IF(AND($J10>BZ$5,MONTH($J10<>BZ$5)),0,+IF(AND($J10>BZ$5,MONTH($J10=BZ$5)),$E10/$R10*DAY($J10),IF(AND($O10<>"",$O10<BZ$5),0,IF($K10="",$E10/$R10*U10,IF(MONTH($K10)=MONTH(BZ$5),$L10/$R10*U10,IF(AND($K10<BZ$5,(MONTH($K10)<>MONTH(BZ$5))),$L10/$R10*U10,$E10/$R10*U10)))))) -> 84.63 | CA10: =+IF(AND($J10>CA$5,MONTH($J10<>CA$5)),0,+IF(AND($J10>CA$5,MONTH($J10=CA$5)),$E10/$R10*DAY($J10),IF(AND($O10<>"",$O10<CA$5),0,IF($K10="",$E10/$R10*V10,IF(MONTH($K10)=MONTH(CA$5),$L10/$R10*V10,IF(AND($K10<CA$5,(MONTH($K10)<>MONTH(CA$5))),$L10/$R10*V10,$E10/$R10*V10)))))) -> 84.63 | CB10: =+IF(AND($J10>CB$5,MONTH($J10<>CB$5)),0,+IF(AND($J10>CB$5,MONTH($J10=CB$5)),$E10/$R10*DAY($J10),IF(AND($O10<>"",$O10<CB$5),0,IF($K10="",$E10/$R10*W10,IF(MONTH($K10)=MONTH(CB$5),$L10/$R10*W10,IF(AND($K10<CB$5,(MONTH($K10)<>MONTH(CB$5))),$L10/$R10*W10,$E10/$R10*W10)))))) -> 84.63 | CC10: =+IF(AND($J10>CC$5,MONTH($J10<>CC$5)),0,+IF(AND($J10>CC$5,MONTH($J10=CC$5)),$E10/$R10*DAY($J10),IF(AND($O10<>"",$O10<CC$5),0,IF($K10="",$E10/$R10*X10,IF(MONTH($K10)=MONTH(CC$5),$L10/$R10*X10,IF(AND($K10<CC$5,(MONTH($K10)<>MONTH(CC$5))),$L10/$R10*X10,$E10/$R10*X10)))))) -> 84.63 | CD10: =+IF(AND($J10>CD$5,MONTH($J10<>CD$5)),0,+IF(AND($J10>CD$5,MONTH($J10=CD$5)),$E10/$R10*DAY($J10),IF(AND($O10<>"",$O10<CD$5),0,IF($K10="",$E10/$R10*Y10,IF(MONTH($K10)=MONTH(CD$5),$L10/$R10*Y10,IF(AND($K10<CD$5,(MONTH($K10)<>MONTH(CD$5))),$L10/$R10*Y10,$E10/$R10*Y10)))))) -> 84.63 | CE10: =+IF(AND($J10>CE$5,MONTH($J10<>CE$5)),0,+IF(AND($J10>CE$5,MONTH($J10=CE$5)),$E10/$R10*DAY($J10),IF(AND($O10<>"",$O10<CE$5),0,IF($K10="",$E10/$R10*Z10,IF(MONTH($K10)=MONTH(CE$5),$L10/$R10*Z10,IF(AND($K10<CE$5,(MONTH($K10)<>MONTH(CE$5))),$L10/$R10*Z10,$E10/$R10*Z10)))))) -> 84.63 | ... CI10: =+IF(AND($J10>CI$5,MONTH($J10<>CI$5)),0,+IF(AND($J10>CI$5,MONTH($J10=CI$5)),$E10/$R10*DAY($J10),IF(AND($O10<>"",$O10<CI$5),0,IF($K10="",$E10/$R10*AD10,IF(MONTH($K10)=MONTH(CI$5),$L10/$R10*AD10,IF(AND($K10<CI$5,(MONTH($K10)<>MONTH(CI$5))),$L10/$R10*AD10,$E10/$R10*AD10)))))) -> 84.63 | CJ10: =SUM(BX10:CI10) -> 1128.4 | CK10: =+IF(P10<5,18,IF(AND(P10>=5,P10<10),19,IF(AND(P10>=10,P10<15),20,IF(AND(P10>=15,P10<20),21,0)))) -> 20 | CL10: =+CM10-CJ10 -> 0 | CM10: =IF(L10=0,E10,(L10-E10+E10)) -> 1128.4
A11: 04019 | B11: MAKUNTIMA MAMBUENE COUCOU | C11: Concierge Supervisor | D11: =+VLOOKUP(A11,'[1]BDD-Avk Tx'!B:CE,82,0) -> 120 | E11: 231.4 | G11: 41153 | H11: =+IF(YEAR(G11)<YEAR($H$5),$H$4,G11) -> 45647 | I11: =+VLOOKUP(A11,'[1]BDD-Avk Tx'!B:BZ,77,0) -> CDI | J11: =+IF(I11="CDI",H11,H11+0) -> 45647 | P11: =DATEDIF(G11,$AD$6,"m")/12 -> 13.25 | Q11: 13 | R11: =SUM(S11:AD11) -> 20 | S11: =+IF(AND(AND($O11="",$P11>=10,MONTH($G11)=MONTH(S$5))),1.5+2,+IF(AND(AND($O11="",$P11>=5,MONTH($G11)=MONTH(S$5))),1.5+1,+IF(AND(AND($P11=5,$O11="",MONTH($G11)=MONTH(S$5))),1.5,+IF(AND($H11>S$5,MONTH($H11)=MONTH(S$5)),1.5/30*(S$4-DAY($H11)),+IF(AND(MONTH($H11)<MONTH(S$5),$O11=""),1.5,+IF(AND($H11=$S$5,$O11=""),1.5,IF($O11<S$5,0,IF(MONTH($O11)=MONTH(S$5),1.5/30*($O11-S$5),1.5)))))))) -> 1.5 | T11: =+IF(AND(AND($O11="",$P11>=10,MONTH($G11)=MONTH(T$5))),1.5+2,+IF(AND(AND($O11="",$P11>=5,MONTH($G11)=MONTH(T$5))),1.5+1,+IF(AND(AND($P11=5,$O11="",MONTH($G11)=MONTH(T$5))),1.5,+IF(AND($H11>T$5,MONTH($H11)=MONTH(T$5)),1.5/30*(T$4-DAY($H11)),+IF(AND(MONTH($H11)<MONTH(T$5),$O11=""),1.5,+IF(AND($H11=$S$5,$O11=""),1.5,IF($O11<T$5,0,IF(MONTH($O11)=MONTH(T$5),1.5/30*($O11-T$5),1.5)))))))) -> 1.5 | U11: =+IF(AND(AND($O11="",$P11>=10,MONTH($G11)=MONTH(U$5))),1.5+2,+IF(AND(AND($O11="",$P11>=5,MONTH($G11)=MONTH(U$5))),1.5+1,+IF(AND(AND($P11=5,$O11="",MONTH($G11)=MONTH(U$5))),1.5,+IF(AND($H11>U$5,MONTH($H11)=MONTH(U$5)),1.5/30*(U$4-DAY($H11)),+IF(AND(MONTH($H11)<MONTH(U$5),$O11=""),1.5,+IF(AND($H11=$S$5,$O11=""),1.5,IF($O11<U$5,0,IF(MONTH($O11)=MONTH(U$5),1.5/30*($O11-U$5),1.5)))))))) -> 1.5 | V11: =+IF(AND(AND($O11="",$P11>=10,MONTH($G11)=MONTH(V$5))),1.5+2,+IF(AND(AND($O11="",$P11>=5,MONTH($G11)=MONTH(V$5))),1.5+1,+IF(AND(AND($P11=5,$O11="",MONTH($G11)=MONTH(V$5))),1.5,+IF(AND($H11>V$5,MONTH($H11)=MONTH(V$5)),1.5/30*(V$4-DAY($H11)),+IF(AND(MONTH($H11)<MONTH(V$5),$O11=""),1.5,+IF(AND($H11=$S$5,$O11=""),1.5,IF($O11<V$5,0,IF(MONTH($O11)=MONTH(V$5),1.5/30*($O11-V$5),1.5)))))))) -> 1.5 | W11: =+IF(AND(AND($O11="",$P11>=10,MONTH($G11)=MONTH(W$5))),1.5+2,+IF(AND(AND($O11="",$P11>=5,MONTH($G11)=MONTH(W$5))),1.5+1,+IF(AND(AND($P11=5,$O11="",MONTH($G11)=MONTH(W$5))),1.5,+IF(AND($H11>W$5,MONTH($H11)=MONTH(W$5)),1.5/30*(W$4-DAY($H11)),+IF(AND(MONTH($H11)<MONTH(W$5),$O11=""),1.5,+IF(AND($H11=$S$5,$O11=""),1.5,IF($O11<W$5,0,IF(MONTH($O11)=MONTH(W$5),1.5/30*($O11-W$5),1.5)))))))) -> 1.5 | X11: =+IF(AND(AND($O11="",$P11>=10,MONTH($G11)=MONTH(X$5))),1.5+2,+IF(AND(AND($O11="",$P11>=5,MONTH($G11)=MONTH(X$5))),1.5+1,+IF(AND(AND($P11=5,$O11="",MONTH($G11)=MONTH(X$5))),1.5,+IF(AND($H11>X$5,MONTH($H11)=MONTH(X$5)),1.5/30*(X$4-DAY($H11)),+IF(AND(MONTH($H11)<MONTH(X$5),$O11=""),1.5,+IF(AND($H11=$S$5,$O11=""),1.5,IF($O11<X$5,0,IF(MONTH($O11)=MONTH(X$5),1.5/30*($O11-X$5),1.5)))))))) -> 1.5 | Y11: =+IF(AND(AND($O11="",$P11>=10,MONTH($G11)=MONTH(Y$5))),1.5+2,+IF(AND(AND($O11="",$P11>=5,MONTH($G11)=MONTH(Y$5))),1.5+1,+IF(AND(AND($P11=5,$O11="",MONTH($G11)=MONTH(Y$5))),1.5,+IF(AND($H11>Y$5,MONTH($H11)=MONTH(Y$5)),1.5/30*(Y$4-DAY($H11)),+IF(AND(MONTH($H11)<MONTH(Y$5),$O11=""),1.5,+IF(AND($H11=$S$5,$O11=""),1.5,IF($O11<Y$5,0,IF(MONTH($O11)=MONTH(Y$5),1.5/30*($O11-Y$5),1.5)))))))) -> 1.5 | Z11: =+IF(AND(AND($O11="",$P11>=10,MONTH($G11)=MONTH(Z$5))),1.5+2,+IF(AND(AND($O11="",$P11>=5,MONTH($G11)=MONTH(Z$5))),1.5+1,+IF(AND(AND($P11=5,$O11="",MONTH($G11)=MONTH(Z$5))),1.5,+IF(AND($H11>Z$5,MONTH($H11)=MONTH(Z$5)),1.5/30*(Z$4-DAY($H11)),+IF(AND(MONTH($H11)<MONTH(Z$5),$O11=""),1.5,+IF(AND($H11=$S$5,$O11=""),1.5,IF($O11<Z$5,0,IF(MONTH($O11)=MONTH(Z$5),1.5/30*($O11-Z$5),1.5)))))))) -> 1.5 | ... AD11: =+IF(AND(AND($O11="",$P11>=10,MONTH($G11)=MONTH(AD$5))),1.5+2,+IF(AND(AND($O11="",$P11>=5,MONTH($G11)=MONTH(AD$5))),1.5+1,+IF(AND(AND($P11=5,$O11="",MONTH($G11)=MONTH(AD$5))),1.5,+IF(AND($H11>AD$5,MONTH($H11)=MONTH(AD$5)),1.5/30*(AD$4-DAY($H11)),+IF(AND(MONTH($H11)<MONTH(AD$5),$O11=""),1.5,+IF(AND($H11=$S$5,$O11=""),1.5,IF($O11<AD$5,0,IF(MONTH($O11)=MONTH(AD$5),1.5/30*($O11-AD$5),1.5)))))))) -> 1.5 | AF11: =SUM(AG11:AR11) -> 14 | AG11: 0 | AH11: 0 | AI11: 14 | AS11: =+Q11+R11-AF11 -> 19 | AU11: 110.59231 | AV11: =SUM(AW11:BH11) -> 178 | AW11: =+IF($K11="",$E11/26*S11,IF(MONTH($K11)=MONTH(AW$5),$L11/26*S11,IF(AND($K11<AW$5,(MONTH($K11)<>MONTH(AW$5))),$L11/26*S11,$E11/26*S11))) -> 13.35 | AX11: =+IF($K11="",$E11/26*T11,IF(MONTH($K11)=MONTH(AX$5),$L11/26*T11,IF(AND($K11<AX$5,(MONTH($K11)<>MONTH(AX$5))),$L11/26*T11,$E11/26*T11))) -> 13.35 | AY11: =+IF($K11="",$E11/26*U11,IF(MONTH($K11)=MONTH(AY$5),$L11/26*U11,IF(AND($K11<AY$5,(MONTH($K11)<>MONTH(AY$5))),$L11/26*U11,$E11/26*U11))) -> 13.35 | AZ11: =+IF($K11="",$E11/26*V11,IF(MONTH($K11)=MONTH(AZ$5),$L11/26*V11,IF(AND($K11<AZ$5,(MONTH($K11)<>MONTH(AZ$5))),$L11/26*V11,$E11/26*V11))) -> 13.35 | BA11: =+IF($K11="",$E11/26*W11,IF(MONTH($K11)=MONTH(BA$5),$L11/26*W11,IF(AND($K11<BA$5,(MONTH($K11)<>MONTH(BA$5))),$L11/26*W11,$E11/26*W11))) -> 13.35 | BB11: =+IF($K11="",$E11/26*X11,IF(MONTH($K11)=MONTH(BB$5),$L11/26*X11,IF(AND($K11<BB$5,(MONTH($K11)<>MONTH(BB$5))),$L11/26*X11,$E11/26*X11))) -> 13.35 | BC11: =+IF($K11="",$E11/26*Y11,IF(MONTH($K11)=MONTH(BC$5),$L11/26*Y11,IF(AND($K11<BC$5,(MONTH($K11)<>MONTH(BC$5))),$L11/26*Y11,$E11/26*Y11))) -> 13.35 | BD11: =+IF($K11="",$E11/26*Z11,IF(MONTH($K11)=MONTH(BD$5),$L11/26*Z11,IF(AND($K11<BD$5,(MONTH($K11)<>MONTH(BD$5))),$L11/26*Z11,$E11/26*Z11))) -> 13.35 | ... BH11: =+IF($K11="",$E11/26*AD11,IF(MONTH($K11)=MONTH(BH$5),$L11/26*AD11,IF(AND($K11<BH$5,(MONTH($K11)<>MONTH(BH$5))),$L11/26*AD11,$E11/26*AD11))) -> 13.35 | BI11: =SUM(BJ11:BU11) -> -124.6 | BJ11: =(+IF($K11="",$E11/26*AG11,IF(MONTH($K11)=MONTH(BJ$5),$L11/26*AG11,IF(AND($K11<BJ$5,(MONTH($K11)<>MONTH(BJ$5))),$L11/26*AG11,$E11/26*AG11))))*-1 -> 0 | BK11: =(+IF($K11="",$E11/26*AH11,IF(MONTH($K11)=MONTH(BK$5),$L11/26*AH11,IF(AND($K11<BK$5,(MONTH($K11)<>MONTH(BK$5))),$L11/26*AH11,$E11/26*AH11))))*-1 -> 0 | BL11: =(+IF($K11="",$E11/26*AI11,IF(MONTH($K11)=MONTH(BL$5),$L11/26*AI11,IF(AND($K11<BL$5,(MONTH($K11)<>MONTH(BL$5))),$L11/26*AI11,$E11/26*AI11))))*-1 -> -124.6 | BM11: =(+IF($K11="",$E11/26*AJ11,IF(MONTH($K11)=MONTH(BM$5),$L11/26*AJ11,IF(AND($K11<BM$5,(MONTH($K11)<>MONTH(BM$5))),$L11/26*AJ11,$E11/26*AJ11))))*-1 -> 0 | BN11: =(+IF($K11="",$E11/26*AK11,IF(MONTH($K11)=MONTH(BN$5),$L11/26*AK11,IF(AND($K11<BN$5,(MONTH($K11)<>MONTH(BN$5))),$L11/26*AK11,$E11/26*AK11))))*-1 -> 0 | BO11: =(+IF($K11="",$E11/26*AL11,IF(MONTH($K11)=MONTH(BO$5),$L11/26*AL11,IF(AND($K11<BO$5,(MONTH($K11)<>MONTH(BO$5))),$L11/26*AL11,$E11/26*AL11))))*-1 -> 0 | BP11: =(+IF($K11="",$E11/26*AM11,IF(MONTH($K11)=MONTH(BP$5),$L11/26*AM11,IF(AND($K11<BP$5,(MONTH($K11)<>MONTH(BP$5))),$L11/26*AM11,$E11/26*AM11))))*-1 -> 0 | BQ11: =(+IF($K11="",$E11/26*AN11,IF(MONTH($K11)=MONTH(BQ$5),$L11/26*AN11,IF(AND($K11<BQ$5,(MONTH($K11)<>MONTH(BQ$5))),$L11/26*AN11,$E11/26*AN11))))*-1 -> 0 | ... BU11: =(+IF($K11="",$E11/26*AR11,IF(MONTH($K11)=MONTH(BU$5),$L11/26*AR11,IF(AND($K11<BU$5,(MONTH($K11)<>MONTH(BU$5))),$L11/26*AR11,$E11/26*AR11))))*-1 -> 0 | BV11: =+AU11+AV11+BI11 -> 163.99231 | BX11: =+IF(AND($J11>BX$5,MONTH($J11<>BX$5)),0,+IF(AND($J11>BX$5,MONTH($J11=BX$5)),$E11/$R11*DAY($J11),IF(AND($O11<>"",$O11<BX$5),0,IF($K11="",$E11/$R11*S11,IF(MONTH($K11)=MONTH(BX$5),$L11/$R11*S11,IF(AND($K11<BX$5,(MONTH($K11)<>MONTH(BX$5))),$L11/$R11*S11,$E11/$R11*S11)))))) -> 17.355 | BY11: =+IF(AND($J11>BY$5,MONTH($J11<>BY$5)),0,+IF(AND($J11>BY$5,MONTH($J11=BY$5)),$E11/$R11*DAY($J11),IF(AND($O11<>"",$O11<BY$5),0,IF($K11="",$E11/$R11*T11,IF(MONTH($K11)=MONTH(BY$5),$L11/$R11*T11,IF(AND($K11<BY$5,(MONTH($K11)<>MONTH(BY$5))),$L11/$R11*T11,$E11/$R11*T11)))))) -> 17.355 | BZ11: =+IF(AND($J11>BZ$5,MONTH($J11<>BZ$5)),0,+IF(AND($J11>BZ$5,MONTH($J11=BZ$5)),$E11/$R11*DAY($J11),IF(AND($O11<>"",$O11<BZ$5),0,IF($K11="",$E11/$R11*U11,IF(MONTH($K11)=MONTH(BZ$5),$L11/$R11*U11,IF(AND($K11<BZ$5,(MONTH($K11)<>MONTH(BZ$5))),$L11/$R11*U11,$E11/$R11*U11)))))) -> 17.355 | CA11: =+IF(AND($J11>CA$5,MONTH($J11<>CA$5)),0,+IF(AND($J11>CA$5,MONTH($J11=CA$5)),$E11/$R11*DAY($J11),IF(AND($O11<>"",$O11<CA$5),0,IF($K11="",$E11/$R11*V11,IF(MONTH($K11)=MONTH(CA$5),$L11/$R11*V11,IF(AND($K11<CA$5,(MONTH($K11)<>MONTH(CA$5))),$L11/$R11*V11,$E11/$R11*V11)))))) -> 17.355 | CB11: =+IF(AND($J11>CB$5,MONTH($J11<>CB$5)),0,+IF(AND($J11>CB$5,MONTH($J11=CB$5)),$E11/$R11*DAY($J11),IF(AND($O11<>"",$O11<CB$5),0,IF($K11="",$E11/$R11*W11,IF(MONTH($K11)=MONTH(CB$5),$L11/$R11*W11,IF(AND($K11<CB$5,(MONTH($K11)<>MONTH(CB$5))),$L11/$R11*W11,$E11/$R11*W11)))))) -> 17.355 | CC11: =+IF(AND($J11>CC$5,MONTH($J11<>CC$5)),0,+IF(AND($J11>CC$5,MONTH($J11=CC$5)),$E11/$R11*DAY($J11),IF(AND($O11<>"",$O11<CC$5),0,IF($K11="",$E11/$R11*X11,IF(MONTH($K11)=MONTH(CC$5),$L11/$R11*X11,IF(AND($K11<CC$5,(MONTH($K11)<>MONTH(CC$5))),$L11/$R11*X11,$E11/$R11*X11)))))) -> 17.355 | CD11: =+IF(AND($J11>CD$5,MONTH($J11<>CD$5)),0,+IF(AND($J11>CD$5,MONTH($J11=CD$5)),$E11/$R11*DAY($J11),IF(AND($O11<>"",$O11<CD$5),0,IF($K11="",$E11/$R11*Y11,IF(MONTH($K11)=MONTH(CD$5),$L11/$R11*Y11,IF(AND($K11<CD$5,(MONTH($K11)<>MONTH(CD$5))),$L11/$R11*Y11,$E11/$R11*Y11)))))) -> 17.355 | CE11: =+IF(AND($J11>CE$5,MONTH($J11<>CE$5)),0,+IF(AND($J11>CE$5,MONTH($J11=CE$5)),$E11/$R11*DAY($J11),IF(AND($O11<>"",$O11<CE$5),0,IF($K11="",$E11/$R11*Z11,IF(MONTH($K11)=MONTH(CE$5),$L11/$R11*Z11,IF(AND($K11<CE$5,(MONTH($K11)<>MONTH(CE$5))),$L11/$R11*Z11,$E11/$R11*Z11)))))) -> 17.355 | ... CI11: =+IF(AND($J11>CI$5,MONTH($J11<>CI$5)),0,+IF(AND($J11>CI$5,MONTH($J11=CI$5)),$E11/$R11*DAY($J11),IF(AND($O11<>"",$O11<CI$5),0,IF($K11="",$E11/$R11*AD11,IF(MONTH($K11)=MONTH(CI$5),$L11/$R11*AD11,IF(AND($K11<CI$5,(MONTH($K11)<>MONTH(CI$5))),$L11/$R11*AD11,$E11/$R11*AD11)))))) -> 17.355 | CJ11: =SUM(BX11:CI11) -> 231.4 | CK11: =+IF(P11<5,18,IF(AND(P11>=5,P11<10),19,IF(AND(P11>=10,P11<15),20,IF(AND(P11>=15,P11<20),21,0)))) -> 20 | CL11: =+CM11-CJ11 -> 0 | CM11: =IF(L11=0,E11,(L11-E11+E11)) -> 231.4
A12: 04020 | B12: NSUMBU KAYEMBE GIRESSE | C12: Receptionist | D12: =+VLOOKUP(A12,'[1]BDD-Avk Tx'!B:CE,82,0) -> 120 | E12: 231.4 | G12: 41153 | H12: =+IF(YEAR(G12)<YEAR($H$5),$H$4,G12) -> 45647 | I12: =+VLOOKUP(A12,'[1]BDD-Avk Tx'!B:BZ,77,0) -> CDI | J12: =+IF(I12="CDI",H12,H12+0) -> 45647 | P12: =DATEDIF(G12,$AD$6,"m")/12 -> 13.25 | Q12: 13 | R12: =SUM(S12:AD12) -> 20 | S12: =+IF(AND(AND($O12="",$P12>=10,MONTH($G12)=MONTH(S$5))),1.5+2,+IF(AND(AND($O12="",$P12>=5,MONTH($G12)=MONTH(S$5))),1.5+1,+IF(AND(AND($P12=5,$O12="",MONTH($G12)=MONTH(S$5))),1.5,+IF(AND($H12>S$5,MONTH($H12)=MONTH(S$5)),1.5/30*(S$4-DAY($H12)),+IF(AND(MONTH($H12)<MONTH(S$5),$O12=""),1.5,+IF(AND($H12=$S$5,$O12=""),1.5,IF($O12<S$5,0,IF(MONTH($O12)=MONTH(S$5),1.5/30*($O12-S$5),1.5)))))))) -> 1.5 | T12: =+IF(AND(AND($O12="",$P12>=10,MONTH($G12)=MONTH(T$5))),1.5+2,+IF(AND(AND($O12="",$P12>=5,MONTH($G12)=MONTH(T$5))),1.5+1,+IF(AND(AND($P12=5,$O12="",MONTH($G12)=MONTH(T$5))),1.5,+IF(AND($H12>T$5,MONTH($H12)=MONTH(T$5)),1.5/30*(T$4-DAY($H12)),+IF(AND(MONTH($H12)<MONTH(T$5),$O12=""),1.5,+IF(AND($H12=$S$5,$O12=""),1.5,IF($O12<T$5,0,IF(MONTH($O12)=MONTH(T$5),1.5/30*($O12-T$5),1.5)))))))) -> 1.5 | U12: =+IF(AND(AND($O12="",$P12>=10,MONTH($G12)=MONTH(U$5))),1.5+2,+IF(AND(AND($O12="",$P12>=5,MONTH($G12)=MONTH(U$5))),1.5+1,+IF(AND(AND($P12=5,$O12="",MONTH($G12)=MONTH(U$5))),1.5,+IF(AND($H12>U$5,MONTH($H12)=MONTH(U$5)),1.5/30*(U$4-DAY($H12)),+IF(AND(MONTH($H12)<MONTH(U$5),$O12=""),1.5,+IF(AND($H12=$S$5,$O12=""),1.5,IF($O12<U$5,0,IF(MONTH($O12)=MONTH(U$5),1.5/30*($O12-U$5),1.5)))))))) -> 1.5 | V12: =+IF(AND(AND($O12="",$P12>=10,MONTH($G12)=MONTH(V$5))),1.5+2,+IF(AND(AND($O12="",$P12>=5,MONTH($G12)=MONTH(V$5))),1.5+1,+IF(AND(AND($P12=5,$O12="",MONTH($G12)=MONTH(V$5))),1.5,+IF(AND($H12>V$5,MONTH($H12)=MONTH(V$5)),1.5/30*(V$4-DAY($H12)),+IF(AND(MONTH($H12)<MONTH(V$5),$O12=""),1.5,+IF(AND($H12=$S$5,$O12=""),1.5,IF($O12<V$5,0,IF(MONTH($O12)=MONTH(V$5),1.5/30*($O12-V$5),1.5)))))))) -> 1.5 | W12: =+IF(AND(AND($O12="",$P12>=10,MONTH($G12)=MONTH(W$5))),1.5+2,+IF(AND(AND($O12="",$P12>=5,MONTH($G12)=MONTH(W$5))),1.5+1,+IF(AND(AND($P12=5,$O12="",MONTH($G12)=MONTH(W$5))),1.5,+IF(AND($H12>W$5,MONTH($H12)=MONTH(W$5)),1.5/30*(W$4-DAY($H12)),+IF(AND(MONTH($H12)<MONTH(W$5),$O12=""),1.5,+IF(AND($H12=$S$5,$O12=""),1.5,IF($O12<W$5,0,IF(MONTH($O12)=MONTH(W$5),1.5/30*($O12-W$5),1.5)))))))) -> 1.5 | X12: =+IF(AND(AND($O12="",$P12>=10,MONTH($G12)=MONTH(X$5))),1.5+2,+IF(AND(AND($O12="",$P12>=5,MONTH($G12)=MONTH(X$5))),1.5+1,+IF(AND(AND($P12=5,$O12="",MONTH($G12)=MONTH(X$5))),1.5,+IF(AND($H12>X$5,MONTH($H12)=MONTH(X$5)),1.5/30*(X$4-DAY($H12)),+IF(AND(MONTH($H12)<MONTH(X$5),$O12=""),1.5,+IF(AND($H12=$S$5,$O12=""),1.5,IF($O12<X$5,0,IF(MONTH($O12)=MONTH(X$5),1.5/30*($O12-X$5),1.5)))))))) -> 1.5 | Y12: =+IF(AND(AND($O12="",$P12>=10,MONTH($G12)=MONTH(Y$5))),1.5+2,+IF(AND(AND($O12="",$P12>=5,MONTH($G12)=MONTH(Y$5))),1.5+1,+IF(AND(AND($P12=5,$O12="",MONTH($G12)=MONTH(Y$5))),1.5,+IF(AND($H12>Y$5,MONTH($H12)=MONTH(Y$5)),1.5/30*(Y$4-DAY($H12)),+IF(AND(MONTH($H12)<MONTH(Y$5),$O12=""),1.5,+IF(AND($H12=$S$5,$O12=""),1.5,IF($O12<Y$5,0,IF(MONTH($O12)=MONTH(Y$5),1.5/30*($O12-Y$5),1.5)))))))) -> 1.5 | Z12: =+IF(AND(AND($O12="",$P12>=10,MONTH($G12)=MONTH(Z$5))),1.5+2,+IF(AND(AND($O12="",$P12>=5,MONTH($G12)=MONTH(Z$5))),1.5+1,+IF(AND(AND($P12=5,$O12="",MONTH($G12)=MONTH(Z$5))),1.5,+IF(AND($H12>Z$5,MONTH($H12)=MONTH(Z$5)),1.5/30*(Z$4-DAY($H12)),+IF(AND(MONTH($H12)<MONTH(Z$5),$O12=""),1.5,+IF(AND($H12=$S$5,$O12=""),1.5,IF($O12<Z$5,0,IF(MONTH($O12)=MONTH(Z$5),1.5/30*($O12-Z$5),1.5)))))))) -> 1.5 | ... AD12: =+IF(AND(AND($O12="",$P12>=10,MONTH($G12)=MONTH(AD$5))),1.5+2,+IF(AND(AND($O12="",$P12>=5,MONTH($G12)=MONTH(AD$5))),1.5+1,+IF(AND(AND($P12=5,$O12="",MONTH($G12)=MONTH(AD$5))),1.5,+IF(AND($H12>AD$5,MONTH($H12)=MONTH(AD$5)),1.5/30*(AD$4-DAY($H12)),+IF(AND(MONTH($H12)<MONTH(AD$5),$O12=""),1.5,+IF(AND($H12=$S$5,$O12=""),1.5,IF($O12<AD$5,0,IF(MONTH($O12)=MONTH(AD$5),1.5/30*($O12-AD$5),1.5)))))))) -> 1.5 | AF12: =SUM(AG12:AR12) -> 7 | AG12: 7 | AH12: 0 | AI12: 0 | AS12: =+Q12+R12-AF12 -> 26 | AU12: 87.453846 | AV12: =SUM(AW12:BH12) -> 178 | AW12: =+IF($K12="",$E12/26*S12,IF(MONTH($K12)=MONTH(AW$5),$L12/26*S12,IF(AND($K12<AW$5,(MONTH($K12)<>MONTH(AW$5))),$L12/26*S12,$E12/26*S12))) -> 13.35 | AX12: =+IF($K12="",$E12/26*T12,IF(MONTH($K12)=MONTH(AX$5),$L12/26*T12,IF(AND($K12<AX$5,(MONTH($K12)<>MONTH(AX$5))),$L12/26*T12,$E12/26*T12))) -> 13.35 | AY12: =+IF($K12="",$E12/26*U12,IF(MONTH($K12)=MONTH(AY$5),$L12/26*U12,IF(AND($K12<AY$5,(MONTH($K12)<>MONTH(AY$5))),$L12/26*U12,$E12/26*U12))) -> 13.35 | AZ12: =+IF($K12="",$E12/26*V12,IF(MONTH($K12)=MONTH(AZ$5),$L12/26*V12,IF(AND($K12<AZ$5,(MONTH($K12)<>MONTH(AZ$5))),$L12/26*V12,$E12/26*V12))) -> 13.35 | BA12: =+IF($K12="",$E12/26*W12,IF(MONTH($K12)=MONTH(BA$5),$L12/26*W12,IF(AND($K12<BA$5,(MONTH($K12)<>MONTH(BA$5))),$L12/26*W12,$E12/26*W12))) -> 13.35 | BB12: =+IF($K12="",$E12/26*X12,IF(MONTH($K12)=MONTH(BB$5),$L12/26*X12,IF(AND($K12<BB$5,(MONTH($K12)<>MONTH(BB$5))),$L12/26*X12,$E12/26*X12))) -> 13.35 | BC12: =+IF($K12="",$E12/26*Y12,IF(MONTH($K12)=MONTH(BC$5),$L12/26*Y12,IF(AND($K12<BC$5,(MONTH($K12)<>MONTH(BC$5))),$L12/26*Y12,$E12/26*Y12))) -> 13.35 | BD12: =+IF($K12="",$E12/26*Z12,IF(MONTH($K12)=MONTH(BD$5),$L12/26*Z12,IF(AND($K12<BD$5,(MONTH($K12)<>MONTH(BD$5))),$L12/26*Z12,$E12/26*Z12))) -> 13.35 | ... BH12: =+IF($K12="",$E12/26*AD12,IF(MONTH($K12)=MONTH(BH$5),$L12/26*AD12,IF(AND($K12<BH$5,(MONTH($K12)<>MONTH(BH$5))),$L12/26*AD12,$E12/26*AD12))) -> 13.35 | BI12: =SUM(BJ12:BU12) -> -62.3 | BJ12: =(+IF($K12="",$E12/26*AG12,IF(MONTH($K12)=MONTH(BJ$5),$L12/26*AG12,IF(AND($K12<BJ$5,(MONTH($K12)<>MONTH(BJ$5))),$L12/26*AG12,$E12/26*AG12))))*-1 -> -62.3 | BK12: =(+IF($K12="",$E12/26*AH12,IF(MONTH($K12)=MONTH(BK$5),$L12/26*AH12,IF(AND($K12<BK$5,(MONTH($K12)<>MONTH(BK$5))),$L12/26*AH12,$E12/26*AH12))))*-1 -> 0 | BL12: =(+IF($K12="",$E12/26*AI12,IF(MONTH($K12)=MONTH(BL$5),$L12/26*AI12,IF(AND($K12<BL$5,(MONTH($K12)<>MONTH(BL$5))),$L12/26*AI12,$E12/26*AI12))))*-1 -> 0 | BM12: =(+IF($K12="",$E12/26*AJ12,IF(MONTH($K12)=MONTH(BM$5),$L12/26*AJ12,IF(AND($K12<BM$5,(MONTH($K12)<>MONTH(BM$5))),$L12/26*AJ12,$E12/26*AJ12))))*-1 -> 0 | BN12: =(+IF($K12="",$E12/26*AK12,IF(MONTH($K12)=MONTH(BN$5),$L12/26*AK12,IF(AND($K12<BN$5,(MONTH($K12)<>MONTH(BN$5))),$L12/26*AK12,$E12/26*AK12))))*-1 -> 0 | BO12: =(+IF($K12="",$E12/26*AL12,IF(MONTH($K12)=MONTH(BO$5),$L12/26*AL12,IF(AND($K12<BO$5,(MONTH($K12)<>MONTH(BO$5))),$L12/26*AL12,$E12/26*AL12))))*-1 -> 0 | BP12: =(+IF($K12="",$E12/26*AM12,IF(MONTH($K12)=MONTH(BP$5),$L12/26*AM12,IF(AND($K12<BP$5,(MONTH($K12)<>MONTH(BP$5))),$L12/26*AM12,$E12/26*AM12))))*-1 -> 0 | BQ12: =(+IF($K12="",$E12/26*AN12,IF(MONTH($K12)=MONTH(BQ$5),$L12/26*AN12,IF(AND($K12<BQ$5,(MONTH($K12)<>MONTH(BQ$5))),$L12/26*AN12,$E12/26*AN12))))*-1 -> 0 | ... BU12: =(+IF($K12="",$E12/26*AR12,IF(MONTH($K12)=MONTH(BU$5),$L12/26*AR12,IF(AND($K12<BU$5,(MONTH($K12)<>MONTH(BU$5))),$L12/26*AR12,$E12/26*AR12))))*-1 -> 0 | BV12: =+AU12+AV12+BI12 -> 203.15385 | BX12: =+IF(AND($J12>BX$5,MONTH($J12<>BX$5)),0,+IF(AND($J12>BX$5,MONTH($J12=BX$5)),$E12/$R12*DAY($J12),IF(AND($O12<>"",$O12<BX$5),0,IF($K12="",$E12/$R12*S12,IF(MONTH($K12)=MONTH(BX$5),$L12/$R12*S12,IF(AND($K12<BX$5,(MONTH($K12)<>MONTH(BX$5))),$L12/$R12*S12,$E12/$R12*S12)))))) -> 17.355 | BY12: =+IF(AND($J12>BY$5,MONTH($J12<>BY$5)),0,+IF(AND($J12>BY$5,MONTH($J12=BY$5)),$E12/$R12*DAY($J12),IF(AND($O12<>"",$O12<BY$5),0,IF($K12="",$E12/$R12*T12,IF(MONTH($K12)=MONTH(BY$5),$L12/$R12*T12,IF(AND($K12<BY$5,(MONTH($K12)<>MONTH(BY$5))),$L12/$R12*T12,$E12/$R12*T12)))))) -> 17.355 | BZ12: =+IF(AND($J12>BZ$5,MONTH($J12<>BZ$5)),0,+IF(AND($J12>BZ$5,MONTH($J12=BZ$5)),$E12/$R12*DAY($J12),IF(AND($O12<>"",$O12<BZ$5),0,IF($K12="",$E12/$R12*U12,IF(MONTH($K12)=MONTH(BZ$5),$L12/$R12*U12,IF(AND($K12<BZ$5,(MONTH($K12)<>MONTH(BZ$5))),$L12/$R12*U12,$E12/$R12*U12)))))) -> 17.355 | CA12: =+IF(AND($J12>CA$5,MONTH($J12<>CA$5)),0,+IF(AND($J12>CA$5,MONTH($J12=CA$5)),$E12/$R12*DAY($J12),IF(AND($O12<>"",$O12<CA$5),0,IF($K12="",$E12/$R12*V12,IF(MONTH($K12)=MONTH(CA$5),$L12/$R12*V12,IF(AND($K12<CA$5,(MONTH($K12)<>MONTH(CA$5))),$L12/$R12*V12,$E12/$R12*V12)))))) -> 17.355 | CB12: =+IF(AND($J12>CB$5,MONTH($J12<>CB$5)),0,+IF(AND($J12>CB$5,MONTH($J12=CB$5)),$E12/$R12*DAY($J12),IF(AND($O12<>"",$O12<CB$5),0,IF($K12="",$E12/$R12*W12,IF(MONTH($K12)=MONTH(CB$5),$L12/$R12*W12,IF(AND($K12<CB$5,(MONTH($K12)<>MONTH(CB$5))),$L12/$R12*W12,$E12/$R12*W12)))))) -> 17.355 | CC12: =+IF(AND($J12>CC$5,MONTH($J12<>CC$5)),0,+IF(AND($J12>CC$5,MONTH($J12=CC$5)),$E12/$R12*DAY($J12),IF(AND($O12<>"",$O12<CC$5),0,IF($K12="",$E12/$R12*X12,IF(MONTH($K12)=MONTH(CC$5),$L12/$R12*X12,IF(AND($K12<CC$5,(MONTH($K12)<>MONTH(CC$5))),$L12/$R12*X12,$E12/$R12*X12)))))) -> 17.355 | CD12: =+IF(AND($J12>CD$5,MONTH($J12<>CD$5)),0,+IF(AND($J12>CD$5,MONTH($J12=CD$5)),$E12/$R12*DAY($J12),IF(AND($O12<>"",$O12<CD$5),0,IF($K12="",$E12/$R12*Y12,IF(MONTH($K12)=MONTH(CD$5),$L12/$R12*Y12,IF(AND($K12<CD$5,(MONTH($K12)<>MONTH(CD$5))),$L12/$R12*Y12,$E12/$R12*Y12)))))) -> 17.355 | CE12: =+IF(AND($J12>CE$5,MONTH($J12<>CE$5)),0,+IF(AND($J12>CE$5,MONTH($J12=CE$5)),$E12/$R12*DAY($J12),IF(AND($O12<>"",$O12<CE$5),0,IF($K12="",$E12/$R12*Z12,IF(MONTH($K12)=MONTH(CE$5),$L12/$R12*Z12,IF(AND($K12<CE$5,(MONTH($K12)<>MONTH(CE$5))),$L12/$R12*Z12,$E12/$R12*Z12)))))) -> 17.355 | ... CI12: =+IF(AND($J12>CI$5,MONTH($J12<>CI$5)),0,+IF(AND($J12>CI$5,MONTH($J12=CI$5)),$E12/$R12*DAY($J12),IF(AND($O12<>"",$O12<CI$5),0,IF($K12="",$E12/$R12*AD12,IF(MONTH($K12)=MONTH(CI$5),$L12/$R12*AD12,IF(AND($K12<CI$5,(MONTH($K12)<>MONTH(CI$5))),$L12/$R12*AD12,$E12/$R12*AD12)))))) -> 17.355 | CJ12: =SUM(BX12:CI12) -> 231.4 | CK12: =+IF(P12<5,18,IF(AND(P12>=5,P12<10),19,IF(AND(P12>=10,P12<15),20,IF(AND(P12>=15,P12<20),21,0)))) -> 20 | CL12: =+CM12-CJ12 -> 0 | CM12: =IF(L12=0,E12,(L12-E12+E12)) -> 231.4
A13: 04035 | B13: TSHIMANGA MUKADI DIDIER | C13: Assistant Front Office Manager | D13: =+VLOOKUP(A13,'[1]BDD-Avk Tx'!B:CE,82,0) -> 120 | E13: 733.2 | G13: 41153 | H13: =+IF(YEAR(G13)<YEAR($H$5),$H$4,G13) -> 45647 | I13: =+VLOOKUP(A13,'[1]BDD-Avk Tx'!B:BZ,77,0) -> CDI | J13: =+IF(I13="CDI",H13,H13+0) -> 45647 | P13: =DATEDIF(G13,$AD$6,"m")/12 -> 13.25 | Q13: 4 | R13: =SUM(S13:AD13) -> 20 | S13: =+IF(AND(AND($O13="",$P13>=10,MONTH($G13)=MONTH(S$5))),1.5+2,+IF(AND(AND($O13="",$P13>=5,MONTH($G13)=MONTH(S$5))),1.5+1,+IF(AND(AND($P13=5,$O13="",MONTH($G13)=MONTH(S$5))),1.5,+IF(AND($H13>S$5,MONTH($H13)=MONTH(S$5)),1.5/30*(S$4-DAY($H13)),+IF(AND(MONTH($H13)<MONTH(S$5),$O13=""),1.5,+IF(AND($H13=$S$5,$O13=""),1.5,IF($O13<S$5,0,IF(MONTH($O13)=MONTH(S$5),1.5/30*($O13-S$5),1.5)))))))) -> 1.5 | T13: =+IF(AND(AND($O13="",$P13>=10,MONTH($G13)=MONTH(T$5))),1.5+2,+IF(AND(AND($O13="",$P13>=5,MONTH($G13)=MONTH(T$5))),1.5+1,+IF(AND(AND($P13=5,$O13="",MONTH($G13)=MONTH(T$5))),1.5,+IF(AND($H13>T$5,MONTH($H13)=MONTH(T$5)),1.5/30*(T$4-DAY($H13)),+IF(AND(MONTH($H13)<MONTH(T$5),$O13=""),1.5,+IF(AND($H13=$S$5,$O13=""),1.5,IF($O13<T$5,0,IF(MONTH($O13)=MONTH(T$5),1.5/30*($O13-T$5),1.5)))))))) -> 1.5 | U13: =+IF(AND(AND($O13="",$P13>=10,MONTH($G13)=MONTH(U$5))),1.5+2,+IF(AND(AND($O13="",$P13>=5,MONTH($G13)=MONTH(U$5))),1.5+1,+IF(AND(AND($P13=5,$O13="",MONTH($G13)=MONTH(U$5))),1.5,+IF(AND($H13>U$5,MONTH($H13)=MONTH(U$5)),1.5/30*(U$4-DAY($H13)),+IF(AND(MONTH($H13)<MONTH(U$5),$O13=""),1.5,+IF(AND($H13=$S$5,$O13=""),1.5,IF($O13<U$5,0,IF(MONTH($O13)=MONTH(U$5),1.5/30*($O13-U$5),1.5)))))))) -> 1.5 | V13: =+IF(AND(AND($O13="",$P13>=10,MONTH($G13)=MONTH(V$5))),1.5+2,+IF(AND(AND($O13="",$P13>=5,MONTH($G13)=MONTH(V$5))),1.5+1,+IF(AND(AND($P13=5,$O13="",MONTH($G13)=MONTH(V$5))),1.5,+IF(AND($H13>V$5,MONTH($H13)=MONTH(V$5)),1.5/30*(V$4-DAY($H13)),+IF(AND(MONTH($H13)<MONTH(V$5),$O13=""),1.5,+IF(AND($H13=$S$5,$O13=""),1.5,IF($O13<V$5,0,IF(MONTH($O13)=MONTH(V$5),1.5/30*($O13-V$5),1.5)))))))) -> 1.5 | W13: =+IF(AND(AND($O13="",$P13>=10,MONTH($G13)=MONTH(W$5))),1.5+2,+IF(AND(AND($O13="",$P13>=5,MONTH($G13)=MONTH(W$5))),1.5+1,+IF(AND(AND($P13=5,$O13="",MONTH($G13)=MONTH(W$5))),1.5,+IF(AND($H13>W$5,MONTH($H13)=MONTH(W$5)),1.5/30*(W$4-DAY($H13)),+IF(AND(MONTH($H13)<MONTH(W$5),$O13=""),1.5,+IF(AND($H13=$S$5,$O13=""),1.5,IF($O13<W$5,0,IF(MONTH($O13)=MONTH(W$5),1.5/30*($O13-W$5),1.5)))))))) -> 1.5 | X13: =+IF(AND(AND($O13="",$P13>=10,MONTH($G13)=MONTH(X$5))),1.5+2,+IF(AND(AND($O13="",$P13>=5,MONTH($G13)=MONTH(X$5))),1.5+1,+IF(AND(AND($P13=5,$O13="",MONTH($G13)=MONTH(X$5))),1.5,+IF(AND($H13>X$5,MONTH($H13)=MONTH(X$5)),1.5/30*(X$4-DAY($H13)),+IF(AND(MONTH($H13)<MONTH(X$5),$O13=""),1.5,+IF(AND($H13=$S$5,$O13=""),1.5,IF($O13<X$5,0,IF(MONTH($O13)=MONTH(X$5),1.5/30*($O13-X$5),1.5)))))))) -> 1.5 | Y13: =+IF(AND(AND($O13="",$P13>=10,MONTH($G13)=MONTH(Y$5))),1.5+2,+IF(AND(AND($O13="",$P13>=5,MONTH($G13)=MONTH(Y$5))),1.5+1,+IF(AND(AND($P13=5,$O13="",MONTH($G13)=MONTH(Y$5))),1.5,+IF(AND($H13>Y$5,MONTH($H13)=MONTH(Y$5)),1.5/30*(Y$4-DAY($H13)),+IF(AND(MONTH($H13)<MONTH(Y$5),$O13=""),1.5,+IF(AND($H13=$S$5,$O13=""),1.5,IF($O13<Y$5,0,IF(MONTH($O13)=MONTH(Y$5),1.5/30*($O13-Y$5),1.5)))))))) -> 1.5 | Z13: =+IF(AND(AND($O13="",$P13>=10,MONTH($G13)=MONTH(Z$5))),1.5+2,+IF(AND(AND($O13="",$P13>=5,MONTH($G13)=MONTH(Z$5))),1.5+1,+IF(AND(AND($P13=5,$O13="",MONTH($G13)=MONTH(Z$5))),1.5,+IF(AND($H13>Z$5,MONTH($H13)=MONTH(Z$5)),1.5/30*(Z$4-DAY($H13)),+IF(AND(MONTH($H13)<MONTH(Z$5),$O13=""),1.5,+IF(AND($H13=$S$5,$O13=""),1.5,IF($O13<Z$5,0,IF(MONTH($O13)=MONTH(Z$5),1.5/30*($O13-Z$5),1.5)))))))) -> 1.5 | ... AD13: =+IF(AND(AND($O13="",$P13>=10,MONTH($G13)=MONTH(AD$5))),1.5+2,+IF(AND(AND($O13="",$P13>=5,MONTH($G13)=MONTH(AD$5))),1.5+1,+IF(AND(AND($P13=5,$O13="",MONTH($G13)=MONTH(AD$5))),1.5,+IF(AND($H13>AD$5,MONTH($H13)=MONTH(AD$5)),1.5/30*(AD$4-DAY($H13)),+IF(AND(MONTH($H13)<MONTH(AD$5),$O13=""),1.5,+IF(AND($H13=$S$5,$O13=""),1.5,IF($O13<AD$5,0,IF(MONTH($O13)=MONTH(AD$5),1.5/30*($O13-AD$5),1.5)))))))) -> 1.5 | AF13: =SUM(AG13:AR13) -> 0 | AG13: 0 | AH13: 0 | AI13: 0 | AS13: =+Q13+R13-AF13 -> 24 | AU13: 103.86154 | AV13: =SUM(AW13:BH13) -> 564 | AW13: =+IF($K13="",$E13/26*S13,IF(MONTH($K13)=MONTH(AW$5),$L13/26*S13,IF(AND($K13<AW$5,(MONTH($K13)<>MONTH(AW$5))),$L13/26*S13,$E13/26*S13))) -> 42.3 | AX13: =+IF($K13="",$E13/26*T13,IF(MONTH($K13)=MONTH(AX$5),$L13/26*T13,IF(AND($K13<AX$5,(MONTH($K13)<>MONTH(AX$5))),$L13/26*T13,$E13/26*T13))) -> 42.3 | AY13: =+IF($K13="",$E13/26*U13,IF(MONTH($K13)=MONTH(AY$5),$L13/26*U13,IF(AND($K13<AY$5,(MONTH($K13)<>MONTH(AY$5))),$L13/26*U13,$E13/26*U13))) -> 42.3 | AZ13: =+IF($K13="",$E13/26*V13,IF(MONTH($K13)=MONTH(AZ$5),$L13/26*V13,IF(AND($K13<AZ$5,(MONTH($K13)<>MONTH(AZ$5))),$L13/26*V13,$E13/26*V13))) -> 42.3 | BA13: =+IF($K13="",$E13/26*W13,IF(MONTH($K13)=MONTH(BA$5),$L13/26*W13,IF(AND($K13<BA$5,(MONTH($K13)<>MONTH(BA$5))),$L13/26*W13,$E13/26*W13))) -> 42.3 | BB13: =+IF($K13="",$E13/26*X13,IF(MONTH($K13)=MONTH(BB$5),$L13/26*X13,IF(AND($K13<BB$5,(MONTH($K13)<>MONTH(BB$5))),$L13/26*X13,$E13/26*X13))) -> 42.3 | BC13: =+IF($K13="",$E13/26*Y13,IF(MONTH($K13)=MONTH(BC$5),$L13/26*Y13,IF(AND($K13<BC$5,(MONTH($K13)<>MONTH(BC$5))),$L13/26*Y13,$E13/26*Y13))) -> 42.3 | BD13: =+IF($K13="",$E13/26*Z13,IF(MONTH($K13)=MONTH(BD$5),$L13/26*Z13,IF(AND($K13<BD$5,(MONTH($K13)<>MONTH(BD$5))),$L13/26*Z13,$E13/26*Z13))) -> 42.3 | ... BH13: =+IF($K13="",$E13/26*AD13,IF(MONTH($K13)=MONTH(BH$5),$L13/26*AD13,IF(AND($K13<BH$5,(MONTH($K13)<>MONTH(BH$5))),$L13/26*AD13,$E13/26*AD13))) -> 42.3 | BI13: =SUM(BJ13:BU13) -> 0 | BJ13: =(+IF($K13="",$E13/26*AG13,IF(MONTH($K13)=MONTH(BJ$5),$L13/26*AG13,IF(AND($K13<BJ$5,(MONTH($K13)<>MONTH(BJ$5))),$L13/26*AG13,$E13/26*AG13))))*-1 -> 0 | BK13: =(+IF($K13="",$E13/26*AH13,IF(MONTH($K13)=MONTH(BK$5),$L13/26*AH13,IF(AND($K13<BK$5,(MONTH($K13)<>MONTH(BK$5))),$L13/26*AH13,$E13/26*AH13))))*-1 -> 0 | BL13: =(+IF($K13="",$E13/26*AI13,IF(MONTH($K13)=MONTH(BL$5),$L13/26*AI13,IF(AND($K13<BL$5,(MONTH($K13)<>MONTH(BL$5))),$L13/26*AI13,$E13/26*AI13))))*-1 -> 0 | BM13: =(+IF($K13="",$E13/26*AJ13,IF(MONTH($K13)=MONTH(BM$5),$L13/26*AJ13,IF(AND($K13<BM$5,(MONTH($K13)<>MONTH(BM$5))),$L13/26*AJ13,$E13/26*AJ13))))*-1 -> 0 | BN13: =(+IF($K13="",$E13/26*AK13,IF(MONTH($K13)=MONTH(BN$5),$L13/26*AK13,IF(AND($K13<BN$5,(MONTH($K13)<>MONTH(BN$5))),$L13/26*AK13,$E13/26*AK13))))*-1 -> 0 | BO13: =(+IF($K13="",$E13/26*AL13,IF(MONTH($K13)=MONTH(BO$5),$L13/26*AL13,IF(AND($K13<BO$5,(MONTH($K13)<>MONTH(BO$5))),$L13/26*AL13,$E13/26*AL13))))*-1 -> 0 | BP13: =(+IF($K13="",$E13/26*AM13,IF(MONTH($K13)=MONTH(BP$5),$L13/26*AM13,IF(AND($K13<BP$5,(MONTH($K13)<>MONTH(BP$5))),$L13/26*AM13,$E13/26*AM13))))*-1 -> 0 | BQ13: =(+IF($K13="",$E13/26*AN13,IF(MONTH($K13)=MONTH(BQ$5),$L13/26*AN13,IF(AND($K13<BQ$5,(MONTH($K13)<>MONTH(BQ$5))),$L13/26*AN13,$E13/26*AN13))))*-1 -> 0 | ... BU13: =(+IF($K13="",$E13/26*AR13,IF(MONTH($K13)=MONTH(BU$5),$L13/26*AR13,IF(AND($K13<BU$5,(MONTH($K13)<>MONTH(BU$5))),$L13/26*AR13,$E13/26*AR13))))*-1 -> 0 | BV13: =+AU13+AV13+BI13 -> 667.86154 | BX13: =+IF(AND($J13>BX$5,MONTH($J13<>BX$5)),0,+IF(AND($J13>BX$5,MONTH($J13=BX$5)),$E13/$R13*DAY($J13),IF(AND($O13<>"",$O13<BX$5),0,IF($K13="",$E13/$R13*S13,IF(MONTH($K13)=MONTH(BX$5),$L13/$R13*S13,IF(AND($K13<BX$5,(MONTH($K13)<>MONTH(BX$5))),$L13/$R13*S13,$E13/$R13*S13)))))) -> 54.99 | BY13: =+IF(AND($J13>BY$5,MONTH($J13<>BY$5)),0,+IF(AND($J13>BY$5,MONTH($J13=BY$5)),$E13/$R13*DAY($J13),IF(AND($O13<>"",$O13<BY$5),0,IF($K13="",$E13/$R13*T13,IF(MONTH($K13)=MONTH(BY$5),$L13/$R13*T13,IF(AND($K13<BY$5,(MONTH($K13)<>MONTH(BY$5))),$L13/$R13*T13,$E13/$R13*T13)))))) -> 54.99 | BZ13: =+IF(AND($J13>BZ$5,MONTH($J13<>BZ$5)),0,+IF(AND($J13>BZ$5,MONTH($J13=BZ$5)),$E13/$R13*DAY($J13),IF(AND($O13<>"",$O13<BZ$5),0,IF($K13="",$E13/$R13*U13,IF(MONTH($K13)=MONTH(BZ$5),$L13/$R13*U13,IF(AND($K13<BZ$5,(MONTH($K13)<>MONTH(BZ$5))),$L13/$R13*U13,$E13/$R13*U13)))))) -> 54.99 | CA13: =+IF(AND($J13>CA$5,MONTH($J13<>CA$5)),0,+IF(AND($J13>CA$5,MONTH($J13=CA$5)),$E13/$R13*DAY($J13),IF(AND($O13<>"",$O13<CA$5),0,IF($K13="",$E13/$R13*V13,IF(MONTH($K13)=MONTH(CA$5),$L13/$R13*V13,IF(AND($K13<CA$5,(MONTH($K13)<>MONTH(CA$5))),$L13/$R13*V13,$E13/$R13*V13)))))) -> 54.99 | CB13: =+IF(AND($J13>CB$5,MONTH($J13<>CB$5)),0,+IF(AND($J13>CB$5,MONTH($J13=CB$5)),$E13/$R13*DAY($J13),IF(AND($O13<>"",$O13<CB$5),0,IF($K13="",$E13/$R13*W13,IF(MONTH($K13)=MONTH(CB$5),$L13/$R13*W13,IF(AND($K13<CB$5,(MONTH($K13)<>MONTH(CB$5))),$L13/$R13*W13,$E13/$R13*W13)))))) -> 54.99 | CC13: =+IF(AND($J13>CC$5,MONTH($J13<>CC$5)),0,+IF(AND($J13>CC$5,MONTH($J13=CC$5)),$E13/$R13*DAY($J13),IF(AND($O13<>"",$O13<CC$5),0,IF($K13="",$E13/$R13*X13,IF(MONTH($K13)=MONTH(CC$5),$L13/$R13*X13,IF(AND($K13<CC$5,(MONTH($K13)<>MONTH(CC$5))),$L13/$R13*X13,$E13/$R13*X13)))))) -> 54.99 | CD13: =+IF(AND($J13>CD$5,MONTH($J13<>CD$5)),0,+IF(AND($J13>CD$5,MONTH($J13=CD$5)),$E13/$R13*DAY($J13),IF(AND($O13<>"",$O13<CD$5),0,IF($K13="",$E13/$R13*Y13,IF(MONTH($K13)=MONTH(CD$5),$L13/$R13*Y13,IF(AND($K13<CD$5,(MONTH($K13)<>MONTH(CD$5))),$L13/$R13*Y13,$E13/$R13*Y13)))))) -> 54.99 | CE13: =+IF(AND($J13>CE$5,MONTH($J13<>CE$5)),0,+IF(AND($J13>CE$5,MONTH($J13=CE$5)),$E13/$R13*DAY($J13),IF(AND($O13<>"",$O13<CE$5),0,IF($K13="",$E13/$R13*Z13,IF(MONTH($K13)=MONTH(CE$5),$L13/$R13*Z13,IF(AND($K13<CE$5,(MONTH($K13)<>MONTH(CE$5))),$L13/$R13*Z13,$E13/$R13*Z13)))))) -> 54.99 | ... CI13: =+IF(AND($J13>CI$5,MONTH($J13<>CI$5)),0,+IF(AND($J13>CI$5,MONTH($J13=CI$5)),$E13/$R13*DAY($J13),IF(AND($O13<>"",$O13<CI$5),0,IF($K13="",$E13/$R13*AD13,IF(MONTH($K13)=MONTH(CI$5),$L13/$R13*AD13,IF(AND($K13<CI$5,(MONTH($K13)<>MONTH(CI$5))),$L13/$R13*AD13,$E13/$R13*AD13)))))) -> 54.99 | CJ13: =SUM(BX13:CI13) -> 733.2 | CK13: =+IF(P13<5,18,IF(AND(P13>=5,P13<10),19,IF(AND(P13>=10,P13<15),20,IF(AND(P13>=15,P13<20),21,0)))) -> 20 | CL13: =+CM13-CJ13 -> 0 | CM13: =IF(L13=0,E13,(L13-E13+E13)) -> 733.2
A14: 04151 | B14: MUNTUNU KILUMU DESCARTES | C14: Night Shift Supervisor | D14: =+VLOOKUP(A14,'[1]BDD-Avk Tx'!B:CE,82,0) -> 120 | E14: 356.2 | G14: 41153 | H14: =+IF(YEAR(G14)<YEAR($H$5),$H$4,G14) -> 45647 | I14: =+VLOOKUP(A14,'[1]BDD-Avk Tx'!B:BZ,77,0) -> CDI | J14: =+IF(I14="CDI",H14,H14+0) -> 45647 | P14: =DATEDIF(G14,$AD$6,"m")/12 -> 13.25 | Q14: 3 | R14: =SUM(S14:AD14) -> 20 | S14: =+IF(AND(AND($O14="",$P14>=10,MONTH($G14)=MONTH(S$5))),1.5+2,+IF(AND(AND($O14="",$P14>=5,MONTH($G14)=MONTH(S$5))),1.5+1,+IF(AND(AND($P14=5,$O14="",MONTH($G14)=MONTH(S$5))),1.5,+IF(AND($H14>S$5,MONTH($H14)=MONTH(S$5)),1.5/30*(S$4-DAY($H14)),+IF(AND(MONTH($H14)<MONTH(S$5),$O14=""),1.5,+IF(AND($H14=$S$5,$O14=""),1.5,IF($O14<S$5,0,IF(MONTH($O14)=MONTH(S$5),1.5/30*($O14-S$5),1.5)))))))) -> 1.5 | T14: =+IF(AND(AND($O14="",$P14>=10,MONTH($G14)=MONTH(T$5))),1.5+2,+IF(AND(AND($O14="",$P14>=5,MONTH($G14)=MONTH(T$5))),1.5+1,+IF(AND(AND($P14=5,$O14="",MONTH($G14)=MONTH(T$5))),1.5,+IF(AND($H14>T$5,MONTH($H14)=MONTH(T$5)),1.5/30*(T$4-DAY($H14)),+IF(AND(MONTH($H14)<MONTH(T$5),$O14=""),1.5,+IF(AND($H14=$S$5,$O14=""),1.5,IF($O14<T$5,0,IF(MONTH($O14)=MONTH(T$5),1.5/30*($O14-T$5),1.5)))))))) -> 1.5 | U14: =+IF(AND(AND($O14="",$P14>=10,MONTH($G14)=MONTH(U$5))),1.5+2,+IF(AND(AND($O14="",$P14>=5,MONTH($G14)=MONTH(U$5))),1.5+1,+IF(AND(AND($P14=5,$O14="",MONTH($G14)=MONTH(U$5))),1.5,+IF(AND($H14>U$5,MONTH($H14)=MONTH(U$5)),1.5/30*(U$4-DAY($H14)),+IF(AND(MONTH($H14)<MONTH(U$5),$O14=""),1.5,+IF(AND($H14=$S$5,$O14=""),1.5,IF($O14<U$5,0,IF(MONTH($O14)=MONTH(U$5),1.5/30*($O14-U$5),1.5)))))))) -> 1.5 | V14: =+IF(AND(AND($O14="",$P14>=10,MONTH($G14)=MONTH(V$5))),1.5+2,+IF(AND(AND($O14="",$P14>=5,MONTH($G14)=MONTH(V$5))),1.5+1,+IF(AND(AND($P14=5,$O14="",MONTH($G14)=MONTH(V$5))),1.5,+IF(AND($H14>V$5,MONTH($H14)=MONTH(V$5)),1.5/30*(V$4-DAY($H14)),+IF(AND(MONTH($H14)<MONTH(V$5),$O14=""),1.5,+IF(AND($H14=$S$5,$O14=""),1.5,IF($O14<V$5,0,IF(MONTH($O14)=MONTH(V$5),1.5/30*($O14-V$5),1.5)))))))) -> 1.5 | W14: =+IF(AND(AND($O14="",$P14>=10,MONTH($G14)=MONTH(W$5))),1.5+2,+IF(AND(AND($O14="",$P14>=5,MONTH($G14)=MONTH(W$5))),1.5+1,+IF(AND(AND($P14=5,$O14="",MONTH($G14)=MONTH(W$5))),1.5,+IF(AND($H14>W$5,MONTH($H14)=MONTH(W$5)),1.5/30*(W$4-DAY($H14)),+IF(AND(MONTH($H14)<MONTH(W$5),$O14=""),1.5,+IF(AND($H14=$S$5,$O14=""),1.5,IF($O14<W$5,0,IF(MONTH($O14)=MONTH(W$5),1.5/30*($O14-W$5),1.5)))))))) -> 1.5 | X14: =+IF(AND(AND($O14="",$P14>=10,MONTH($G14)=MONTH(X$5))),1.5+2,+IF(AND(AND($O14="",$P14>=5,MONTH($G14)=MONTH(X$5))),1.5+1,+IF(AND(AND($P14=5,$O14="",MONTH($G14)=MONTH(X$5))),1.5,+IF(AND($H14>X$5,MONTH($H14)=MONTH(X$5)),1.5/30*(X$4-DAY($H14)),+IF(AND(MONTH($H14)<MONTH(X$5),$O14=""),1.5,+IF(AND($H14=$S$5,$O14=""),1.5,IF($O14<X$5,0,IF(MONTH($O14)=MONTH(X$5),1.5/30*($O14-X$5),1.5)))))))) -> 1.5 | Y14: =+IF(AND(AND($O14="",$P14>=10,MONTH($G14)=MONTH(Y$5))),1.5+2,+IF(AND(AND($O14="",$P14>=5,MONTH($G14)=MONTH(Y$5))),1.5+1,+IF(AND(AND($P14=5,$O14="",MONTH($G14)=MONTH(Y$5))),1.5,+IF(AND($H14>Y$5,MONTH($H14)=MONTH(Y$5)),1.5/30*(Y$4-DAY($H14)),+IF(AND(MONTH($H14)<MONTH(Y$5),$O14=""),1.5,+IF(AND($H14=$S$5,$O14=""),1.5,IF($O14<Y$5,0,IF(MONTH($O14)=MONTH(Y$5),1.5/30*($O14-Y$5),1.5)))))))) -> 1.5 | Z14: =+IF(AND(AND($O14="",$P14>=10,MONTH($G14)=MONTH(Z$5))),1.5+2,+IF(AND(AND($O14="",$P14>=5,MONTH($G14)=MONTH(Z$5))),1.5+1,+IF(AND(AND($P14=5,$O14="",MONTH($G14)=MONTH(Z$5))),1.5,+IF(AND($H14>Z$5,MONTH($H14)=MONTH(Z$5)),1.5/30*(Z$4-DAY($H14)),+IF(AND(MONTH($H14)<MONTH(Z$5),$O14=""),1.5,+IF(AND($H14=$S$5,$O14=""),1.5,IF($O14<Z$5,0,IF(MONTH($O14)=MONTH(Z$5),1.5/30*($O14-Z$5),1.5)))))))) -> 1.5 | ... AD14: =+IF(AND(AND($O14="",$P14>=10,MONTH($G14)=MONTH(AD$5))),1.5+2,+IF(AND(AND($O14="",$P14>=5,MONTH($G14)=MONTH(AD$5))),1.5+1,+IF(AND(AND($P14=5,$O14="",MONTH($G14)=MONTH(AD$5))),1.5,+IF(AND($H14>AD$5,MONTH($H14)=MONTH(AD$5)),1.5/30*(AD$4-DAY($H14)),+IF(AND(MONTH($H14)<MONTH(AD$5),$O14=""),1.5,+IF(AND($H14=$S$5,$O14=""),1.5,IF($O14<AD$5,0,IF(MONTH($O14)=MONTH(AD$5),1.5/30*($O14-AD$5),1.5)))))))) -> 1.5 | AF14: =SUM(AG14:AR14) -> 0 | AG14: 0 | AH14: 0 | AI14: 0 | AS14: =+Q14+R14-AF14 -> 23 | AU14: 32.7 | AV14: =SUM(AW14:BH14) -> 274 | AW14: =+IF($K14="",$E14/26*S14,IF(MONTH($K14)=MONTH(AW$5),$L14/26*S14,IF(AND($K14<AW$5,(MONTH($K14)<>MONTH(AW$5))),$L14/26*S14,$E14/26*S14))) -> 20.55 | AX14: =+IF($K14="",$E14/26*T14,IF(MONTH($K14)=MONTH(AX$5),$L14/26*T14,IF(AND($K14<AX$5,(MONTH($K14)<>MONTH(AX$5))),$L14/26*T14,$E14/26*T14))) -> 20.55 | AY14: =+IF($K14="",$E14/26*U14,IF(MONTH($K14)=MONTH(AY$5),$L14/26*U14,IF(AND($K14<AY$5,(MONTH($K14)<>MONTH(AY$5))),$L14/26*U14,$E14/26*U14))) -> 20.55 | AZ14: =+IF($K14="",$E14/26*V14,IF(MONTH($K14)=MONTH(AZ$5),$L14/26*V14,IF(AND($K14<AZ$5,(MONTH($K14)<>MONTH(AZ$5))),$L14/26*V14,$E14/26*V14))) -> 20.55 | BA14: =+IF($K14="",$E14/26*W14,IF(MONTH($K14)=MONTH(BA$5),$L14/26*W14,IF(AND($K14<BA$5,(MONTH($K14)<>MONTH(BA$5))),$L14/26*W14,$E14/26*W14))) -> 20.55 | BB14: =+IF($K14="",$E14/26*X14,IF(MONTH($K14)=MONTH(BB$5),$L14/26*X14,IF(AND($K14<BB$5,(MONTH($K14)<>MONTH(BB$5))),$L14/26*X14,$E14/26*X14))) -> 20.55 | BC14: =+IF($K14="",$E14/26*Y14,IF(MONTH($K14)=MONTH(BC$5),$L14/26*Y14,IF(AND($K14<BC$5,(MONTH($K14)<>MONTH(BC$5))),$L14/26*Y14,$E14/26*Y14))) -> 20.55 | BD14: =+IF($K14="",$E14/26*Z14,IF(MONTH($K14)=MONTH(BD$5),$L14/26*Z14,IF(AND($K14<BD$5,(MONTH($K14)<>MONTH(BD$5))),$L14/26*Z14,$E14/26*Z14))) -> 20.55 | ... BH14: =+IF($K14="",$E14/26*AD14,IF(MONTH($K14)=MONTH(BH$5),$L14/26*AD14,IF(AND($K14<BH$5,(MONTH($K14)<>MONTH(BH$5))),$L14/26*AD14,$E14/26*AD14))) -> 20.55 | BI14: =SUM(BJ14:BU14) -> 0 | BJ14: =(+IF($K14="",$E14/26*AG14,IF(MONTH($K14)=MONTH(BJ$5),$L14/26*AG14,IF(AND($K14<BJ$5,(MONTH($K14)<>MONTH(BJ$5))),$L14/26*AG14,$E14/26*AG14))))*-1 -> 0 | BK14: =(+IF($K14="",$E14/26*AH14,IF(MONTH($K14)=MONTH(BK$5),$L14/26*AH14,IF(AND($K14<BK$5,(MONTH($K14)<>MONTH(BK$5))),$L14/26*AH14,$E14/26*AH14))))*-1 -> 0 | BL14: =(+IF($K14="",$E14/26*AI14,IF(MONTH($K14)=MONTH(BL$5),$L14/26*AI14,IF(AND($K14<BL$5,(MONTH($K14)<>MONTH(BL$5))),$L14/26*AI14,$E14/26*AI14))))*-1 -> 0 | BM14: =(+IF($K14="",$E14/26*AJ14,IF(MONTH($K14)=MONTH(BM$5),$L14/26*AJ14,IF(AND($K14<BM$5,(MONTH($K14)<>MONTH(BM$5))),$L14/26*AJ14,$E14/26*AJ14))))*-1 -> 0 | BN14: =(+IF($K14="",$E14/26*AK14,IF(MONTH($K14)=MONTH(BN$5),$L14/26*AK14,IF(AND($K14<BN$5,(MONTH($K14)<>MONTH(BN$5))),$L14/26*AK14,$E14/26*AK14))))*-1 -> 0 | BO14: =(+IF($K14="",$E14/26*AL14,IF(MONTH($K14)=MONTH(BO$5),$L14/26*AL14,IF(AND($K14<BO$5,(MONTH($K14)<>MONTH(BO$5))),$L14/26*AL14,$E14/26*AL14))))*-1 -> 0 | BP14: =(+IF($K14="",$E14/26*AM14,IF(MONTH($K14)=MONTH(BP$5),$L14/26*AM14,IF(AND($K14<BP$5,(MONTH($K14)<>MONTH(BP$5))),$L14/26*AM14,$E14/26*AM14))))*-1 -> 0 | BQ14: =(+IF($K14="",$E14/26*AN14,IF(MONTH($K14)=MONTH(BQ$5),$L14/26*AN14,IF(AND($K14<BQ$5,(MONTH($K14)<>MONTH(BQ$5))),$L14/26*AN14,$E14/26*AN14))))*-1 -> 0 | ... BU14: =(+IF($K14="",$E14/26*AR14,IF(MONTH($K14)=MONTH(BU$5),$L14/26*AR14,IF(AND($K14<BU$5,(MONTH($K14)<>MONTH(BU$5))),$L14/26*AR14,$E14/26*AR14))))*-1 -> 0 | BV14: =+AU14+AV14+BI14 -> 306.7 | BX14: =+IF(AND($J14>BX$5,MONTH($J14<>BX$5)),0,+IF(AND($J14>BX$5,MONTH($J14=BX$5)),$E14/$R14*DAY($J14),IF(AND($O14<>"",$O14<BX$5),0,IF($K14="",$E14/$R14*S14,IF(MONTH($K14)=MONTH(BX$5),$L14/$R14*S14,IF(AND($K14<BX$5,(MONTH($K14)<>MONTH(BX$5))),$L14/$R14*S14,$E14/$R14*S14)))))) -> 26.715 | BY14: =+IF(AND($J14>BY$5,MONTH($J14<>BY$5)),0,+IF(AND($J14>BY$5,MONTH($J14=BY$5)),$E14/$R14*DAY($J14),IF(AND($O14<>"",$O14<BY$5),0,IF($K14="",$E14/$R14*T14,IF(MONTH($K14)=MONTH(BY$5),$L14/$R14*T14,IF(AND($K14<BY$5,(MONTH($K14)<>MONTH(BY$5))),$L14/$R14*T14,$E14/$R14*T14)))))) -> 26.715 | BZ14: =+IF(AND($J14>BZ$5,MONTH($J14<>BZ$5)),0,+IF(AND($J14>BZ$5,MONTH($J14=BZ$5)),$E14/$R14*DAY($J14),IF(AND($O14<>"",$O14<BZ$5),0,IF($K14="",$E14/$R14*U14,IF(MONTH($K14)=MONTH(BZ$5),$L14/$R14*U14,IF(AND($K14<BZ$5,(MONTH($K14)<>MONTH(BZ$5))),$L14/$R14*U14,$E14/$R14*U14)))))) -> 26.715 | CA14: =+IF(AND($J14>CA$5,MONTH($J14<>CA$5)),0,+IF(AND($J14>CA$5,MONTH($J14=CA$5)),$E14/$R14*DAY($J14),IF(AND($O14<>"",$O14<CA$5),0,IF($K14="",$E14/$R14*V14,IF(MONTH($K14)=MONTH(CA$5),$L14/$R14*V14,IF(AND($K14<CA$5,(MONTH($K14)<>MONTH(CA$5))),$L14/$R14*V14,$E14/$R14*V14)))))) -> 26.715 | CB14: =+IF(AND($J14>CB$5,MONTH($J14<>CB$5)),0,+IF(AND($J14>CB$5,MONTH($J14=CB$5)),$E14/$R14*DAY($J14),IF(AND($O14<>"",$O14<CB$5),0,IF($K14="",$E14/$R14*W14,IF(MONTH($K14)=MONTH(CB$5),$L14/$R14*W14,IF(AND($K14<CB$5,(MONTH($K14)<>MONTH(CB$5))),$L14/$R14*W14,$E14/$R14*W14)))))) -> 26.715 | CC14: =+IF(AND($J14>CC$5,MONTH($J14<>CC$5)),0,+IF(AND($J14>CC$5,MONTH($J14=CC$5)),$E14/$R14*DAY($J14),IF(AND($O14<>"",$O14<CC$5),0,IF($K14="",$E14/$R14*X14,IF(MONTH($K14)=MONTH(CC$5),$L14/$R14*X14,IF(AND($K14<CC$5,(MONTH($K14)<>MONTH(CC$5))),$L14/$R14*X14,$E14/$R14*X14)))))) -> 26.715 | CD14: =+IF(AND($J14>CD$5,MONTH($J14<>CD$5)),0,+IF(AND($J14>CD$5,MONTH($J14=CD$5)),$E14/$R14*DAY($J14),IF(AND($O14<>"",$O14<CD$5),0,IF($K14="",$E14/$R14*Y14,IF(MONTH($K14)=MONTH(CD$5),$L14/$R14*Y14,IF(AND($K14<CD$5,(MONTH($K14)<>MONTH(CD$5))),$L14/$R14*Y14,$E14/$R14*Y14)))))) -> 26.715 | CE14: =+IF(AND($J14>CE$5,MONTH($J14<>CE$5)),0,+IF(AND($J14>CE$5,MONTH($J14=CE$5)),$E14/$R14*DAY($J14),IF(AND($O14<>"",$O14<CE$5),0,IF($K14="",$E14/$R14*Z14,IF(MONTH($K14)=MONTH(CE$5),$L14/$R14*Z14,IF(AND($K14<CE$5,(MONTH($K14)<>MONTH(CE$5))),$L14/$R14*Z14,$E14/$R14*Z14)))))) -> 26.715 | ... CI14: =+IF(AND($J14>CI$5,MONTH($J14<>CI$5)),0,+IF(AND($J14>CI$5,MONTH($J14=CI$5)),$E14/$R14*DAY($J14),IF(AND($O14<>"",$O14<CI$5),0,IF($K14="",$E14/$R14*AD14,IF(MONTH($K14)=MONTH(CI$5),$L14/$R14*AD14,IF(AND($K14<CI$5,(MONTH($K14)<>MONTH(CI$5))),$L14/$R14*AD14,$E14/$R14*AD14)))))) -> 26.715 | CJ14: =SUM(BX14:CI14) -> 356.2 | CK14: =+IF(P14<5,18,IF(AND(P14>=5,P14<10),19,IF(AND(P14>=10,P14<15),20,IF(AND(P14>=15,P14<20),21,0)))) -> 20 | CL14: =+CM14-CJ14 -> 0 | CM14: =IF(L14=0,E14,(L14-E14+E14)) -> 356.2
A15: 04177 | B15: NDONGO NDONGO LARRY | C15: Bell Boy | D15: =+VLOOKUP(A15,'[1]BDD-Avk Tx'!B:CE,82,0) -> 120 | E15: 200.2 | G15: 41153 | H15: =+IF(YEAR(G15)<YEAR($H$5),$H$4,G15) -> 45647 | I15: =+VLOOKUP(A15,'[1]BDD-Avk Tx'!B:BZ,77,0) -> CDI | J15: =+IF(I15="CDI",H15,H15+0) -> 45647 | P15: =DATEDIF(G15,$AD$6,"m")/12 -> 13.25 | Q15: 2 | R15: =SUM(S15:AD15) -> 20 | S15: =+IF(AND(AND($O15="",$P15>=10,MONTH($G15)=MONTH(S$5))),1.5+2,+IF(AND(AND($O15="",$P15>=5,MONTH($G15)=MONTH(S$5))),1.5+1,+IF(AND(AND($P15=5,$O15="",MONTH($G15)=MONTH(S$5))),1.5,+IF(AND($H15>S$5,MONTH($H15)=MONTH(S$5)),1.5/30*(S$4-DAY($H15)),+IF(AND(MONTH($H15)<MONTH(S$5),$O15=""),1.5,+IF(AND($H15=$S$5,$O15=""),1.5,IF($O15<S$5,0,IF(MONTH($O15)=MONTH(S$5),1.5/30*($O15-S$5),1.5)))))))) -> 1.5 | T15: =+IF(AND(AND($O15="",$P15>=10,MONTH($G15)=MONTH(T$5))),1.5+2,+IF(AND(AND($O15="",$P15>=5,MONTH($G15)=MONTH(T$5))),1.5+1,+IF(AND(AND($P15=5,$O15="",MONTH($G15)=MONTH(T$5))),1.5,+IF(AND($H15>T$5,MONTH($H15)=MONTH(T$5)),1.5/30*(T$4-DAY($H15)),+IF(AND(MONTH($H15)<MONTH(T$5),$O15=""),1.5,+IF(AND($H15=$S$5,$O15=""),1.5,IF($O15<T$5,0,IF(MONTH($O15)=MONTH(T$5),1.5/30*($O15-T$5),1.5)))))))) -> 1.5 | U15: =+IF(AND(AND($O15="",$P15>=10,MONTH($G15)=MONTH(U$5))),1.5+2,+IF(AND(AND($O15="",$P15>=5,MONTH($G15)=MONTH(U$5))),1.5+1,+IF(AND(AND($P15=5,$O15="",MONTH($G15)=MONTH(U$5))),1.5,+IF(AND($H15>U$5,MONTH($H15)=MONTH(U$5)),1.5/30*(U$4-DAY($H15)),+IF(AND(MONTH($H15)<MONTH(U$5),$O15=""),1.5,+IF(AND($H15=$S$5,$O15=""),1.5,IF($O15<U$5,0,IF(MONTH($O15)=MONTH(U$5),1.5/30*($O15-U$5),1.5)))))))) -> 1.5 | V15: =+IF(AND(AND($O15="",$P15>=10,MONTH($G15)=MONTH(V$5))),1.5+2,+IF(AND(AND($O15="",$P15>=5,MONTH($G15)=MONTH(V$5))),1.5+1,+IF(AND(AND($P15=5,$O15="",MONTH($G15)=MONTH(V$5))),1.5,+IF(AND($H15>V$5,MONTH($H15)=MONTH(V$5)),1.5/30*(V$4-DAY($H15)),+IF(AND(MONTH($H15)<MONTH(V$5),$O15=""),1.5,+IF(AND($H15=$S$5,$O15=""),1.5,IF($O15<V$5,0,IF(MONTH($O15)=MONTH(V$5),1.5/30*($O15-V$5),1.5)))))))) -> 1.5 | W15: =+IF(AND(AND($O15="",$P15>=10,MONTH($G15)=MONTH(W$5))),1.5+2,+IF(AND(AND($O15="",$P15>=5,MONTH($G15)=MONTH(W$5))),1.5+1,+IF(AND(AND($P15=5,$O15="",MONTH($G15)=MONTH(W$5))),1.5,+IF(AND($H15>W$5,MONTH($H15)=MONTH(W$5)),1.5/30*(W$4-DAY($H15)),+IF(AND(MONTH($H15)<MONTH(W$5),$O15=""),1.5,+IF(AND($H15=$S$5,$O15=""),1.5,IF($O15<W$5,0,IF(MONTH($O15)=MONTH(W$5),1.5/30*($O15-W$5),1.5)))))))) -> 1.5 | X15: =+IF(AND(AND($O15="",$P15>=10,MONTH($G15)=MONTH(X$5))),1.5+2,+IF(AND(AND($O15="",$P15>=5,MONTH($G15)=MONTH(X$5))),1.5+1,+IF(AND(AND($P15=5,$O15="",MONTH($G15)=MONTH(X$5))),1.5,+IF(AND($H15>X$5,MONTH($H15)=MONTH(X$5)),1.5/30*(X$4-DAY($H15)),+IF(AND(MONTH($H15)<MONTH(X$5),$O15=""),1.5,+IF(AND($H15=$S$5,$O15=""),1.5,IF($O15<X$5,0,IF(MONTH($O15)=MONTH(X$5),1.5/30*($O15-X$5),1.5)))))))) -> 1.5 | Y15: =+IF(AND(AND($O15="",$P15>=10,MONTH($G15)=MONTH(Y$5))),1.5+2,+IF(AND(AND($O15="",$P15>=5,MONTH($G15)=MONTH(Y$5))),1.5+1,+IF(AND(AND($P15=5,$O15="",MONTH($G15)=MONTH(Y$5))),1.5,+IF(AND($H15>Y$5,MONTH($H15)=MONTH(Y$5)),1.5/30*(Y$4-DAY($H15)),+IF(AND(MONTH($H15)<MONTH(Y$5),$O15=""),1.5,+IF(AND($H15=$S$5,$O15=""),1.5,IF($O15<Y$5,0,IF(MONTH($O15)=MONTH(Y$5),1.5/30*($O15-Y$5),1.5)))))))) -> 1.5 | Z15: =+IF(AND(AND($O15="",$P15>=10,MONTH($G15)=MONTH(Z$5))),1.5+2,+IF(AND(AND($O15="",$P15>=5,MONTH($G15)=MONTH(Z$5))),1.5+1,+IF(AND(AND($P15=5,$O15="",MONTH($G15)=MONTH(Z$5))),1.5,+IF(AND($H15>Z$5,MONTH($H15)=MONTH(Z$5)),1.5/30*(Z$4-DAY($H15)),+IF(AND(MONTH($H15)<MONTH(Z$5),$O15=""),1.5,+IF(AND($H15=$S$5,$O15=""),1.5,IF($O15<Z$5,0,IF(MONTH($O15)=MONTH(Z$5),1.5/30*($O15-Z$5),1.5)))))))) -> 1.5 | ... AD15: =+IF(AND(AND($O15="",$P15>=10,MONTH($G15)=MONTH(AD$5))),1.5+2,+IF(AND(AND($O15="",$P15>=5,MONTH($G15)=MONTH(AD$5))),1.5+1,+IF(AND(AND($P15=5,$O15="",MONTH($G15)=MONTH(AD$5))),1.5,+IF(AND($H15>AD$5,MONTH($H15)=MONTH(AD$5)),1.5/30*(AD$4-DAY($H15)),+IF(AND(MONTH($H15)<MONTH(AD$5),$O15=""),1.5,+IF(AND($H15=$S$5,$O15=""),1.5,IF($O15<AD$5,0,IF(MONTH($O15)=MONTH(AD$5),1.5/30*($O15-AD$5),1.5)))))))) -> 1.5 | AF15: =SUM(AG15:AR15) -> 0 | AG15: 0 | AH15: 0 | AI15: 0 | AS15: =+Q15+R15-AF15 -> 22 | AU15: 20.138462 | AV15: =SUM(AW15:BH15) -> 154 | AW15: =+IF($K15="",$E15/26*S15,IF(MONTH($K15)=MONTH(AW$5),$L15/26*S15,IF(AND($K15<AW$5,(MONTH($K15)<>MONTH(AW$5))),$L15/26*S15,$E15/26*S15))) -> 11.55 | AX15: =+IF($K15="",$E15/26*T15,IF(MONTH($K15)=MONTH(AX$5),$L15/26*T15,IF(AND($K15<AX$5,(MONTH($K15)<>MONTH(AX$5))),$L15/26*T15,$E15/26*T15))) -> 11.55 | AY15: =+IF($K15="",$E15/26*U15,IF(MONTH($K15)=MONTH(AY$5),$L15/26*U15,IF(AND($K15<AY$5,(MONTH($K15)<>MONTH(AY$5))),$L15/26*U15,$E15/26*U15))) -> 11.55 | AZ15: =+IF($K15="",$E15/26*V15,IF(MONTH($K15)=MONTH(AZ$5),$L15/26*V15,IF(AND($K15<AZ$5,(MONTH($K15)<>MONTH(AZ$5))),$L15/26*V15,$E15/26*V15))) -> 11.55 | BA15: =+IF($K15="",$E15/26*W15,IF(MONTH($K15)=MONTH(BA$5),$L15/26*W15,IF(AND($K15<BA$5,(MONTH($K15)<>MONTH(BA$5))),$L15/26*W15,$E15/26*W15))) -> 11.55 | BB15: =+IF($K15="",$E15/26*X15,IF(MONTH($K15)=MONTH(BB$5),$L15/26*X15,IF(AND($K15<BB$5,(MONTH($K15)<>MONTH(BB$5))),$L15/26*X15,$E15/26*X15))) -> 11.55 | BC15: =+IF($K15="",$E15/26*Y15,IF(MONTH($K15)=MONTH(BC$5),$L15/26*Y15,IF(AND($K15<BC$5,(MONTH($K15)<>MONTH(BC$5))),$L15/26*Y15,$E15/26*Y15))) -> 11.55 | BD15: =+IF($K15="",$E15/26*Z15,IF(MONTH($K15)=MONTH(BD$5),$L15/26*Z15,IF(AND($K15<BD$5,(MONTH($K15)<>MONTH(BD$5))),$L15/26*Z15,$E15/26*Z15))) -> 11.55 | ... BH15: =+IF($K15="",$E15/26*AD15,IF(MONTH($K15)=MONTH(BH$5),$L15/26*AD15,IF(AND($K15<BH$5,(MONTH($K15)<>MONTH(BH$5))),$L15/26*AD15,$E15/26*AD15))) -> 11.55 | BI15: =SUM(BJ15:BU15) -> 0 | BJ15: =(+IF($K15="",$E15/26*AG15,IF(MONTH($K15)=MONTH(BJ$5),$L15/26*AG15,IF(AND($K15<BJ$5,(MONTH($K15)<>MONTH(BJ$5))),$L15/26*AG15,$E15/26*AG15))))*-1 -> 0 | BK15: =(+IF($K15="",$E15/26*AH15,IF(MONTH($K15)=MONTH(BK$5),$L15/26*AH15,IF(AND($K15<BK$5,(MONTH($K15)<>MONTH(BK$5))),$L15/26*AH15,$E15/26*AH15))))*-1 -> 0 | BL15: =(+IF($K15="",$E15/26*AI15,IF(MONTH($K15)=MONTH(BL$5),$L15/26*AI15,IF(AND($K15<BL$5,(MONTH($K15)<>MONTH(BL$5))),$L15/26*AI15,$E15/26*AI15))))*-1 -> 0 | BM15: =(+IF($K15="",$E15/26*AJ15,IF(MONTH($K15)=MONTH(BM$5),$L15/26*AJ15,IF(AND($K15<BM$5,(MONTH($K15)<>MONTH(BM$5))),$L15/26*AJ15,$E15/26*AJ15))))*-1 -> 0 | BN15: =(+IF($K15="",$E15/26*AK15,IF(MONTH($K15)=MONTH(BN$5),$L15/26*AK15,IF(AND($K15<BN$5,(MONTH($K15)<>MONTH(BN$5))),$L15/26*AK15,$E15/26*AK15))))*-1 -> 0 | BO15: =(+IF($K15="",$E15/26*AL15,IF(MONTH($K15)=MONTH(BO$5),$L15/26*AL15,IF(AND($K15<BO$5,(MONTH($K15)<>MONTH(BO$5))),$L15/26*AL15,$E15/26*AL15))))*-1 -> 0 | BP15: =(+IF($K15="",$E15/26*AM15,IF(MONTH($K15)=MONTH(BP$5),$L15/26*AM15,IF(AND($K15<BP$5,(MONTH($K15)<>MONTH(BP$5))),$L15/26*AM15,$E15/26*AM15))))*-1 -> 0 | BQ15: =(+IF($K15="",$E15/26*AN15,IF(MONTH($K15)=MONTH(BQ$5),$L15/26*AN15,IF(AND($K15<BQ$5,(MONTH($K15)<>MONTH(BQ$5))),$L15/26*AN15,$E15/26*AN15))))*-1 -> 0 | ... BU15: =(+IF($K15="",$E15/26*AR15,IF(MONTH($K15)=MONTH(BU$5),$L15/26*AR15,IF(AND($K15<BU$5,(MONTH($K15)<>MONTH(BU$5))),$L15/26*AR15,$E15/26*AR15))))*-1 -> 0 | BV15: =+AU15+AV15+BI15 -> 174.13846 | BX15: =+IF(AND($J15>BX$5,MONTH($J15<>BX$5)),0,+IF(AND($J15>BX$5,MONTH($J15=BX$5)),$E15/$R15*DAY($J15),IF(AND($O15<>"",$O15<BX$5),0,IF($K15="",$E15/$R15*S15,IF(MONTH($K15)=MONTH(BX$5),$L15/$R15*S15,IF(AND($K15<BX$5,(MONTH($K15)<>MONTH(BX$5))),$L15/$R15*S15,$E15/$R15*S15)))))) -> 15.015 | BY15: =+IF(AND($J15>BY$5,MONTH($J15<>BY$5)),0,+IF(AND($J15>BY$5,MONTH($J15=BY$5)),$E15/$R15*DAY($J15),IF(AND($O15<>"",$O15<BY$5),0,IF($K15="",$E15/$R15*T15,IF(MONTH($K15)=MONTH(BY$5),$L15/$R15*T15,IF(AND($K15<BY$5,(MONTH($K15)<>MONTH(BY$5))),$L15/$R15*T15,$E15/$R15*T15)))))) -> 15.015 | BZ15: =+IF(AND($J15>BZ$5,MONTH($J15<>BZ$5)),0,+IF(AND($J15>BZ$5,MONTH($J15=BZ$5)),$E15/$R15*DAY($J15),IF(AND($O15<>"",$O15<BZ$5),0,IF($K15="",$E15/$R15*U15,IF(MONTH($K15)=MONTH(BZ$5),$L15/$R15*U15,IF(AND($K15<BZ$5,(MONTH($K15)<>MONTH(BZ$5))),$L15/$R15*U15,$E15/$R15*U15)))))) -> 15.015 | CA15: =+IF(AND($J15>CA$5,MONTH($J15<>CA$5)),0,+IF(AND($J15>CA$5,MONTH($J15=CA$5)),$E15/$R15*DAY($J15),IF(AND($O15<>"",$O15<CA$5),0,IF($K15="",$E15/$R15*V15,IF(MONTH($K15)=MONTH(CA$5),$L15/$R15*V15,IF(AND($K15<CA$5,(MONTH($K15)<>MONTH(CA$5))),$L15/$R15*V15,$E15/$R15*V15)))))) -> 15.015 | CB15: =+IF(AND($J15>CB$5,MONTH($J15<>CB$5)),0,+IF(AND($J15>CB$5,MONTH($J15=CB$5)),$E15/$R15*DAY($J15),IF(AND($O15<>"",$O15<CB$5),0,IF($K15="",$E15/$R15*W15,IF(MONTH($K15)=MONTH(CB$5),$L15/$R15*W15,IF(AND($K15<CB$5,(MONTH($K15)<>MONTH(CB$5))),$L15/$R15*W15,$E15/$R15*W15)))))) -> 15.015 | CC15: =+IF(AND($J15>CC$5,MONTH($J15<>CC$5)),0,+IF(AND($J15>CC$5,MONTH($J15=CC$5)),$E15/$R15*DAY($J15),IF(AND($O15<>"",$O15<CC$5),0,IF($K15="",$E15/$R15*X15,IF(MONTH($K15)=MONTH(CC$5),$L15/$R15*X15,IF(AND($K15<CC$5,(MONTH($K15)<>MONTH(CC$5))),$L15/$R15*X15,$E15/$R15*X15)))))) -> 15.015 | CD15: =+IF(AND($J15>CD$5,MONTH($J15<>CD$5)),0,+IF(AND($J15>CD$5,MONTH($J15=CD$5)),$E15/$R15*DAY($J15),IF(AND($O15<>"",$O15<CD$5),0,IF($K15="",$E15/$R15*Y15,IF(MONTH($K15)=MONTH(CD$5),$L15/$R15*Y15,IF(AND($K15<CD$5,(MONTH($K15)<>MONTH(CD$5))),$L15/$R15*Y15,$E15/$R15*Y15)))))) -> 15.015 | CE15: =+IF(AND($J15>CE$5,MONTH($J15<>CE$5)),0,+IF(AND($J15>CE$5,MONTH($J15=CE$5)),$E15/$R15*DAY($J15),IF(AND($O15<>"",$O15<CE$5),0,IF($K15="",$E15/$R15*Z15,IF(MONTH($K15)=MONTH(CE$5),$L15/$R15*Z15,IF(AND($K15<CE$5,(MONTH($K15)<>MONTH(CE$5))),$L15/$R15*Z15,$E15/$R15*Z15)))))) -> 15.015 | ... CI15: =+IF(AND($J15>CI$5,MONTH($J15<>CI$5)),0,+IF(AND($J15>CI$5,MONTH($J15=CI$5)),$E15/$R15*DAY($J15),IF(AND($O15<>"",$O15<CI$5),0,IF($K15="",$E15/$R15*AD15,IF(MONTH($K15)=MONTH(CI$5),$L15/$R15*AD15,IF(AND($K15<CI$5,(MONTH($K15)<>MONTH(CI$5))),$L15/$R15*AD15,$E15/$R15*AD15)))))) -> 15.015 | CJ15: =SUM(BX15:CI15) -> 200.2 | CK15: =+IF(P15<5,18,IF(AND(P15>=5,P15<10),19,IF(AND(P15>=10,P15<15),20,IF(AND(P15>=15,P15<20),21,0)))) -> 20 | CL15: =+CM15-CJ15 -> 0 | CM15: =IF(L15=0,E15,(L15-E15+E15)) -> 200.2
A16: 04221 | B16: DUNGIKA NGUNGA CHRISTOPHE | C16: Business Center Agent | D16: =+VLOOKUP(A16,'[1]BDD-Avk Tx'!B:CE,82,0) -> 420 | E16: 231.4 | G16: 41800 | H16: =+IF(YEAR(G16)<YEAR($H$5),$H$4,G16) -> 45647 | I16: =+VLOOKUP(A16,'[1]BDD-Avk Tx'!B:BZ,77,0) -> CDI | J16: =+IF(I16="CDI",H16,H16+0) -> 45647 | P16: =DATEDIF(G16,$AD$6,"m")/12 -> 11.5 | Q16: 4 | R16: =SUM(S16:AD16) -> 20 | S16: =+IF(AND(AND($O16="",$P16>=10,MONTH($G16)=MONTH(S$5))),1.5+2,+IF(AND(AND($O16="",$P16>=5,MONTH($G16)=MONTH(S$5))),1.5+1,+IF(AND(AND($P16=5,$O16="",MONTH($G16)=MONTH(S$5))),1.5,+IF(AND($H16>S$5,MONTH($H16)=MONTH(S$5)),1.5/30*(S$4-DAY($H16)),+IF(AND(MONTH($H16)<MONTH(S$5),$O16=""),1.5,+IF(AND($H16=$S$5,$O16=""),1.5,IF($O16<S$5,0,IF(MONTH($O16)=MONTH(S$5),1.5/30*($O16-S$5),1.5)))))))) -> 1.5 | T16: =+IF(AND(AND($O16="",$P16>=10,MONTH($G16)=MONTH(T$5))),1.5+2,+IF(AND(AND($O16="",$P16>=5,MONTH($G16)=MONTH(T$5))),1.5+1,+IF(AND(AND($P16=5,$O16="",MONTH($G16)=MONTH(T$5))),1.5,+IF(AND($H16>T$5,MONTH($H16)=MONTH(T$5)),1.5/30*(T$4-DAY($H16)),+IF(AND(MONTH($H16)<MONTH(T$5),$O16=""),1.5,+IF(AND($H16=$S$5,$O16=""),1.5,IF($O16<T$5,0,IF(MONTH($O16)=MONTH(T$5),1.5/30*($O16-T$5),1.5)))))))) -> 1.5 | U16: =+IF(AND(AND($O16="",$P16>=10,MONTH($G16)=MONTH(U$5))),1.5+2,+IF(AND(AND($O16="",$P16>=5,MONTH($G16)=MONTH(U$5))),1.5+1,+IF(AND(AND($P16=5,$O16="",MONTH($G16)=MONTH(U$5))),1.5,+IF(AND($H16>U$5,MONTH($H16)=MONTH(U$5)),1.5/30*(U$4-DAY($H16)),+IF(AND(MONTH($H16)<MONTH(U$5),$O16=""),1.5,+IF(AND($H16=$S$5,$O16=""),1.5,IF($O16<U$5,0,IF(MONTH($O16)=MONTH(U$5),1.5/30*($O16-U$5),1.5)))))))) -> 1.5 | V16: =+IF(AND(AND($O16="",$P16>=10,MONTH($G16)=MONTH(V$5))),1.5+2,+IF(AND(AND($O16="",$P16>=5,MONTH($G16)=MONTH(V$5))),1.5+1,+IF(AND(AND($P16=5,$O16="",MONTH($G16)=MONTH(V$5))),1.5,+IF(AND($H16>V$5,MONTH($H16)=MONTH(V$5)),1.5/30*(V$4-DAY($H16)),+IF(AND(MONTH($H16)<MONTH(V$5),$O16=""),1.5,+IF(AND($H16=$S$5,$O16=""),1.5,IF($O16<V$5,0,IF(MONTH($O16)=MONTH(V$5),1.5/30*($O16-V$5),1.5)))))))) -> 1.5 | W16: =+IF(AND(AND($O16="",$P16>=10,MONTH($G16)=MONTH(W$5))),1.5+2,+IF(AND(AND($O16="",$P16>=5,MONTH($G16)=MONTH(W$5))),1.5+1,+IF(AND(AND($P16=5,$O16="",MONTH($G16)=MONTH(W$5))),1.5,+IF(AND($H16>W$5,MONTH($H16)=MONTH(W$5)),1.5/30*(W$4-DAY($H16)),+IF(AND(MONTH($H16)<MONTH(W$5),$O16=""),1.5,+IF(AND($H16=$S$5,$O16=""),1.5,IF($O16<W$5,0,IF(MONTH($O16)=MONTH(W$5),1.5/30*($O16-W$5),1.5)))))))) -> 1.5 | X16: =+IF(AND(AND($O16="",$P16>=10,MONTH($G16)=MONTH(X$5))),1.5+2,+IF(AND(AND($O16="",$P16>=5,MONTH($G16)=MONTH(X$5))),1.5+1,+IF(AND(AND($P16=5,$O16="",MONTH($G16)=MONTH(X$5))),1.5,+IF(AND($H16>X$5,MONTH($H16)=MONTH(X$5)),1.5/30*(X$4-DAY($H16)),+IF(AND(MONTH($H16)<MONTH(X$5),$O16=""),1.5,+IF(AND($H16=$S$5,$O16=""),1.5,IF($O16<X$5,0,IF(MONTH($O16)=MONTH(X$5),1.5/30*($O16-X$5),1.5)))))))) -> 1.5 | Y16: =+IF(AND(AND($O16="",$P16>=10,MONTH($G16)=MONTH(Y$5))),1.5+2,+IF(AND(AND($O16="",$P16>=5,MONTH($G16)=MONTH(Y$5))),1.5+1,+IF(AND(AND($P16=5,$O16="",MONTH($G16)=MONTH(Y$5))),1.5,+IF(AND($H16>Y$5,MONTH($H16)=MONTH(Y$5)),1.5/30*(Y$4-DAY($H16)),+IF(AND(MONTH($H16)<MONTH(Y$5),$O16=""),1.5,+IF(AND($H16=$S$5,$O16=""),1.5,IF($O16<Y$5,0,IF(MONTH($O16)=MONTH(Y$5),1.5/30*($O16-Y$5),1.5)))))))) -> 3.5 | Z16: =+IF(AND(AND($O16="",$P16>=10,MONTH($G16)=MONTH(Z$5))),1.5+2,+IF(AND(AND($O16="",$P16>=5,MONTH($G16)=MONTH(Z$5))),1.5+1,+IF(AND(AND($P16=5,$O16="",MONTH($G16)=MONTH(Z$5))),1.5,+IF(AND($H16>Z$5,MONTH($H16)=MONTH(Z$5)),1.5/30*(Z$4-DAY($H16)),+IF(AND(MONTH($H16)<MONTH(Z$5),$O16=""),1.5,+IF(AND($H16=$S$5,$O16=""),1.5,IF($O16<Z$5,0,IF(MONTH($O16)=MONTH(Z$5),1.5/30*($O16-Z$5),1.5)))))))) -> 1.5 | ... AD16: =+IF(AND(AND($O16="",$P16>=10,MONTH($G16)=MONTH(AD$5))),1.5+2,+IF(AND(AND($O16="",$P16>=5,MONTH($G16)=MONTH(AD$5))),1.5+1,+IF(AND(AND($P16=5,$O16="",MONTH($G16)=MONTH(AD$5))),1.5,+IF(AND($H16>AD$5,MONTH($H16)=MONTH(AD$5)),1.5/30*(AD$4-DAY($H16)),+IF(AND(MONTH($H16)<MONTH(AD$5),$O16=""),1.5,+IF(AND($H16=$S$5,$O16=""),1.5,IF($O16<AD$5,0,IF(MONTH($O16)=MONTH(AD$5),1.5/30*($O16-AD$5),1.5)))))))) -> 1.5 | AF16: =SUM(AG16:AR16) -> 0 | AG16: 0 | AH16: 0 | AI16: 0 | AS16: =+Q16+R16-AF16 -> 24 | AU16: 27.723077 | AV16: =SUM(AW16:BH16) -> 178 | AW16: =+IF($K16="",$E16/26*S16,IF(MONTH($K16)=MONTH(AW$5),$L16/26*S16,IF(AND($K16<AW$5,(MONTH($K16)<>MONTH(AW$5))),$L16/26*S16,$E16/26*S16))) -> 13.35 | AX16: =+IF($K16="",$E16/26*T16,IF(MONTH($K16)=MONTH(AX$5),$L16/26*T16,IF(AND($K16<AX$5,(MONTH($K16)<>MONTH(AX$5))),$L16/26*T16,$E16/26*T16))) -> 13.35 | AY16: =+IF($K16="",$E16/26*U16,IF(MONTH($K16)=MONTH(AY$5),$L16/26*U16,IF(AND($K16<AY$5,(MONTH($K16)<>MONTH(AY$5))),$L16/26*U16,$E16/26*U16))) -> 13.35 | AZ16: =+IF($K16="",$E16/26*V16,IF(MONTH($K16)=MONTH(AZ$5),$L16/26*V16,IF(AND($K16<AZ$5,(MONTH($K16)<>MONTH(AZ$5))),$L16/26*V16,$E16/26*V16))) -> 13.35 | BA16: =+IF($K16="",$E16/26*W16,IF(MONTH($K16)=MONTH(BA$5),$L16/26*W16,IF(AND($K16<BA$5,(MONTH($K16)<>MONTH(BA$5))),$L16/26*W16,$E16/26*W16))) -> 13.35 | BB16: =+IF($K16="",$E16/26*X16,IF(MONTH($K16)=MONTH(BB$5),$L16/26*X16,IF(AND($K16<BB$5,(MONTH($K16)<>MONTH(BB$5))),$L16/26*X16,$E16/26*X16))) -> 13.35 | BC16: =+IF($K16="",$E16/26*Y16,IF(MONTH($K16)=MONTH(BC$5),$L16/26*Y16,IF(AND($K16<BC$5,(MONTH($K16)<>MONTH(BC$5))),$L16/26*Y16,$E16/26*Y16))) -> 31.15 | BD16: =+IF($K16="",$E16/26*Z16,IF(MONTH($K16)=MONTH(BD$5),$L16/26*Z16,IF(AND($K16<BD$5,(MONTH($K16)<>MONTH(BD$5))),$L16/26*Z16,$E16/26*Z16))) -> 13.35 | ... BH16: =+IF($K16="",$E16/26*AD16,IF(MONTH($K16)=MONTH(BH$5),$L16/26*AD16,IF(AND($K16<BH$5,(MONTH($K16)<>MONTH(BH$5))),$L16/26*AD16,$E16/26*AD16))) -> 13.35 | BI16: =SUM(BJ16:BU16) -> 0 | BJ16: =(+IF($K16="",$E16/26*AG16,IF(MONTH($K16)=MONTH(BJ$5),$L16/26*AG16,IF(AND($K16<BJ$5,(MONTH($K16)<>MONTH(BJ$5))),$L16/26*AG16,$E16/26*AG16))))*-1 -> 0 | BK16: =(+IF($K16="",$E16/26*AH16,IF(MONTH($K16)=MONTH(BK$5),$L16/26*AH16,IF(AND($K16<BK$5,(MONTH($K16)<>MONTH(BK$5))),$L16/26*AH16,$E16/26*AH16))))*-1 -> 0 | BL16: =(+IF($K16="",$E16/26*AI16,IF(MONTH($K16)=MONTH(BL$5),$L16/26*AI16,IF(AND($K16<BL$5,(MONTH($K16)<>MONTH(BL$5))),$L16/26*AI16,$E16/26*AI16))))*-1 -> 0 | BM16: =(+IF($K16="",$E16/26*AJ16,IF(MONTH($K16)=MONTH(BM$5),$L16/26*AJ16,IF(AND($K16<BM$5,(MONTH($K16)<>MONTH(BM$5))),$L16/26*AJ16,$E16/26*AJ16))))*-1 -> 0 | BN16: =(+IF($K16="",$E16/26*AK16,IF(MONTH($K16)=MONTH(BN$5),$L16/26*AK16,IF(AND($K16<BN$5,(MONTH($K16)<>MONTH(BN$5))),$L16/26*AK16,$E16/26*AK16))))*-1 -> 0 | BO16: =(+IF($K16="",$E16/26*AL16,IF(MONTH($K16)=MONTH(BO$5),$L16/26*AL16,IF(AND($K16<BO$5,(MONTH($K16)<>MONTH(BO$5))),$L16/26*AL16,$E16/26*AL16))))*-1 -> 0 | BP16: =(+IF($K16="",$E16/26*AM16,IF(MONTH($K16)=MONTH(BP$5),$L16/26*AM16,IF(AND($K16<BP$5,(MONTH($K16)<>MONTH(BP$5))),$L16/26*AM16,$E16/26*AM16))))*-1 -> 0 | BQ16: =(+IF($K16="",$E16/26*AN16,IF(MONTH($K16)=MONTH(BQ$5),$L16/26*AN16,IF(AND($K16<BQ$5,(MONTH($K16)<>MONTH(BQ$5))),$L16/26*AN16,$E16/26*AN16))))*-1 -> 0 | ... BU16: =(+IF($K16="",$E16/26*AR16,IF(MONTH($K16)=MONTH(BU$5),$L16/26*AR16,IF(AND($K16<BU$5,(MONTH($K16)<>MONTH(BU$5))),$L16/26*AR16,$E16/26*AR16))))*-1 -> 0 | BV16: =+AU16+AV16+BI16 -> 205.72308 | BX16: =+IF(AND($J16>BX$5,MONTH($J16<>BX$5)),0,+IF(AND($J16>BX$5,MONTH($J16=BX$5)),$E16/$R16*DAY($J16),IF(AND($O16<>"",$O16<BX$5),0,IF($K16="",$E16/$R16*S16,IF(MONTH($K16)=MONTH(BX$5),$L16/$R16*S16,IF(AND($K16<BX$5,(MONTH($K16)<>MONTH(BX$5))),$L16/$R16*S16,$E16/$R16*S16)))))) -> 17.355 | BY16: =+IF(AND($J16>BY$5,MONTH($J16<>BY$5)),0,+IF(AND($J16>BY$5,MONTH($J16=BY$5)),$E16/$R16*DAY($J16),IF(AND($O16<>"",$O16<BY$5),0,IF($K16="",$E16/$R16*T16,IF(MONTH($K16)=MONTH(BY$5),$L16/$R16*T16,IF(AND($K16<BY$5,(MONTH($K16)<>MONTH(BY$5))),$L16/$R16*T16,$E16/$R16*T16)))))) -> 17.355 | BZ16: =+IF(AND($J16>BZ$5,MONTH($J16<>BZ$5)),0,+IF(AND($J16>BZ$5,MONTH($J16=BZ$5)),$E16/$R16*DAY($J16),IF(AND($O16<>"",$O16<BZ$5),0,IF($K16="",$E16/$R16*U16,IF(MONTH($K16)=MONTH(BZ$5),$L16/$R16*U16,IF(AND($K16<BZ$5,(MONTH($K16)<>MONTH(BZ$5))),$L16/$R16*U16,$E16/$R16*U16)))))) -> 17.355 | CA16: =+IF(AND($J16>CA$5,MONTH($J16<>CA$5)),0,+IF(AND($J16>CA$5,MONTH($J16=CA$5)),$E16/$R16*DAY($J16),IF(AND($O16<>"",$O16<CA$5),0,IF($K16="",$E16/$R16*V16,IF(MONTH($K16)=MONTH(CA$5),$L16/$R16*V16,IF(AND($K16<CA$5,(MONTH($K16)<>MONTH(CA$5))),$L16/$R16*V16,$E16/$R16*V16)))))) -> 17.355 | CB16: =+IF(AND($J16>CB$5,MONTH($J16<>CB$5)),0,+IF(AND($J16>CB$5,MONTH($J16=CB$5)),$E16/$R16*DAY($J16),IF(AND($O16<>"",$O16<CB$5),0,IF($K16="",$E16/$R16*W16,IF(MONTH($K16)=MONTH(CB$5),$L16/$R16*W16,IF(AND($K16<CB$5,(MONTH($K16)<>MONTH(CB$5))),$L16/$R16*W16,$E16/$R16*W16)))))) -> 17.355 | CC16: =+IF(AND($J16>CC$5,MONTH($J16<>CC$5)),0,+IF(AND($J16>CC$5,MONTH($J16=CC$5)),$E16/$R16*DAY($J16),IF(AND($O16<>"",$O16<CC$5),0,IF($K16="",$E16/$R16*X16,IF(MONTH($K16)=MONTH(CC$5),$L16/$R16*X16,IF(AND($K16<CC$5,(MONTH($K16)<>MONTH(CC$5))),$L16/$R16*X16,$E16/$R16*X16)))))) -> 17.355 | CD16: =+IF(AND($J16>CD$5,MONTH($J16<>CD$5)),0,+IF(AND($J16>CD$5,MONTH($J16=CD$5)),$E16/$R16*DAY($J16),IF(AND($O16<>"",$O16<CD$5),0,IF($K16="",$E16/$R16*Y16,IF(MONTH($K16)=MONTH(CD$5),$L16/$R16*Y16,IF(AND($K16<CD$5,(MONTH($K16)<>MONTH(CD$5))),$L16/$R16*Y16,$E16/$R16*Y16)))))) -> 40.495 | CE16: =+IF(AND($J16>CE$5,MONTH($J16<>CE$5)),0,+IF(AND($J16>CE$5,MONTH($J16=CE$5)),$E16/$R16*DAY($J16),IF(AND($O16<>"",$O16<CE$5),0,IF($K16="",$E16/$R16*Z16,IF(MONTH($K16)=MONTH(CE$5),$L16/$R16*Z16,IF(AND($K16<CE$5,(MONTH($K16)<>MONTH(CE$5))),$L16/$R16*Z16,$E16/$R16*Z16)))))) -> 17.355 | ... CI16: =+IF(AND($J16>CI$5,MONTH($J16<>CI$5)),0,+IF(AND($J16>CI$5,MONTH($J16=CI$5)),$E16/$R16*DAY($J16),IF(AND($O16<>"",$O16<CI$5),0,IF($K16="",$E16/$R16*AD16,IF(MONTH($K16)=MONTH(CI$5),$L16/$R16*AD16,IF(AND($K16<CI$5,(MONTH($K16)<>MONTH(CI$5))),$L16/$R16*AD16,$E16/$R16*AD16)))))) -> 17.355 | CJ16: =SUM(BX16:CI16) -> 231.4 | CK16: =+IF(P16<5,18,IF(AND(P16>=5,P16<10),19,IF(AND(P16>=10,P16<15),20,IF(AND(P16>=15,P16<20),21,0)))) -> 20 | CL16: =+CM16-CJ16 -> 0 | CM16: =IF(L16=0,E16,(L16-E16+E16)) -> 231.4
A17: 04087 | B17: BONGONDO EALE DADDY | C17: Laundry Manager | D17: =+VLOOKUP(A17,'[1]BDD-Avk Tx'!B:CE,82,0) -> 460 | E17: 1128.4 | G17: 41153 | H17: =+IF(YEAR(G17)<YEAR($H$5),$H$4,G17) -> 45647 | I17: =+VLOOKUP(A17,'[1]BDD-Avk Tx'!B:BZ,77,0) -> CDI | J17: =+IF(I17="CDI",H17,H17+0) -> 45647 | P17: =DATEDIF(G17,$AD$6,"m")/12 -> 13.25 | Q17: 5.5 | R17: =SUM(S17:AD17) -> 20 | S17: =+IF(AND(AND($O17="",$P17>=10,MONTH($G17)=MONTH(S$5))),1.5+2,+IF(AND(AND($O17="",$P17>=5,MONTH($G17)=MONTH(S$5))),1.5+1,+IF(AND(AND($P17=5,$O17="",MONTH($G17)=MONTH(S$5))),1.5,+IF(AND($H17>S$5,MONTH($H17)=MONTH(S$5)),1.5/30*(S$4-DAY($H17)),+IF(AND(MONTH($H17)<MONTH(S$5),$O17=""),1.5,+IF(AND($H17=$S$5,$O17=""),1.5,IF($O17<S$5,0,IF(MONTH($O17)=MONTH(S$5),1.5/30*($O17-S$5),1.5)))))))) -> 1.5 | T17: =+IF(AND(AND($O17="",$P17>=10,MONTH($G17)=MONTH(T$5))),1.5+2,+IF(AND(AND($O17="",$P17>=5,MONTH($G17)=MONTH(T$5))),1.5+1,+IF(AND(AND($P17=5,$O17="",MONTH($G17)=MONTH(T$5))),1.5,+IF(AND($H17>T$5,MONTH($H17)=MONTH(T$5)),1.5/30*(T$4-DAY($H17)),+IF(AND(MONTH($H17)<MONTH(T$5),$O17=""),1.5,+IF(AND($H17=$S$5,$O17=""),1.5,IF($O17<T$5,0,IF(MONTH($O17)=MONTH(T$5),1.5/30*($O17-T$5),1.5)))))))) -> 1.5 | U17: =+IF(AND(AND($O17="",$P17>=10,MONTH($G17)=MONTH(U$5))),1.5+2,+IF(AND(AND($O17="",$P17>=5,MONTH($G17)=MONTH(U$5))),1.5+1,+IF(AND(AND($P17=5,$O17="",MONTH($G17)=MONTH(U$5))),1.5,+IF(AND($H17>U$5,MONTH($H17)=MONTH(U$5)),1.5/30*(U$4-DAY($H17)),+IF(AND(MONTH($H17)<MONTH(U$5),$O17=""),1.5,+IF(AND($H17=$S$5,$O17=""),1.5,IF($O17<U$5,0,IF(MONTH($O17)=MONTH(U$5),1.5/30*($O17-U$5),1.5)))))))) -> 1.5 | V17: =+IF(AND(AND($O17="",$P17>=10,MONTH($G17)=MONTH(V$5))),1.5+2,+IF(AND(AND($O17="",$P17>=5,MONTH($G17)=MONTH(V$5))),1.5+1,+IF(AND(AND($P17=5,$O17="",MONTH($G17)=MONTH(V$5))),1.5,+IF(AND($H17>V$5,MONTH($H17)=MONTH(V$5)),1.5/30*(V$4-DAY($H17)),+IF(AND(MONTH($H17)<MONTH(V$5),$O17=""),1.5,+IF(AND($H17=$S$5,$O17=""),1.5,IF($O17<V$5,0,IF(MONTH($O17)=MONTH(V$5),1.5/30*($O17-V$5),1.5)))))))) -> 1.5 | W17: =+IF(AND(AND($O17="",$P17>=10,MONTH($G17)=MONTH(W$5))),1.5+2,+IF(AND(AND($O17="",$P17>=5,MONTH($G17)=MONTH(W$5))),1.5+1,+IF(AND(AND($P17=5,$O17="",MONTH($G17)=MONTH(W$5))),1.5,+IF(AND($H17>W$5,MONTH($H17)=MONTH(W$5)),1.5/30*(W$4-DAY($H17)),+IF(AND(MONTH($H17)<MONTH(W$5),$O17=""),1.5,+IF(AND($H17=$S$5,$O17=""),1.5,IF($O17<W$5,0,IF(MONTH($O17)=MONTH(W$5),1.5/30*($O17-W$5),1.5)))))))) -> 1.5 | X17: =+IF(AND(AND($O17="",$P17>=10,MONTH($G17)=MONTH(X$5))),1.5+2,+IF(AND(AND($O17="",$P17>=5,MONTH($G17)=MONTH(X$5))),1.5+1,+IF(AND(AND($P17=5,$O17="",MONTH($G17)=MONTH(X$5))),1.5,+IF(AND($H17>X$5,MONTH($H17)=MONTH(X$5)),1.5/30*(X$4-DAY($H17)),+IF(AND(MONTH($H17)<MONTH(X$5),$O17=""),1.5,+IF(AND($H17=$S$5,$O17=""),1.5,IF($O17<X$5,0,IF(MONTH($O17)=MONTH(X$5),1.5/30*($O17-X$5),1.5)))))))) -> 1.5 | Y17: =+IF(AND(AND($O17="",$P17>=10,MONTH($G17)=MONTH(Y$5))),1.5+2,+IF(AND(AND($O17="",$P17>=5,MONTH($G17)=MONTH(Y$5))),1.5+1,+IF(AND(AND($P17=5,$O17="",MONTH($G17)=MONTH(Y$5))),1.5,+IF(AND($H17>Y$5,MONTH($H17)=MONTH(Y$5)),1.5/30*(Y$4-DAY($H17)),+IF(AND(MONTH($H17)<MONTH(Y$5),$O17=""),1.5,+IF(AND($H17=$S$5,$O17=""),1.5,IF($O17<Y$5,0,IF(MONTH($O17)=MONTH(Y$5),1.5/30*($O17-Y$5),1.5)))))))) -> 1.5 | Z17: =+IF(AND(AND($O17="",$P17>=10,MONTH($G17)=MONTH(Z$5))),1.5+2,+IF(AND(AND($O17="",$P17>=5,MONTH($G17)=MONTH(Z$5))),1.5+1,+IF(AND(AND($P17=5,$O17="",MONTH($G17)=MONTH(Z$5))),1.5,+IF(AND($H17>Z$5,MONTH($H17)=MONTH(Z$5)),1.5/30*(Z$4-DAY($H17)),+IF(AND(MONTH($H17)<MONTH(Z$5),$O17=""),1.5,+IF(AND($H17=$S$5,$O17=""),1.5,IF($O17<Z$5,0,IF(MONTH($O17)=MONTH(Z$5),1.5/30*($O17-Z$5),1.5)))))))) -> 1.5 | ... AD17: =+IF(AND(AND($O17="",$P17>=10,MONTH($G17)=MONTH(AD$5))),1.5+2,+IF(AND(AND($O17="",$P17>=5,MONTH($G17)=MONTH(AD$5))),1.5+1,+IF(AND(AND($P17=5,$O17="",MONTH($G17)=MONTH(AD$5))),1.5,+IF(AND($H17>AD$5,MONTH($H17)=MONTH(AD$5)),1.5/30*(AD$4-DAY($H17)),+IF(AND(MONTH($H17)<MONTH(AD$5),$O17=""),1.5,+IF(AND($H17=$S$5,$O17=""),1.5,IF($O17<AD$5,0,IF(MONTH($O17)=MONTH(AD$5),1.5/30*($O17-AD$5),1.5)))))))) -> 1.5 | AF17: =SUM(AG17:AR17) -> 0 | AG17: 0 | AH17: 0 | AI17: 0 | AS17: =+Q17+R17-AF17 -> 25.5 | AU17: 225.59462 | AV17: =SUM(AW17:BH17) -> 868 | AW17: =+IF($K17="",$E17/26*S17,IF(MONTH($K17)=MONTH(AW$5),$L17/26*S17,IF(AND($K17<AW$5,(MONTH($K17)<>MONTH(AW$5))),$L17/26*S17,$E17/26*S17))) -> 65.1 | AX17: =+IF($K17="",$E17/26*T17,IF(MONTH($K17)=MONTH(AX$5),$L17/26*T17,IF(AND($K17<AX$5,(MONTH($K17)<>MONTH(AX$5))),$L17/26*T17,$E17/26*T17))) -> 65.1 | AY17: =+IF($K17="",$E17/26*U17,IF(MONTH($K17)=MONTH(AY$5),$L17/26*U17,IF(AND($K17<AY$5,(MONTH($K17)<>MONTH(AY$5))),$L17/26*U17,$E17/26*U17))) -> 65.1 | AZ17: =+IF($K17="",$E17/26*V17,IF(MONTH($K17)=MONTH(AZ$5),$L17/26*V17,IF(AND($K17<AZ$5,(MONTH($K17)<>MONTH(AZ$5))),$L17/26*V17,$E17/26*V17))) -> 65.1 | BA17: =+IF($K17="",$E17/26*W17,IF(MONTH($K17)=MONTH(BA$5),$L17/26*W17,IF(AND($K17<BA$5,(MONTH($K17)<>MONTH(BA$5))),$L17/26*W17,$E17/26*W17))) -> 65.1 | BB17: =+IF($K17="",$E17/26*X17,IF(MONTH($K17)=MONTH(BB$5),$L17/26*X17,IF(AND($K17<BB$5,(MONTH($K17)<>MONTH(BB$5))),$L17/26*X17,$E17/26*X17))) -> 65.1 | BC17: =+IF($K17="",$E17/26*Y17,IF(MONTH($K17)=MONTH(BC$5),$L17/26*Y17,IF(AND($K17<BC$5,(MONTH($K17)<>MONTH(BC$5))),$L17/26*Y17,$E17/26*Y17))) -> 65.1 | BD17: =+IF($K17="",$E17/26*Z17,IF(MONTH($K17)=MONTH(BD$5),$L17/26*Z17,IF(AND($K17<BD$5,(MONTH($K17)<>MONTH(BD$5))),$L17/26*Z17,$E17/26*Z17))) -> 65.1 | ... BH17: =+IF($K17="",$E17/26*AD17,IF(MONTH($K17)=MONTH(BH$5),$L17/26*AD17,IF(AND($K17<BH$5,(MONTH($K17)<>MONTH(BH$5))),$L17/26*AD17,$E17/26*AD17))) -> 65.1 | BI17: =SUM(BJ17:BU17) -> 0 | BJ17: =(+IF($K17="",$E17/26*AG17,IF(MONTH($K17)=MONTH(BJ$5),$L17/26*AG17,IF(AND($K17<BJ$5,(MONTH($K17)<>MONTH(BJ$5))),$L17/26*AG17,$E17/26*AG17))))*-1 -> 0 | BK17: =(+IF($K17="",$E17/26*AH17,IF(MONTH($K17)=MONTH(BK$5),$L17/26*AH17,IF(AND($K17<BK$5,(MONTH($K17)<>MONTH(BK$5))),$L17/26*AH17,$E17/26*AH17))))*-1 -> 0 | BL17: =(+IF($K17="",$E17/26*AI17,IF(MONTH($K17)=MONTH(BL$5),$L17/26*AI17,IF(AND($K17<BL$5,(MONTH($K17)<>MONTH(BL$5))),$L17/26*AI17,$E17/26*AI17))))*-1 -> 0 | BM17: =(+IF($K17="",$E17/26*AJ17,IF(MONTH($K17)=MONTH(BM$5),$L17/26*AJ17,IF(AND($K17<BM$5,(MONTH($K17)<>MONTH(BM$5))),$L17/26*AJ17,$E17/26*AJ17))))*-1 -> 0 | BN17: =(+IF($K17="",$E17/26*AK17,IF(MONTH($K17)=MONTH(BN$5),$L17/26*AK17,IF(AND($K17<BN$5,(MONTH($K17)<>MONTH(BN$5))),$L17/26*AK17,$E17/26*AK17))))*-1 -> 0 | BO17: =(+IF($K17="",$E17/26*AL17,IF(MONTH($K17)=MONTH(BO$5),$L17/26*AL17,IF(AND($K17<BO$5,(MONTH($K17)<>MONTH(BO$5))),$L17/26*AL17,$E17/26*AL17))))*-1 -> 0 | BP17: =(+IF($K17="",$E17/26*AM17,IF(MONTH($K17)=MONTH(BP$5),$L17/26*AM17,IF(AND($K17<BP$5,(MONTH($K17)<>MONTH(BP$5))),$L17/26*AM17,$E17/26*AM17))))*-1 -> 0 | BQ17: =(+IF($K17="",$E17/26*AN17,IF(MONTH($K17)=MONTH(BQ$5),$L17/26*AN17,IF(AND($K17<BQ$5,(MONTH($K17)<>MONTH(BQ$5))),$L17/26*AN17,$E17/26*AN17))))*-1 -> 0 | ... BU17: =(+IF($K17="",$E17/26*AR17,IF(MONTH($K17)=MONTH(BU$5),$L17/26*AR17,IF(AND($K17<BU$5,(MONTH($K17)<>MONTH(BU$5))),$L17/26*AR17,$E17/26*AR17))))*-1 -> 0 | BV17: =+AU17+AV17+BI17 -> 1093.5946 | BX17: =+IF(AND($J17>BX$5,MONTH($J17<>BX$5)),0,+IF(AND($J17>BX$5,MONTH($J17=BX$5)),$E17/$R17*DAY($J17),IF(AND($O17<>"",$O17<BX$5),0,IF($K17="",$E17/$R17*S17,IF(MONTH($K17)=MONTH(BX$5),$L17/$R17*S17,IF(AND($K17<BX$5,(MONTH($K17)<>MONTH(BX$5))),$L17/$R17*S17,$E17/$R17*S17)))))) -> 84.63 | BY17: =+IF(AND($J17>BY$5,MONTH($J17<>BY$5)),0,+IF(AND($J17>BY$5,MONTH($J17=BY$5)),$E17/$R17*DAY($J17),IF(AND($O17<>"",$O17<BY$5),0,IF($K17="",$E17/$R17*T17,IF(MONTH($K17)=MONTH(BY$5),$L17/$R17*T17,IF(AND($K17<BY$5,(MONTH($K17)<>MONTH(BY$5))),$L17/$R17*T17,$E17/$R17*T17)))))) -> 84.63 | BZ17: =+IF(AND($J17>BZ$5,MONTH($J17<>BZ$5)),0,+IF(AND($J17>BZ$5,MONTH($J17=BZ$5)),$E17/$R17*DAY($J17),IF(AND($O17<>"",$O17<BZ$5),0,IF($K17="",$E17/$R17*U17,IF(MONTH($K17)=MONTH(BZ$5),$L17/$R17*U17,IF(AND($K17<BZ$5,(MONTH($K17)<>MONTH(BZ$5))),$L17/$R17*U17,$E17/$R17*U17)))))) -> 84.63 | CA17: =+IF(AND($J17>CA$5,MONTH($J17<>CA$5)),0,+IF(AND($J17>CA$5,MONTH($J17=CA$5)),$E17/$R17*DAY($J17),IF(AND($O17<>"",$O17<CA$5),0,IF($K17="",$E17/$R17*V17,IF(MONTH($K17)=MONTH(CA$5),$L17/$R17*V17,IF(AND($K17<CA$5,(MONTH($K17)<>MONTH(CA$5))),$L17/$R17*V17,$E17/$R17*V17)))))) -> 84.63 | CB17: =+IF(AND($J17>CB$5,MONTH($J17<>CB$5)),0,+IF(AND($J17>CB$5,MONTH($J17=CB$5)),$E17/$R17*DAY($J17),IF(AND($O17<>"",$O17<CB$5),0,IF($K17="",$E17/$R17*W17,IF(MONTH($K17)=MONTH(CB$5),$L17/$R17*W17,IF(AND($K17<CB$5,(MONTH($K17)<>MONTH(CB$5))),$L17/$R17*W17,$E17/$R17*W17)))))) -> 84.63 | CC17: =+IF(AND($J17>CC$5,MONTH($J17<>CC$5)),0,+IF(AND($J17>CC$5,MONTH($J17=CC$5)),$E17/$R17*DAY($J17),IF(AND($O17<>"",$O17<CC$5),0,IF($K17="",$E17/$R17*X17,IF(MONTH($K17)=MONTH(CC$5),$L17/$R17*X17,IF(AND($K17<CC$5,(MONTH($K17)<>MONTH(CC$5))),$L17/$R17*X17,$E17/$R17*X17)))))) -> 84.63 | CD17: =+IF(AND($J17>CD$5,MONTH($J17<>CD$5)),0,+IF(AND($J17>CD$5,MONTH($J17=CD$5)),$E17/$R17*DAY($J17),IF(AND($O17<>"",$O17<CD$5),0,IF($K17="",$E17/$R17*Y17,IF(MONTH($K17)=MONTH(CD$5),$L17/$R17*Y17,IF(AND($K17<CD$5,(MONTH($K17)<>MONTH(CD$5))),$L17/$R17*Y17,$E17/$R17*Y17)))))) -> 84.63 | CE17: =+IF(AND($J17>CE$5,MONTH($J17<>CE$5)),0,+IF(AND($J17>CE$5,MONTH($J17=CE$5)),$E17/$R17*DAY($J17),IF(AND($O17<>"",$O17<CE$5),0,IF($K17="",$E17/$R17*Z17,IF(MONTH($K17)=MONTH(CE$5),$L17/$R17*Z17,IF(AND($K17<CE$5,(MONTH($K17)<>MONTH(CE$5))),$L17/$R17*Z17,$E17/$R17*Z17)))))) -> 84.63 | ... CI17: =+IF(AND($J17>CI$5,MONTH($J17<>CI$5)),0,+IF(AND($J17>CI$5,MONTH($J17=CI$5)),$E17/$R17*DAY($J17),IF(AND($O17<>"",$O17<CI$5),0,IF($K17="",$E17/$R17*AD17,IF(MONTH($K17)=MONTH(CI$5),$L17/$R17*AD17,IF(AND($K17<CI$5,(MONTH($K17)<>MONTH(CI$5))),$L17/$R17*AD17,$E17/$R17*AD17)))))) -> 84.63 | CJ17: =SUM(BX17:CI17) -> 1128.4 | CK17: =+IF(P17<5,18,IF(AND(P17>=5,P17<10),19,IF(AND(P17>=10,P17<15),20,IF(AND(P17>=15,P17<20),21,0)))) -> 20 | CL17: =+CM17-CJ17 -> 0 | CM17: =IF(L17=0,E17,(L17-E17+E17)) -> 1128.4
A18: 04088 | B18: MUNGWA NTSHUE SERGE | C18: Uniform Room Attendant | D18: =+VLOOKUP(A18,'[1]BDD-Avk Tx'!B:CE,82,0) -> 460 | E18: 308.1 | G18: 41153 | H18: =+IF(YEAR(G18)<YEAR($H$5),$H$4,G18) -> 45647 | I18: =+VLOOKUP(A18,'[1]BDD-Avk Tx'!B:BZ,77,0) -> CDI | J18: =+IF(I18="CDI",H18,H18+0) -> 45647 | P18: =DATEDIF(G18,$AD$6,"m")/12 -> 13.25 | Q18: 1 | R18: =SUM(S18:AD18) -> 20 | S18: =+IF(AND(AND($O18="",$P18>=10,MONTH($G18)=MONTH(S$5))),1.5+2,+IF(AND(AND($O18="",$P18>=5,MONTH($G18)=MONTH(S$5))),1.5+1,+IF(AND(AND($P18=5,$O18="",MONTH($G18)=MONTH(S$5))),1.5,+IF(AND($H18>S$5,MONTH($H18)=MONTH(S$5)),1.5/30*(S$4-DAY($H18)),+IF(AND(MONTH($H18)<MONTH(S$5),$O18=""),1.5,+IF(AND($H18=$S$5,$O18=""),1.5,IF($O18<S$5,0,IF(MONTH($O18)=MONTH(S$5),1.5/30*($O18-S$5),1.5)))))))) -> 1.5 | T18: =+IF(AND(AND($O18="",$P18>=10,MONTH($G18)=MONTH(T$5))),1.5+2,+IF(AND(AND($O18="",$P18>=5,MONTH($G18)=MONTH(T$5))),1.5+1,+IF(AND(AND($P18=5,$O18="",MONTH($G18)=MONTH(T$5))),1.5,+IF(AND($H18>T$5,MONTH($H18)=MONTH(T$5)),1.5/30*(T$4-DAY($H18)),+IF(AND(MONTH($H18)<MONTH(T$5),$O18=""),1.5,+IF(AND($H18=$S$5,$O18=""),1.5,IF($O18<T$5,0,IF(MONTH($O18)=MONTH(T$5),1.5/30*($O18-T$5),1.5)))))))) -> 1.5 | U18: =+IF(AND(AND($O18="",$P18>=10,MONTH($G18)=MONTH(U$5))),1.5+2,+IF(AND(AND($O18="",$P18>=5,MONTH($G18)=MONTH(U$5))),1.5+1,+IF(AND(AND($P18=5,$O18="",MONTH($G18)=MONTH(U$5))),1.5,+IF(AND($H18>U$5,MONTH($H18)=MONTH(U$5)),1.5/30*(U$4-DAY($H18)),+IF(AND(MONTH($H18)<MONTH(U$5),$O18=""),1.5,+IF(AND($H18=$S$5,$O18=""),1.5,IF($O18<U$5,0,IF(MONTH($O18)=MONTH(U$5),1.5/30*($O18-U$5),1.5)))))))) -> 1.5 | V18: =+IF(AND(AND($O18="",$P18>=10,MONTH($G18)=MONTH(V$5))),1.5+2,+IF(AND(AND($O18="",$P18>=5,MONTH($G18)=MONTH(V$5))),1.5+1,+IF(AND(AND($P18=5,$O18="",MONTH($G18)=MONTH(V$5))),1.5,+IF(AND($H18>V$5,MONTH($H18)=MONTH(V$5)),1.5/30*(V$4-DAY($H18)),+IF(AND(MONTH($H18)<MONTH(V$5),$O18=""),1.5,+IF(AND($H18=$S$5,$O18=""),1.5,IF($O18<V$5,0,IF(MONTH($O18)=MONTH(V$5),1.5/30*($O18-V$5),1.5)))))))) -> 1.5 | W18: =+IF(AND(AND($O18="",$P18>=10,MONTH($G18)=MONTH(W$5))),1.5+2,+IF(AND(AND($O18="",$P18>=5,MONTH($G18)=MONTH(W$5))),1.5+1,+IF(AND(AND($P18=5,$O18="",MONTH($G18)=MONTH(W$5))),1.5,+IF(AND($H18>W$5,MONTH($H18)=MONTH(W$5)),1.5/30*(W$4-DAY($H18)),+IF(AND(MONTH($H18)<MONTH(W$5),$O18=""),1.5,+IF(AND($H18=$S$5,$O18=""),1.5,IF($O18<W$5,0,IF(MONTH($O18)=MONTH(W$5),1.5/30*($O18-W$5),1.5)))))))) -> 1.5 | X18: =+IF(AND(AND($O18="",$P18>=10,MONTH($G18)=MONTH(X$5))),1.5+2,+IF(AND(AND($O18="",$P18>=5,MONTH($G18)=MONTH(X$5))),1.5+1,+IF(AND(AND($P18=5,$O18="",MONTH($G18)=MONTH(X$5))),1.5,+IF(AND($H18>X$5,MONTH($H18)=MONTH(X$5)),1.5/30*(X$4-DAY($H18)),+IF(AND(MONTH($H18)<MONTH(X$5),$O18=""),1.5,+IF(AND($H18=$S$5,$O18=""),1.5,IF($O18<X$5,0,IF(MONTH($O18)=MONTH(X$5),1.5/30*($O18-X$5),1.5)))))))) -> 1.5 | Y18: =+IF(AND(AND($O18="",$P18>=10,MONTH($G18)=MONTH(Y$5))),1.5+2,+IF(AND(AND($O18="",$P18>=5,MONTH($G18)=MONTH(Y$5))),1.5+1,+IF(AND(AND($P18=5,$O18="",MONTH($G18)=MONTH(Y$5))),1.5,+IF(AND($H18>Y$5,MONTH($H18)=MONTH(Y$5)),1.5/30*(Y$4-DAY($H18)),+IF(AND(MONTH($H18)<MONTH(Y$5),$O18=""),1.5,+IF(AND($H18=$S$5,$O18=""),1.5,IF($O18<Y$5,0,IF(MONTH($O18)=MONTH(Y$5),1.5/30*($O18-Y$5),1.5)))))))) -> 1.5 | Z18: =+IF(AND(AND($O18="",$P18>=10,MONTH($G18)=MONTH(Z$5))),1.5+2,+IF(AND(AND($O18="",$P18>=5,MONTH($G18)=MONTH(Z$5))),1.5+1,+IF(AND(AND($P18=5,$O18="",MONTH($G18)=MONTH(Z$5))),1.5,+IF(AND($H18>Z$5,MONTH($H18)=MONTH(Z$5)),1.5/30*(Z$4-DAY($H18)),+IF(AND(MONTH($H18)<MONTH(Z$5),$O18=""),1.5,+IF(AND($H18=$S$5,$O18=""),1.5,IF($O18<Z$5,0,IF(MONTH($O18)=MONTH(Z$5),1.5/30*($O18-Z$5),1.5)))))))) -> 1.5 | ... AD18: =+IF(AND(AND($O18="",$P18>=10,MONTH($G18)=MONTH(AD$5))),1.5+2,+IF(AND(AND($O18="",$P18>=5,MONTH($G18)=MONTH(AD$5))),1.5+1,+IF(AND(AND($P18=5,$O18="",MONTH($G18)=MONTH(AD$5))),1.5,+IF(AND($H18>AD$5,MONTH($H18)=MONTH(AD$5)),1.5/30*(AD$4-DAY($H18)),+IF(AND(MONTH($H18)<MONTH(AD$5),$O18=""),1.5,+IF(AND($H18=$S$5,$O18=""),1.5,IF($O18<AD$5,0,IF(MONTH($O18)=MONTH(AD$5),1.5/30*($O18-AD$5),1.5)))))))) -> 1.5 | AF18: =SUM(AG18:AR18) -> 0 | AG18: 0 | AH18: 0 | AI18: 0 | AS18: =+Q18+R18-AF18 -> 21 | AU18: 1.4807692 | AV18: =SUM(AW18:BH18) -> 237 | AW18: =+IF($K18="",$E18/26*S18,IF(MONTH($K18)=MONTH(AW$5),$L18/26*S18,IF(AND($K18<AW$5,(MONTH($K18)<>MONTH(AW$5))),$L18/26*S18,$E18/26*S18))) -> 17.775 | AX18: =+IF($K18="",$E18/26*T18,IF(MONTH($K18)=MONTH(AX$5),$L18/26*T18,IF(AND($K18<AX$5,(MONTH($K18)<>MONTH(AX$5))),$L18/26*T18,$E18/26*T18))) -> 17.775 | AY18: =+IF($K18="",$E18/26*U18,IF(MONTH($K18)=MONTH(AY$5),$L18/26*U18,IF(AND($K18<AY$5,(MONTH($K18)<>MONTH(AY$5))),$L18/26*U18,$E18/26*U18))) -> 17.775 | AZ18: =+IF($K18="",$E18/26*V18,IF(MONTH($K18)=MONTH(AZ$5),$L18/26*V18,IF(AND($K18<AZ$5,(MONTH($K18)<>MONTH(AZ$5))),$L18/26*V18,$E18/26*V18))) -> 17.775 | BA18: =+IF($K18="",$E18/26*W18,IF(MONTH($K18)=MONTH(BA$5),$L18/26*W18,IF(AND($K18<BA$5,(MONTH($K18)<>MONTH(BA$5))),$L18/26*W18,$E18/26*W18))) -> 17.775 | BB18: =+IF($K18="",$E18/26*X18,IF(MONTH($K18)=MONTH(BB$5),$L18/26*X18,IF(AND($K18<BB$5,(MONTH($K18)<>MONTH(BB$5))),$L18/26*X18,$E18/26*X18))) -> 17.775 | BC18: =+IF($K18="",$E18/26*Y18,IF(MONTH($K18)=MONTH(BC$5),$L18/26*Y18,IF(AND($K18<BC$5,(MONTH($K18)<>MONTH(BC$5))),$L18/26*Y18,$E18/26*Y18))) -> 17.775 | BD18: =+IF($K18="",$E18/26*Z18,IF(MONTH($K18)=MONTH(BD$5),$L18/26*Z18,IF(AND($K18<BD$5,(MONTH($K18)<>MONTH(BD$5))),$L18/26*Z18,$E18/26*Z18))) -> 17.775 | ... BH18: =+IF($K18="",$E18/26*AD18,IF(MONTH($K18)=MONTH(BH$5),$L18/26*AD18,IF(AND($K18<BH$5,(MONTH($K18)<>MONTH(BH$5))),$L18/26*AD18,$E18/26*AD18))) -> 17.775 | BI18: =SUM(BJ18:BU18) -> 0 | BJ18: =(+IF($K18="",$E18/26*AG18,IF(MONTH($K18)=MONTH(BJ$5),$L18/26*AG18,IF(AND($K18<BJ$5,(MONTH($K18)<>MONTH(BJ$5))),$L18/26*AG18,$E18/26*AG18))))*-1 -> 0 | BK18: =(+IF($K18="",$E18/26*AH18,IF(MONTH($K18)=MONTH(BK$5),$L18/26*AH18,IF(AND($K18<BK$5,(MONTH($K18)<>MONTH(BK$5))),$L18/26*AH18,$E18/26*AH18))))*-1 -> 0 | BL18: =(+IF($K18="",$E18/26*AI18,IF(MONTH($K18)=MONTH(BL$5),$L18/26*AI18,IF(AND($K18<BL$5,(MONTH($K18)<>MONTH(BL$5))),$L18/26*AI18,$E18/26*AI18))))*-1 -> 0 | BM18: =(+IF($K18="",$E18/26*AJ18,IF(MONTH($K18)=MONTH(BM$5),$L18/26*AJ18,IF(AND($K18<BM$5,(MONTH($K18)<>MONTH(BM$5))),$L18/26*AJ18,$E18/26*AJ18))))*-1 -> 0 | BN18: =(+IF($K18="",$E18/26*AK18,IF(MONTH($K18)=MONTH(BN$5),$L18/26*AK18,IF(AND($K18<BN$5,(MONTH($K18)<>MONTH(BN$5))),$L18/26*AK18,$E18/26*AK18))))*-1 -> 0 | BO18: =(+IF($K18="",$E18/26*AL18,IF(MONTH($K18)=MONTH(BO$5),$L18/26*AL18,IF(AND($K18<BO$5,(MONTH($K18)<>MONTH(BO$5))),$L18/26*AL18,$E18/26*AL18))))*-1 -> 0 | BP18: =(+IF($K18="",$E18/26*AM18,IF(MONTH($K18)=MONTH(BP$5),$L18/26*AM18,IF(AND($K18<BP$5,(MONTH($K18)<>MONTH(BP$5))),$L18/26*AM18,$E18/26*AM18))))*-1 -> 0 | BQ18: =(+IF($K18="",$E18/26*AN18,IF(MONTH($K18)=MONTH(BQ$5),$L18/26*AN18,IF(AND($K18<BQ$5,(MONTH($K18)<>MONTH(BQ$5))),$L18/26*AN18,$E18/26*AN18))))*-1 -> 0 | ... BU18: =(+IF($K18="",$E18/26*AR18,IF(MONTH($K18)=MONTH(BU$5),$L18/26*AR18,IF(AND($K18<BU$5,(MONTH($K18)<>MONTH(BU$5))),$L18/26*AR18,$E18/26*AR18))))*-1 -> 0 | BV18: =+AU18+AV18+BI18 -> 238.48077 | BX18: =+IF(AND($J18>BX$5,MONTH($J18<>BX$5)),0,+IF(AND($J18>BX$5,MONTH($J18=BX$5)),$E18/$R18*DAY($J18),IF(AND($O18<>"",$O18<BX$5),0,IF($K18="",$E18/$R18*S18,IF(MONTH($K18)=MONTH(BX$5),$L18/$R18*S18,IF(AND($K18<BX$5,(MONTH($K18)<>MONTH(BX$5))),$L18/$R18*S18,$E18/$R18*S18)))))) -> 23.1075 | BY18: =+IF(AND($J18>BY$5,MONTH($J18<>BY$5)),0,+IF(AND($J18>BY$5,MONTH($J18=BY$5)),$E18/$R18*DAY($J18),IF(AND($O18<>"",$O18<BY$5),0,IF($K18="",$E18/$R18*T18,IF(MONTH($K18)=MONTH(BY$5),$L18/$R18*T18,IF(AND($K18<BY$5,(MONTH($K18)<>MONTH(BY$5))),$L18/$R18*T18,$E18/$R18*T18)))))) -> 23.1075 | BZ18: =+IF(AND($J18>BZ$5,MONTH($J18<>BZ$5)),0,+IF(AND($J18>BZ$5,MONTH($J18=BZ$5)),$E18/$R18*DAY($J18),IF(AND($O18<>"",$O18<BZ$5),0,IF($K18="",$E18/$R18*U18,IF(MONTH($K18)=MONTH(BZ$5),$L18/$R18*U18,IF(AND($K18<BZ$5,(MONTH($K18)<>MONTH(BZ$5))),$L18/$R18*U18,$E18/$R18*U18)))))) -> 23.1075 | CA18: =+IF(AND($J18>CA$5,MONTH($J18<>CA$5)),0,+IF(AND($J18>CA$5,MONTH($J18=CA$5)),$E18/$R18*DAY($J18),IF(AND($O18<>"",$O18<CA$5),0,IF($K18="",$E18/$R18*V18,IF(MONTH($K18)=MONTH(CA$5),$L18/$R18*V18,IF(AND($K18<CA$5,(MONTH($K18)<>MONTH(CA$5))),$L18/$R18*V18,$E18/$R18*V18)))))) -> 23.1075 | CB18: =+IF(AND($J18>CB$5,MONTH($J18<>CB$5)),0,+IF(AND($J18>CB$5,MONTH($J18=CB$5)),$E18/$R18*DAY($J18),IF(AND($O18<>"",$O18<CB$5),0,IF($K18="",$E18/$R18*W18,IF(MONTH($K18)=MONTH(CB$5),$L18/$R18*W18,IF(AND($K18<CB$5,(MONTH($K18)<>MONTH(CB$5))),$L18/$R18*W18,$E18/$R18*W18)))))) -> 23.1075 | CC18: =+IF(AND($J18>CC$5,MONTH($J18<>CC$5)),0,+IF(AND($J18>CC$5,MONTH($J18=CC$5)),$E18/$R18*DAY($J18),IF(AND($O18<>"",$O18<CC$5),0,IF($K18="",$E18/$R18*X18,IF(MONTH($K18)=MONTH(CC$5),$L18/$R18*X18,IF(AND($K18<CC$5,(MONTH($K18)<>MONTH(CC$5))),$L18/$R18*X18,$E18/$R18*X18)))))) -> 23.1075 | CD18: =+IF(AND($J18>CD$5,MONTH($J18<>CD$5)),0,+IF(AND($J18>CD$5,MONTH($J18=CD$5)),$E18/$R18*DAY($J18),IF(AND($O18<>"",$O18<CD$5),0,IF($K18="",$E18/$R18*Y18,IF(MONTH($K18)=MONTH(CD$5),$L18/$R18*Y18,IF(AND($K18<CD$5,(MONTH($K18)<>MONTH(CD$5))),$L18/$R18*Y18,$E18/$R18*Y18)))))) -> 23.1075 | CE18: =+IF(AND($J18>CE$5,MONTH($J18<>CE$5)),0,+IF(AND($J18>CE$5,MONTH($J18=CE$5)),$E18/$R18*DAY($J18),IF(AND($O18<>"",$O18<CE$5),0,IF($K18="",$E18/$R18*Z18,IF(MONTH($K18)=MONTH(CE$5),$L18/$R18*Z18,IF(AND($K18<CE$5,(MONTH($K18)<>MONTH(CE$5))),$L18/$R18*Z18,$E18/$R18*Z18)))))) -> 23.1075 | ... CI18: =+IF(AND($J18>CI$5,MONTH($J18<>CI$5)),0,+IF(AND($J18>CI$5,MONTH($J18=CI$5)),$E18/$R18*DAY($J18),IF(AND($O18<>"",$O18<CI$5),0,IF($K18="",$E18/$R18*AD18,IF(MONTH($K18)=MONTH(CI$5),$L18/$R18*AD18,IF(AND($K18<CI$5,(MONTH($K18)<>MONTH(CI$5))),$L18/$R18*AD18,$E18/$R18*AD18)))))) -> 23.1075 | CJ18: =SUM(BX18:CI18) -> 308.1 | CK18: =+IF(P18<5,18,IF(AND(P18>=5,P18<10),19,IF(AND(P18>=10,P18<15),20,IF(AND(P18>=15,P18<20),21,0)))) -> 20 | CL18: =+CM18-CJ18 -> 0 | CM18: =IF(L18=0,E18,(L18-E18+E18)) -> 308.1
A19: 04102 | B19: NSIMBA LUFOKO PLATINI | C19: Laundry Attendant | D19: =+VLOOKUP(A19,'[1]BDD-Avk Tx'!B:CE,82,0) -> 460 | E19: 200.2 | G19: 41153 | H19: =+IF(YEAR(G19)<YEAR($H$5),$H$4,G19) -> 45647 | I19: =+VLOOKUP(A19,'[1]BDD-Avk Tx'!B:BZ,77,0) -> CDI | J19: =+IF(I19="CDI",H19,H19+0) -> 45647 | P19: =DATEDIF(G19,$AD$6,"m")/12 -> 13.25 | Q19: 0 | R19: =SUM(S19:AD19) -> 20 | S19: =+IF(AND(AND($O19="",$P19>=10,MONTH($G19)=MONTH(S$5))),1.5+2,+IF(AND(AND($O19="",$P19>=5,MONTH($G19)=MONTH(S$5))),1.5+1,+IF(AND(AND($P19=5,$O19="",MONTH($G19)=MONTH(S$5))),1.5,+IF(AND($H19>S$5,MONTH($H19)=MONTH(S$5)),1.5/30*(S$4-DAY($H19)),+IF(AND(MONTH($H19)<MONTH(S$5),$O19=""),1.5,+IF(AND($H19=$S$5,$O19=""),1.5,IF($O19<S$5,0,IF(MONTH($O19)=MONTH(S$5),1.5/30*($O19-S$5),1.5)))))))) -> 1.5 | T19: =+IF(AND(AND($O19="",$P19>=10,MONTH($G19)=MONTH(T$5))),1.5+2,+IF(AND(AND($O19="",$P19>=5,MONTH($G19)=MONTH(T$5))),1.5+1,+IF(AND(AND($P19=5,$O19="",MONTH($G19)=MONTH(T$5))),1.5,+IF(AND($H19>T$5,MONTH($H19)=MONTH(T$5)),1.5/30*(T$4-DAY($H19)),+IF(AND(MONTH($H19)<MONTH(T$5),$O19=""),1.5,+IF(AND($H19=$S$5,$O19=""),1.5,IF($O19<T$5,0,IF(MONTH($O19)=MONTH(T$5),1.5/30*($O19-T$5),1.5)))))))) -> 1.5 | U19: =+IF(AND(AND($O19="",$P19>=10,MONTH($G19)=MONTH(U$5))),1.5+2,+IF(AND(AND($O19="",$P19>=5,MONTH($G19)=MONTH(U$5))),1.5+1,+IF(AND(AND($P19=5,$O19="",MONTH($G19)=MONTH(U$5))),1.5,+IF(AND($H19>U$5,MONTH($H19)=MONTH(U$5)),1.5/30*(U$4-DAY($H19)),+IF(AND(MONTH($H19)<MONTH(U$5),$O19=""),1.5,+IF(AND($H19=$S$5,$O19=""),1.5,IF($O19<U$5,0,IF(MONTH($O19)=MONTH(U$5),1.5/30*($O19-U$5),1.5)))))))) -> 1.5 | V19: =+IF(AND(AND($O19="",$P19>=10,MONTH($G19)=MONTH(V$5))),1.5+2,+IF(AND(AND($O19="",$P19>=5,MONTH($G19)=MONTH(V$5))),1.5+1,+IF(AND(AND($P19=5,$O19="",MONTH($G19)=MONTH(V$5))),1.5,+IF(AND($H19>V$5,MONTH($H19)=MONTH(V$5)),1.5/30*(V$4-DAY($H19)),+IF(AND(MONTH($H19)<MONTH(V$5),$O19=""),1.5,+IF(AND($H19=$S$5,$O19=""),1.5,IF($O19<V$5,0,IF(MONTH($O19)=MONTH(V$5),1.5/30*($O19-V$5),1.5)))))))) -> 1.5 | W19: =+IF(AND(AND($O19="",$P19>=10,MONTH($G19)=MONTH(W$5))),1.5+2,+IF(AND(AND($O19="",$P19>=5,MONTH($G19)=MONTH(W$5))),1.5+1,+IF(AND(AND($P19=5,$O19="",MONTH($G19)=MONTH(W$5))),1.5,+IF(AND($H19>W$5,MONTH($H19)=MONTH(W$5)),1.5/30*(W$4-DAY($H19)),+IF(AND(MONTH($H19)<MONTH(W$5),$O19=""),1.5,+IF(AND($H19=$S$5,$O19=""),1.5,IF($O19<W$5,0,IF(MONTH($O19)=MONTH(W$5),1.5/30*($O19-W$5),1.5)))))))) -> 1.5 | X19: =+IF(AND(AND($O19="",$P19>=10,MONTH($G19)=MONTH(X$5))),1.5+2,+IF(AND(AND($O19="",$P19>=5,MONTH($G19)=MONTH(X$5))),1.5+1,+IF(AND(AND($P19=5,$O19="",MONTH($G19)=MONTH(X$5))),1.5,+IF(AND($H19>X$5,MONTH($H19)=MONTH(X$5)),1.5/30*(X$4-DAY($H19)),+IF(AND(MONTH($H19)<MONTH(X$5),$O19=""),1.5,+IF(AND($H19=$S$5,$O19=""),1.5,IF($O19<X$5,0,IF(MONTH($O19)=MONTH(X$5),1.5/30*($O19-X$5),1.5)))))))) -> 1.5 | Y19: =+IF(AND(AND($O19="",$P19>=10,MONTH($G19)=MONTH(Y$5))),1.5+2,+IF(AND(AND($O19="",$P19>=5,MONTH($G19)=MONTH(Y$5))),1.5+1,+IF(AND(AND($P19=5,$O19="",MONTH($G19)=MONTH(Y$5))),1.5,+IF(AND($H19>Y$5,MONTH($H19)=MONTH(Y$5)),1.5/30*(Y$4-DAY($H19)),+IF(AND(MONTH($H19)<MONTH(Y$5),$O19=""),1.5,+IF(AND($H19=$S$5,$O19=""),1.5,IF($O19<Y$5,0,IF(MONTH($O19)=MONTH(Y$5),1.5/30*($O19-Y$5),1.5)))))))) -> 1.5 | Z19: =+IF(AND(AND($O19="",$P19>=10,MONTH($G19)=MONTH(Z$5))),1.5+2,+IF(AND(AND($O19="",$P19>=5,MONTH($G19)=MONTH(Z$5))),1.5+1,+IF(AND(AND($P19=5,$O19="",MONTH($G19)=MONTH(Z$5))),1.5,+IF(AND($H19>Z$5,MONTH($H19)=MONTH(Z$5)),1.5/30*(Z$4-DAY($H19)),+IF(AND(MONTH($H19)<MONTH(Z$5),$O19=""),1.5,+IF(AND($H19=$S$5,$O19=""),1.5,IF($O19<Z$5,0,IF(MONTH($O19)=MONTH(Z$5),1.5/30*($O19-Z$5),1.5)))))))) -> 1.5 | ... AD19: =+IF(AND(AND($O19="",$P19>=10,MONTH($G19)=MONTH(AD$5))),1.5+2,+IF(AND(AND($O19="",$P19>=5,MONTH($G19)=MONTH(AD$5))),1.5+1,+IF(AND(AND($P19=5,$O19="",MONTH($G19)=MONTH(AD$5))),1.5,+IF(AND($H19>AD$5,MONTH($H19)=MONTH(AD$5)),1.5/30*(AD$4-DAY($H19)),+IF(AND(MONTH($H19)<MONTH(AD$5),$O19=""),1.5,+IF(AND($H19=$S$5,$O19=""),1.5,IF($O19<AD$5,0,IF(MONTH($O19)=MONTH(AD$5),1.5/30*($O19-AD$5),1.5)))))))) -> 1.5 | AF19: =SUM(AG19:AR19) -> 0 | AG19: 0 | AH19: 0 | AI19: 0 | AS19: =+Q19+R19-AF19 -> 20 | AU19: -6.2192308 | AV19: =SUM(AW19:BH19) -> 154 | AW19: =+IF($K19="",$E19/26*S19,IF(MONTH($K19)=MONTH(AW$5),$L19/26*S19,IF(AND($K19<AW$5,(MONTH($K19)<>MONTH(AW$5))),$L19/26*S19,$E19/26*S19))) -> 11.55 | AX19: =+IF($K19="",$E19/26*T19,IF(MONTH($K19)=MONTH(AX$5),$L19/26*T19,IF(AND($K19<AX$5,(MONTH($K19)<>MONTH(AX$5))),$L19/26*T19,$E19/26*T19))) -> 11.55 | AY19: =+IF($K19="",$E19/26*U19,IF(MONTH($K19)=MONTH(AY$5),$L19/26*U19,IF(AND($K19<AY$5,(MONTH($K19)<>MONTH(AY$5))),$L19/26*U19,$E19/26*U19))) -> 11.55 | AZ19: =+IF($K19="",$E19/26*V19,IF(MONTH($K19)=MONTH(AZ$5),$L19/26*V19,IF(AND($K19<AZ$5,(MONTH($K19)<>MONTH(AZ$5))),$L19/26*V19,$E19/26*V19))) -> 11.55 | BA19: =+IF($K19="",$E19/26*W19,IF(MONTH($K19)=MONTH(BA$5),$L19/26*W19,IF(AND($K19<BA$5,(MONTH($K19)<>MONTH(BA$5))),$L19/26*W19,$E19/26*W19))) -> 11.55 | BB19: =+IF($K19="",$E19/26*X19,IF(MONTH($K19)=MONTH(BB$5),$L19/26*X19,IF(AND($K19<BB$5,(MONTH($K19)<>MONTH(BB$5))),$L19/26*X19,$E19/26*X19))) -> 11.55 | BC19: =+IF($K19="",$E19/26*Y19,IF(MONTH($K19)=MONTH(BC$5),$L19/26*Y19,IF(AND($K19<BC$5,(MONTH($K19)<>MONTH(BC$5))),$L19/26*Y19,$E19/26*Y19))) -> 11.55 | BD19: =+IF($K19="",$E19/26*Z19,IF(MONTH($K19)=MONTH(BD$5),$L19/26*Z19,IF(AND($K19<BD$5,(MONTH($K19)<>MONTH(BD$5))),$L19/26*Z19,$E19/26*Z19))) -> 11.55 | ... BH19: =+IF($K19="",$E19/26*AD19,IF(MONTH($K19)=MONTH(BH$5),$L19/26*AD19,IF(AND($K19<BH$5,(MONTH($K19)<>MONTH(BH$5))),$L19/26*AD19,$E19/26*AD19))) -> 11.55 | BI19: =SUM(BJ19:BU19) -> 0 | BJ19: =(+IF($K19="",$E19/26*AG19,IF(MONTH($K19)=MONTH(BJ$5),$L19/26*AG19,IF(AND($K19<BJ$5,(MONTH($K19)<>MONTH(BJ$5))),$L19/26*AG19,$E19/26*AG19))))*-1 -> 0 | BK19: =(+IF($K19="",$E19/26*AH19,IF(MONTH($K19)=MONTH(BK$5),$L19/26*AH19,IF(AND($K19<BK$5,(MONTH($K19)<>MONTH(BK$5))),$L19/26*AH19,$E19/26*AH19))))*-1 -> 0 | BL19: =(+IF($K19="",$E19/26*AI19,IF(MONTH($K19)=MONTH(BL$5),$L19/26*AI19,IF(AND($K19<BL$5,(MONTH($K19)<>MONTH(BL$5))),$L19/26*AI19,$E19/26*AI19))))*-1 -> 0 | BM19: =(+IF($K19="",$E19/26*AJ19,IF(MONTH($K19)=MONTH(BM$5),$L19/26*AJ19,IF(AND($K19<BM$5,(MONTH($K19)<>MONTH(BM$5))),$L19/26*AJ19,$E19/26*AJ19))))*-1 -> 0 | BN19: =(+IF($K19="",$E19/26*AK19,IF(MONTH($K19)=MONTH(BN$5),$L19/26*AK19,IF(AND($K19<BN$5,(MONTH($K19)<>MONTH(BN$5))),$L19/26*AK19,$E19/26*AK19))))*-1 -> 0 | BO19: =(+IF($K19="",$E19/26*AL19,IF(MONTH($K19)=MONTH(BO$5),$L19/26*AL19,IF(AND($K19<BO$5,(MONTH($K19)<>MONTH(BO$5))),$L19/26*AL19,$E19/26*AL19))))*-1 -> 0 | BP19: =(+IF($K19="",$E19/26*AM19,IF(MONTH($K19)=MONTH(BP$5),$L19/26*AM19,IF(AND($K19<BP$5,(MONTH($K19)<>MONTH(BP$5))),$L19/26*AM19,$E19/26*AM19))))*-1 -> 0 | BQ19: =(+IF($K19="",$E19/26*AN19,IF(MONTH($K19)=MONTH(BQ$5),$L19/26*AN19,IF(AND($K19<BQ$5,(MONTH($K19)<>MONTH(BQ$5))),$L19/26*AN19,$E19/26*AN19))))*-1 -> 0 | ... BU19: =(+IF($K19="",$E19/26*AR19,IF(MONTH($K19)=MONTH(BU$5),$L19/26*AR19,IF(AND($K19<BU$5,(MONTH($K19)<>MONTH(BU$5))),$L19/26*AR19,$E19/26*AR19))))*-1 -> 0 | BV19: =+AU19+AV19+BI19 -> 147.78077 | BX19: =+IF(AND($J19>BX$5,MONTH($J19<>BX$5)),0,+IF(AND($J19>BX$5,MONTH($J19=BX$5)),$E19/$R19*DAY($J19),IF(AND($O19<>"",$O19<BX$5),0,IF($K19="",$E19/$R19*S19,IF(MONTH($K19)=MONTH(BX$5),$L19/$R19*S19,IF(AND($K19<BX$5,(MONTH($K19)<>MONTH(BX$5))),$L19/$R19*S19,$E19/$R19*S19)))))) -> 15.015 | BY19: =+IF(AND($J19>BY$5,MONTH($J19<>BY$5)),0,+IF(AND($J19>BY$5,MONTH($J19=BY$5)),$E19/$R19*DAY($J19),IF(AND($O19<>"",$O19<BY$5),0,IF($K19="",$E19/$R19*T19,IF(MONTH($K19)=MONTH(BY$5),$L19/$R19*T19,IF(AND($K19<BY$5,(MONTH($K19)<>MONTH(BY$5))),$L19/$R19*T19,$E19/$R19*T19)))))) -> 15.015 | BZ19: =+IF(AND($J19>BZ$5,MONTH($J19<>BZ$5)),0,+IF(AND($J19>BZ$5,MONTH($J19=BZ$5)),$E19/$R19*DAY($J19),IF(AND($O19<>"",$O19<BZ$5),0,IF($K19="",$E19/$R19*U19,IF(MONTH($K19)=MONTH(BZ$5),$L19/$R19*U19,IF(AND($K19<BZ$5,(MONTH($K19)<>MONTH(BZ$5))),$L19/$R19*U19,$E19/$R19*U19)))))) -> 15.015 | CA19: =+IF(AND($J19>CA$5,MONTH($J19<>CA$5)),0,+IF(AND($J19>CA$5,MONTH($J19=CA$5)),$E19/$R19*DAY($J19),IF(AND($O19<>"",$O19<CA$5),0,IF($K19="",$E19/$R19*V19,IF(MONTH($K19)=MONTH(CA$5),$L19/$R19*V19,IF(AND($K19<CA$5,(MONTH($K19)<>MONTH(CA$5))),$L19/$R19*V19,$E19/$R19*V19)))))) -> 15.015 | CB19: =+IF(AND($J19>CB$5,MONTH($J19<>CB$5)),0,+IF(AND($J19>CB$5,MONTH($J19=CB$5)),$E19/$R19*DAY($J19),IF(AND($O19<>"",$O19<CB$5),0,IF($K19="",$E19/$R19*W19,IF(MONTH($K19)=MONTH(CB$5),$L19/$R19*W19,IF(AND($K19<CB$5,(MONTH($K19)<>MONTH(CB$5))),$L19/$R19*W19,$E19/$R19*W19)))))) -> 15.015 | CC19: =+IF(AND($J19>CC$5,MONTH($J19<>CC$5)),0,+IF(AND($J19>CC$5,MONTH($J19=CC$5)),$E19/$R19*DAY($J19),IF(AND($O19<>"",$O19<CC$5),0,IF($K19="",$E19/$R19*X19,IF(MONTH($K19)=MONTH(CC$5),$L19/$R19*X19,IF(AND($K19<CC$5,(MONTH($K19)<>MONTH(CC$5))),$L19/$R19*X19,$E19/$R19*X19)))))) -> 15.015 | CD19: =+IF(AND($J19>CD$5,MONTH($J19<>CD$5)),0,+IF(AND($J19>CD$5,MONTH($J19=CD$5)),$E19/$R19*DAY($J19),IF(AND($O19<>"",$O19<CD$5),0,IF($K19="",$E19/$R19*Y19,IF(MONTH($K19)=MONTH(CD$5),$L19/$R19*Y19,IF(AND($K19<CD$5,(MONTH($K19)<>MONTH(CD$5))),$L19/$R19*Y19,$E19/$R19*Y19)))))) -> 15.015 | CE19: =+IF(AND($J19>CE$5,MONTH($J19<>CE$5)),0,+IF(AND($J19>CE$5,MONTH($J19=CE$5)),$E19/$R19*DAY($J19),IF(AND($O19<>"",$O19<CE$5),0,IF($K19="",$E19/$R19*Z19,IF(MONTH($K19)=MONTH(CE$5),$L19/$R19*Z19,IF(AND($K19<CE$5,(MONTH($K19)<>MONTH(CE$5))),$L19/$R19*Z19,$E19/$R19*Z19)))))) -> 15.015 | ... CI19: =+IF(AND($J19>CI$5,MONTH($J19<>CI$5)),0,+IF(AND($J19>CI$5,MONTH($J19=CI$5)),$E19/$R19*DAY($J19),IF(AND($O19<>"",$O19<CI$5),0,IF($K19="",$E19/$R19*AD19,IF(MONTH($K19)=MONTH(CI$5),$L19/$R19*AD19,IF(AND($K19<CI$5,(MONTH($K19)<>MONTH(CI$5))),$L19/$R19*AD19,$E19/$R19*AD19)))))) -> 15.015 | CJ19: =SUM(BX19:CI19) -> 200.2 | CK19: =+IF(P19<5,18,IF(AND(P19>=5,P19<10),19,IF(AND(P19>=10,P19<15),20,IF(AND(P19>=15,P19<20),21,0)))) -> 20 | CL19: =+CM19-CJ19 -> 0 | CM19: =IF(L19=0,E19,(L19-E19+E19)) -> 200.2
... A210: 07288 | B210: MUNDIDI MUNANGI AIME | C210: Night Auditor | D210: =+VLOOKUP(A210,'[1]BDD-Avk Tx'!B:CE,82,0) -> 620 | E210: 412.1 | G210: 44987 | H210: =+IF(YEAR(G210)<YEAR($H$5),$H$4,G210) -> 45647 | I210: =+VLOOKUP(A210,'[1]BDD-Avk Tx'!B:BZ,77,0) -> CDI | J210: =+IF(I210="CDI",H210,H210+0) -> 45647 | P210: =DATEDIF(G210,$AD$6,"m")/12 -> 2.75 | Q210: 18.8 | R210: =SUM(S210:AD210) -> 18 | S210: =+IF(AND(AND($O210="",$P210>=10,MONTH($G210)=MONTH(S$5))),1.5+2,+IF(AND(AND($O210="",$P210>=5,MONTH($G210)=MONTH(S$5))),1.5+1,+IF(AND(AND($P210=5,$O210="",MONTH($G210)=MONTH(S$5))),1.5,+IF(AND($H210>S$5,MONTH($H210)=MONTH(S$5)),1.5/30*(S$4-DAY($H210)),+IF(AND(MONTH($H210)<MONTH(S$5),$O210=""),1.5,+IF(AND($H210=$S$5,$O210=""),1.5,IF($O210<S$5,0,IF(MONTH($O210)=MONTH(S$5),1.5/30*($O210-S$5),1.5)))))))) -> 1.5 | T210: =+IF(AND(AND($O210="",$P210>=10,MONTH($G210)=MONTH(T$5))),1.5+2,+IF(AND(AND($O210="",$P210>=5,MONTH($G210)=MONTH(T$5))),1.5+1,+IF(AND(AND($P210=5,$O210="",MONTH($G210)=MONTH(T$5))),1.5,+IF(AND($H210>T$5,MONTH($H210)=MONTH(T$5)),1.5/30*(T$4-DAY($H210)),+IF(AND(MONTH($H210)<MONTH(T$5),$O210=""),1.5,+IF(AND($H210=$S$5,$O210=""),1.5,IF($O210<T$5,0,IF(MONTH($O210)=MONTH(T$5),1.5/30*($O210-T$5),1.5)))))))) -> 1.5 | U210: =+IF(AND(AND($O210="",$P210>=10,MONTH($G210)=MONTH(U$5))),1.5+2,+IF(AND(AND($O210="",$P210>=5,MONTH($G210)=MONTH(U$5))),1.5+1,+IF(AND(AND($P210=5,$O210="",MONTH($G210)=MONTH(U$5))),1.5,+IF(AND($H210>U$5,MONTH($H210)=MONTH(U$5)),1.5/30*(U$4-DAY($H210)),+IF(AND(MONTH($H210)<MONTH(U$5),$O210=""),1.5,+IF(AND($H210=$S$5,$O210=""),1.5,IF($O210<U$5,0,IF(MONTH($O210)=MONTH(U$5),1.5/30*($O210-U$5),1.5)))))))) -> 1.5 | V210: =+IF(AND(AND($O210="",$P210>=10,MONTH($G210)=MONTH(V$5))),1.5+2,+IF(AND(AND($O210="",$P210>=5,MONTH($G210)=MONTH(V$5))),1.5+1,+IF(AND(AND($P210=5,$O210="",MONTH($G210)=MONTH(V$5))),1.5,+IF(AND($H210>V$5,MONTH($H210)=MONTH(V$5)),1.5/30*(V$4-DAY($H210)),+IF(AND(MONTH($H210)<MONTH(V$5),$O210=""),1.5,+IF(AND($H210=$S$5,$O210=""),1.5,IF($O210<V$5,0,IF(MONTH($O210)=MONTH(V$5),1.5/30*($O210-V$5),1.5)))))))) -> 1.5 | W210: =+IF(AND(AND($O210="",$P210>=10,MONTH($G210)=MONTH(W$5))),1.5+2,+IF(AND(AND($O210="",$P210>=5,MONTH($G210)=MONTH(W$5))),1.5+1,+IF(AND(AND($P210=5,$O210="",MONTH($G210)=MONTH(W$5))),1.5,+IF(AND($H210>W$5,MONTH($H210)=MONTH(W$5)),1.5/30*(W$4-DAY($H210)),+IF(AND(MONTH($H210)<MONTH(W$5),$O210=""),1.5,+IF(AND($H210=$S$5,$O210=""),1.5,IF($O210<W$5,0,IF(MONTH($O210)=MONTH(W$5),1.5/30*($O210-W$5),1.5)))))))) -> 1.5 | X210: =+IF(AND(AND($O210="",$P210>=10,MONTH($G210)=MONTH(X$5))),1.5+2,+IF(AND(AND($O210="",$P210>=5,MONTH($G210)=MONTH(X$5))),1.5+1,+IF(AND(AND($P210=5,$O210="",MONTH($G210)=MONTH(X$5))),1.5,+IF(AND($H210>X$5,MONTH($H210)=MONTH(X$5)),1.5/30*(X$4-DAY($H210)),+IF(AND(MONTH($H210)<MONTH(X$5),$O210=""),1.5,+IF(AND($H210=$S$5,$O210=""),1.5,IF($O210<X$5,0,IF(MONTH($O210)=MONTH(X$5),1.5/30*($O210-X$5),1.5)))))))) -> 1.5 | Y210: =+IF(AND(AND($O210="",$P210>=10,MONTH($G210)=MONTH(Y$5))),1.5+2,+IF(AND(AND($O210="",$P210>=5,MONTH($G210)=MONTH(Y$5))),1.5+1,+IF(AND(AND($P210=5,$O210="",MONTH($G210)=MONTH(Y$5))),1.5,+IF(AND($H210>Y$5,MONTH($H210)=MONTH(Y$5)),1.5/30*(Y$4-DAY($H210)),+IF(AND(MONTH($H210)<MONTH(Y$5),$O210=""),1.5,+IF(AND($H210=$S$5,$O210=""),1.5,IF($O210<Y$5,0,IF(MONTH($O210)=MONTH(Y$5),1.5/30*($O210-Y$5),1.5)))))))) -> 1.5 | Z210: =+IF(AND(AND($O210="",$P210>=10,MONTH($G210)=MONTH(Z$5))),1.5+2,+IF(AND(AND($O210="",$P210>=5,MONTH($G210)=MONTH(Z$5))),1.5+1,+IF(AND(AND($P210=5,$O210="",MONTH($G210)=MONTH(Z$5))),1.5,+IF(AND($H210>Z$5,MONTH($H210)=MONTH(Z$5)),1.5/30*(Z$4-DAY($H210)),+IF(AND(MONTH($H210)<MONTH(Z$5),$O210=""),1.5,+IF(AND($H210=$S$5,$O210=""),1.5,IF($O210<Z$5,0,IF(MONTH($O210)=MONTH(Z$5),1.5/30*($O210-Z$5),1.5)))))))) -> 1.5 | ... AD210: =+IF(AND(AND($O210="",$P210>=10,MONTH($G210)=MONTH(AD$5))),1.5+2,+IF(AND(AND($O210="",$P210>=5,MONTH($G210)=MONTH(AD$5))),1.5+1,+IF(AND(AND($P210=5,$O210="",MONTH($G210)=MONTH(AD$5))),1.5,+IF(AND($H210>AD$5,MONTH($H210)=MONTH(AD$5)),1.5/30*(AD$4-DAY($H210)),+IF(AND(MONTH($H210)<MONTH(AD$5),$O210=""),1.5,+IF(AND($H210=$S$5,$O210=""),1.5,IF($O210<AD$5,0,IF(MONTH($O210)=MONTH(AD$5),1.5/30*($O210-AD$5),1.5)))))))) -> 1.5 | AF210: =SUM(AG210:AR210) -> 0 | AG210: 0 | AH210: 0 | AI210: 0 | AS210: =+Q210+R210-AF210 -> 36.8 | AU210: 296.70019 | AV210: =SUM(AW210:BH210) -> 285.3 | AW210: =+IF($K210="",$E210/26*S210,IF(MONTH($K210)=MONTH(AW$5),$L210/26*S210,IF(AND($K210<AW$5,(MONTH($K210)<>MONTH(AW$5))),$L210/26*S210,$E210/26*S210))) -> 23.775 | AX210: =+IF($K210="",$E210/26*T210,IF(MONTH($K210)=MONTH(AX$5),$L210/26*T210,IF(AND($K210<AX$5,(MONTH($K210)<>MONTH(AX$5))),$L210/26*T210,$E210/26*T210))) -> 23.775 | AY210: =+IF($K210="",$E210/26*U210,IF(MONTH($K210)=MONTH(AY$5),$L210/26*U210,IF(AND($K210<AY$5,(MONTH($K210)<>MONTH(AY$5))),$L210/26*U210,$E210/26*U210))) -> 23.775 | AZ210: =+IF($K210="",$E210/26*V210,IF(MONTH($K210)=MONTH(AZ$5),$L210/26*V210,IF(AND($K210<AZ$5,(MONTH($K210)<>MONTH(AZ$5))),$L210/26*V210,$E210/26*V210))) -> 23.775 | BA210: =+IF($K210="",$E210/26*W210,IF(MONTH($K210)=MONTH(BA$5),$L210/26*W210,IF(AND($K210<BA$5,(MONTH($K210)<>MONTH(BA$5))),$L210/26*W210,$E210/26*W210))) -> 23.775 | BB210: =+IF($K210="",$E210/26*X210,IF(MONTH($K210)=MONTH(BB$5),$L210/26*X210,IF(AND($K210<BB$5,(MONTH($K210)<>MONTH(BB$5))),$L210/26*X210,$E210/26*X210))) -> 23.775 | BC210: =+IF($K210="",$E210/26*Y210,IF(MONTH($K210)=MONTH(BC$5),$L210/26*Y210,IF(AND($K210<BC$5,(MONTH($K210)<>MONTH(BC$5))),$L210/26*Y210,$E210/26*Y210))) -> 23.775 | BD210: =+IF($K210="",$E210/26*Z210,IF(MONTH($K210)=MONTH(BD$5),$L210/26*Z210,IF(AND($K210<BD$5,(MONTH($K210)<>MONTH(BD$5))),$L210/26*Z210,$E210/26*Z210))) -> 23.775 | ... BH210: =+IF($K210="",$E210/26*AD210,IF(MONTH($K210)=MONTH(BH$5),$L210/26*AD210,IF(AND($K210<BH$5,(MONTH($K210)<>MONTH(BH$5))),$L210/26*AD210,$E210/26*AD210))) -> 23.775 | BI210: =SUM(BJ210:BU210) -> 0 | BJ210: =(+IF($K210="",$E210/26*AG210,IF(MONTH($K210)=MONTH(BJ$5),$L210/26*AG210,IF(AND($K210<BJ$5,(MONTH($K210)<>MONTH(BJ$5))),$L210/26*AG210,$E210/26*AG210))))*-1 -> 0 | BK210: =(+IF($K210="",$E210/26*AH210,IF(MONTH($K210)=MONTH(BK$5),$L210/26*AH210,IF(AND($K210<BK$5,(MONTH($K210)<>MONTH(BK$5))),$L210/26*AH210,$E210/26*AH210))))*-1 -> 0 | BL210: =(+IF($K210="",$E210/26*AI210,IF(MONTH($K210)=MONTH(BL$5),$L210/26*AI210,IF(AND($K210<BL$5,(MONTH($K210)<>MONTH(BL$5))),$L210/26*AI210,$E210/26*AI210))))*-1 -> 0 | BM210: =(+IF($K210="",$E210/26*AJ210,IF(MONTH($K210)=MONTH(BM$5),$L210/26*AJ210,IF(AND($K210<BM$5,(MONTH($K210)<>MONTH(BM$5))),$L210/26*AJ210,$E210/26*AJ210))))*-1 -> 0 | BN210: =(+IF($K210="",$E210/26*AK210,IF(MONTH($K210)=MONTH(BN$5),$L210/26*AK210,IF(AND($K210<BN$5,(MONTH($K210)<>MONTH(BN$5))),$L210/26*AK210,$E210/26*AK210))))*-1 -> 0 | BO210: =(+IF($K210="",$E210/26*AL210,IF(MONTH($K210)=MONTH(BO$5),$L210/26*AL210,IF(AND($K210<BO$5,(MONTH($K210)<>MONTH(BO$5))),$L210/26*AL210,$E210/26*AL210))))*-1 -> 0 | BP210: =(+IF($K210="",$E210/26*AM210,IF(MONTH($K210)=MONTH(BP$5),$L210/26*AM210,IF(AND($K210<BP$5,(MONTH($K210)<>MONTH(BP$5))),$L210/26*AM210,$E210/26*AM210))))*-1 -> 0 | BQ210: =(+IF($K210="",$E210/26*AN210,IF(MONTH($K210)=MONTH(BQ$5),$L210/26*AN210,IF(AND($K210<BQ$5,(MONTH($K210)<>MONTH(BQ$5))),$L210/26*AN210,$E210/26*AN210))))*-1 -> 0 | ... BU210: =(+IF($K210="",$E210/26*AR210,IF(MONTH($K210)=MONTH(BU$5),$L210/26*AR210,IF(AND($K210<BU$5,(MONTH($K210)<>MONTH(BU$5))),$L210/26*AR210,$E210/26*AR210))))*-1 -> 0 | BV210: =+AU210+AV210+BI210 -> 582.00019 | BX210: =+IF(AND($J210>BX$5,MONTH($J210<>BX$5)),0,+IF(AND($J210>BX$5,MONTH($J210=BX$5)),$E210/$R210*DAY($J210),IF(AND($O210<>"",$O210<BX$5),0,IF($K210="",$E210/$R210*S210,IF(MONTH($K210)=MONTH(BX$5),$L210/$R210*S210,IF(AND($K210<BX$5,(MONTH($K210)<>MONTH(BX$5))),$L210/$R210*S210,$E210/$R210*S210)))))) -> 34.341667 | BY210: =+IF(AND($J210>BY$5,MONTH($J210<>BY$5)),0,+IF(AND($J210>BY$5,MONTH($J210=BY$5)),$E210/$R210*DAY($J210),IF(AND($O210<>"",$O210<BY$5),0,IF($K210="",$E210/$R210*T210,IF(MONTH($K210)=MONTH(BY$5),$L210/$R210*T210,IF(AND($K210<BY$5,(MONTH($K210)<>MONTH(BY$5))),$L210/$R210*T210,$E210/$R210*T210)))))) -> 34.341667 | BZ210: =+IF(AND($J210>BZ$5,MONTH($J210<>BZ$5)),0,+IF(AND($J210>BZ$5,MONTH($J210=BZ$5)),$E210/$R210*DAY($J210),IF(AND($O210<>"",$O210<BZ$5),0,IF($K210="",$E210/$R210*U210,IF(MONTH($K210)=MONTH(BZ$5),$L210/$R210*U210,IF(AND($K210<BZ$5,(MONTH($K210)<>MONTH(BZ$5))),$L210/$R210*U210,$E210/$R210*U210)))))) -> 34.341667 | CA210: =+IF(AND($J210>CA$5,MONTH($J210<>CA$5)),0,+IF(AND($J210>CA$5,MONTH($J210=CA$5)),$E210/$R210*DAY($J210),IF(AND($O210<>"",$O210<CA$5),0,IF($K210="",$E210/$R210*V210,IF(MONTH($K210)=MONTH(CA$5),$L210/$R210*V210,IF(AND($K210<CA$5,(MONTH($K210)<>MONTH(CA$5))),$L210/$R210*V210,$E210/$R210*V210)))))) -> 34.341667 | CB210: =+IF(AND($J210>CB$5,MONTH($J210<>CB$5)),0,+IF(AND($J210>CB$5,MONTH($J210=CB$5)),$E210/$R210*DAY($J210),IF(AND($O210<>"",$O210<CB$5),0,IF($K210="",$E210/$R210*W210,IF(MONTH($K210)=MONTH(CB$5),$L210/$R210*W210,IF(AND($K210<CB$5,(MONTH($K210)<>MONTH(CB$5))),$L210/$R210*W210,$E210/$R210*W210)))))) -> 34.341667 | CC210: =+IF(AND($J210>CC$5,MONTH($J210<>CC$5)),0,+IF(AND($J210>CC$5,MONTH($J210=CC$5)),$E210/$R210*DAY($J210),IF(AND($O210<>"",$O210<CC$5),0,IF($K210="",$E210/$R210*X210,IF(MONTH($K210)=MONTH(CC$5),$L210/$R210*X210,IF(AND($K210<CC$5,(MONTH($K210)<>MONTH(CC$5))),$L210/$R210*X210,$E210/$R210*X210)))))) -> 34.341667 | CD210: =+IF(AND($J210>CD$5,MONTH($J210<>CD$5)),0,+IF(AND($J210>CD$5,MONTH($J210=CD$5)),$E210/$R210*DAY($J210),IF(AND($O210<>"",$O210<CD$5),0,IF($K210="",$E210/$R210*Y210,IF(MONTH($K210)=MONTH(CD$5),$L210/$R210*Y210,IF(AND($K210<CD$5,(MONTH($K210)<>MONTH(CD$5))),$L210/$R210*Y210,$E210/$R210*Y210)))))) -> 34.341667 | CE210: =+IF(AND($J210>CE$5,MONTH($J210<>CE$5)),0,+IF(AND($J210>CE$5,MONTH($J210=CE$5)),$E210/$R210*DAY($J210),IF(AND($O210<>"",$O210<CE$5),0,IF($K210="",$E210/$R210*Z210,IF(MONTH($K210)=MONTH(CE$5),$L210/$R210*Z210,IF(AND($K210<CE$5,(MONTH($K210)<>MONTH(CE$5))),$L210/$R210*Z210,$E210/$R210*Z210)))))) -> 34.341667 | ... CI210: =+IF(AND($J210>CI$5,MONTH($J210<>CI$5)),0,+IF(AND($J210>CI$5,MONTH($J210=CI$5)),$E210/$R210*DAY($J210),IF(AND($O210<>"",$O210<CI$5),0,IF($K210="",$E210/$R210*AD210,IF(MONTH($K210)=MONTH(CI$5),$L210/$R210*AD210,IF(AND($K210<CI$5,(MONTH($K210)<>MONTH(CI$5))),$L210/$R210*AD210,$E210/$R210*AD210)))))) -> 34.341667 | CJ210: =SUM(BX210:CI210) -> 412.1 | CK210: =+IF(P210<5,18,IF(AND(P210>=5,P210<10),19,IF(AND(P210>=10,P210<15),20,IF(AND(P210>=15,P210<20),21,0)))) -> 18 | CL210: =+CM210-CJ210 -> 0 | CM210: =IF(L210=0,E210,(L210-E210+E210)) -> 412.1
A211: 07289 | B211: ZOLA GISUPA CHRISTIAN | C211: Store Clerk | D211: =+VLOOKUP(A211,'[1]BDD-Avk Tx'!B:CE,82,0) -> 640 | E211: 130 | G211: 44993 | H211: =+IF(YEAR(G211)<YEAR($H$5),$H$4,G211) -> 45647 | I211: =+VLOOKUP(A211,'[1]BDD-Avk Tx'!B:BZ,77,0) -> CDI | J211: =+IF(I211="CDI",H211,H211+0) -> 45647 | K211: 45724 | L211: 356.2 | P211: =DATEDIF(G211,$AD$6,"m")/12 -> 2.75 | Q211: 0.5 | R211: =SUM(S211:AD211) -> 18 | S211: =+IF(AND(AND($O211="",$P211>=10,MONTH($G211)=MONTH(S$5))),1.5+2,+IF(AND(AND($O211="",$P211>=5,MONTH($G211)=MONTH(S$5))),1.5+1,+IF(AND(AND($P211=5,$O211="",MONTH($G211)=MONTH(S$5))),1.5,+IF(AND($H211>S$5,MONTH($H211)=MONTH(S$5)),1.5/30*(S$4-DAY($H211)),+IF(AND(MONTH($H211)<MONTH(S$5),$O211=""),1.5,+IF(AND($H211=$S$5,$O211=""),1.5,IF($O211<S$5,0,IF(MONTH($O211)=MONTH(S$5),1.5/30*($O211-S$5),1.5)))))))) -> 1.5 | T211: =+IF(AND(AND($O211="",$P211>=10,MONTH($G211)=MONTH(T$5))),1.5+2,+IF(AND(AND($O211="",$P211>=5,MONTH($G211)=MONTH(T$5))),1.5+1,+IF(AND(AND($P211=5,$O211="",MONTH($G211)=MONTH(T$5))),1.5,+IF(AND($H211>T$5,MONTH($H211)=MONTH(T$5)),1.5/30*(T$4-DAY($H211)),+IF(AND(MONTH($H211)<MONTH(T$5),$O211=""),1.5,+IF(AND($H211=$S$5,$O211=""),1.5,IF($O211<T$5,0,IF(MONTH($O211)=MONTH(T$5),1.5/30*($O211-T$5),1.5)))))))) -> 1.5 | U211: =+IF(AND(AND($O211="",$P211>=10,MONTH($G211)=MONTH(U$5))),1.5+2,+IF(AND(AND($O211="",$P211>=5,MONTH($G211)=MONTH(U$5))),1.5+1,+IF(AND(AND($P211=5,$O211="",MONTH($G211)=MONTH(U$5))),1.5,+IF(AND($H211>U$5,MONTH($H211)=MONTH(U$5)),1.5/30*(U$4-DAY($H211)),+IF(AND(MONTH($H211)<MONTH(U$5),$O211=""),1.5,+IF(AND($H211=$S$5,$O211=""),1.5,IF($O211<U$5,0,IF(MONTH($O211)=MONTH(U$5),1.5/30*($O211-U$5),1.5)))))))) -> 1.5 | V211: =+IF(AND(AND($O211="",$P211>=10,MONTH($G211)=MONTH(V$5))),1.5+2,+IF(AND(AND($O211="",$P211>=5,MONTH($G211)=MONTH(V$5))),1.5+1,+IF(AND(AND($P211=5,$O211="",MONTH($G211)=MONTH(V$5))),1.5,+IF(AND($H211>V$5,MONTH($H211)=MONTH(V$5)),1.5/30*(V$4-DAY($H211)),+IF(AND(MONTH($H211)<MONTH(V$5),$O211=""),1.5,+IF(AND($H211=$S$5,$O211=""),1.5,IF($O211<V$5,0,IF(MONTH($O211)=MONTH(V$5),1.5/30*($O211-V$5),1.5)))))))) -> 1.5 | W211: =+IF(AND(AND($O211="",$P211>=10,MONTH($G211)=MONTH(W$5))),1.5+2,+IF(AND(AND($O211="",$P211>=5,MONTH($G211)=MONTH(W$5))),1.5+1,+IF(AND(AND($P211=5,$O211="",MONTH($G211)=MONTH(W$5))),1.5,+IF(AND($H211>W$5,MONTH($H211)=MONTH(W$5)),1.5/30*(W$4-DAY($H211)),+IF(AND(MONTH($H211)<MONTH(W$5),$O211=""),1.5,+IF(AND($H211=$S$5,$O211=""),1.5,IF($O211<W$5,0,IF(MONTH($O211)=MONTH(W$5),1.5/30*($O211-W$5),1.5)))))))) -> 1.5 | X211: =+IF(AND(AND($O211="",$P211>=10,MONTH($G211)=MONTH(X$5))),1.5+2,+IF(AND(AND($O211="",$P211>=5,MONTH($G211)=MONTH(X$5))),1.5+1,+IF(AND(AND($P211=5,$O211="",MONTH($G211)=MONTH(X$5))),1.5,+IF(AND($H211>X$5,MONTH($H211)=MONTH(X$5)),1.5/30*(X$4-DAY($H211)),+IF(AND(MONTH($H211)<MONTH(X$5),$O211=""),1.5,+IF(AND($H211=$S$5,$O211=""),1.5,IF($O211<X$5,0,IF(MONTH($O211)=MONTH(X$5),1.5/30*($O211-X$5),1.5)))))))) -> 1.5 | Y211: =+IF(AND(AND($O211="",$P211>=10,MONTH($G211)=MONTH(Y$5))),1.5+2,+IF(AND(AND($O211="",$P211>=5,MONTH($G211)=MONTH(Y$5))),1.5+1,+IF(AND(AND($P211=5,$O211="",MONTH($G211)=MONTH(Y$5))),1.5,+IF(AND($H211>Y$5,MONTH($H211)=MONTH(Y$5)),1.5/30*(Y$4-DAY($H211)),+IF(AND(MONTH($H211)<MONTH(Y$5),$O211=""),1.5,+IF(AND($H211=$S$5,$O211=""),1.5,IF($O211<Y$5,0,IF(MONTH($O211)=MONTH(Y$5),1.5/30*($O211-Y$5),1.5)))))))) -> 1.5 | Z211: =+IF(AND(AND($O211="",$P211>=10,MONTH($G211)=MONTH(Z$5))),1.5+2,+IF(AND(AND($O211="",$P211>=5,MONTH($G211)=MONTH(Z$5))),1.5+1,+IF(AND(AND($P211=5,$O211="",MONTH($G211)=MONTH(Z$5))),1.5,+IF(AND($H211>Z$5,MONTH($H211)=MONTH(Z$5)),1.5/30*(Z$4-DAY($H211)),+IF(AND(MONTH($H211)<MONTH(Z$5),$O211=""),1.5,+IF(AND($H211=$S$5,$O211=""),1.5,IF($O211<Z$5,0,IF(MONTH($O211)=MONTH(Z$5),1.5/30*($O211-Z$5),1.5)))))))) -> 1.5 | ... AD211: =+IF(AND(AND($O211="",$P211>=10,MONTH($G211)=MONTH(AD$5))),1.5+2,+IF(AND(AND($O211="",$P211>=5,MONTH($G211)=MONTH(AD$5))),1.5+1,+IF(AND(AND($P211=5,$O211="",MONTH($G211)=MONTH(AD$5))),1.5,+IF(AND($H211>AD$5,MONTH($H211)=MONTH(AD$5)),1.5/30*(AD$4-DAY($H211)),+IF(AND(MONTH($H211)<MONTH(AD$5),$O211=""),1.5,+IF(AND($H211=$S$5,$O211=""),1.5,IF($O211<AD$5,0,IF(MONTH($O211)=MONTH(AD$5),1.5/30*($O211-AD$5),1.5)))))))) -> 1.5 | AF211: =SUM(AG211:AR211) -> 0 | AG211: 0 | AH211: 0 | AI211: 0 | AS211: =+Q211+R211-AF211 -> 18.5 | AU211: 2.5 | AV211: =SUM(AW211:BH211) -> 207.45 | AW211: =+IF($K211="",$E211/26*S211,IF(MONTH($K211)=MONTH(AW$5),$L211/26*S211,IF(AND($K211<AW$5,(MONTH($K211)<>MONTH(AW$5))),$L211/26*S211,$E211/26*S211))) -> 7.5 | AX211: =+IF($K211="",$E211/26*T211,IF(MONTH($K211)=MONTH(AX$5),$L211/26*T211,IF(AND($K211<AX$5,(MONTH($K211)<>MONTH(AX$5))),$L211/26*T211,$E211/26*T211))) -> 7.5 | AY211: =+IF($K211="",$E211/26*U211,IF(MONTH($K211)=MONTH(AY$5),$L211/26*U211,IF(AND($K211<AY$5,(MONTH($K211)<>MONTH(AY$5))),$L211/26*U211,$E211/26*U211))) -> 7.5 | AZ211: =+IF($K211="",$E211/26*V211,IF(MONTH($K211)=MONTH(AZ$5),$L211/26*V211,IF(AND($K211<AZ$5,(MONTH($K211)<>MONTH(AZ$5))),$L211/26*V211,$E211/26*V211))) -> 20.55 | BA211: =+IF($K211="",$E211/26*W211,IF(MONTH($K211)=MONTH(BA$5),$L211/26*W211,IF(AND($K211<BA$5,(MONTH($K211)<>MONTH(BA$5))),$L211/26*W211,$E211/26*W211))) -> 20.55 | BB211: =+IF($K211="",$E211/26*X211,IF(MONTH($K211)=MONTH(BB$5),$L211/26*X211,IF(AND($K211<BB$5,(MONTH($K211)<>MONTH(BB$5))),$L211/26*X211,$E211/26*X211))) -> 20.55 | BC211: =+IF($K211="",$E211/26*Y211,IF(MONTH($K211)=MONTH(BC$5),$L211/26*Y211,IF(AND($K211<BC$5,(MONTH($K211)<>MONTH(BC$5))),$L211/26*Y211,$E211/26*Y211))) -> 20.55 | BD211: =+IF($K211="",$E211/26*Z211,IF(MONTH($K211)=MONTH(BD$5),$L211/26*Z211,IF(AND($K211<BD$5,(MONTH($K211)<>MONTH(BD$5))),$L211/26*Z211,$E211/26*Z211))) -> 20.55 | ... BH211: =+IF($K211="",$E211/26*AD211,IF(MONTH($K211)=MONTH(BH$5),$L211/26*AD211,IF(AND($K211<BH$5,(MONTH($K211)<>MONTH(BH$5))),$L211/26*AD211,$E211/26*AD211))) -> 20.55 | BI211: =SUM(BJ211:BU211) -> 0 | BJ211: =(+IF($K211="",$E211/26*AG211,IF(MONTH($K211)=MONTH(BJ$5),$L211/26*AG211,IF(AND($K211<BJ$5,(MONTH($K211)<>MONTH(BJ$5))),$L211/26*AG211,$E211/26*AG211))))*-1 -> 0 | BK211: =(+IF($K211="",$E211/26*AH211,IF(MONTH($K211)=MONTH(BK$5),$L211/26*AH211,IF(AND($K211<BK$5,(MONTH($K211)<>MONTH(BK$5))),$L211/26*AH211,$E211/26*AH211))))*-1 -> 0 | BL211: =(+IF($K211="",$E211/26*AI211,IF(MONTH($K211)=MONTH(BL$5),$L211/26*AI211,IF(AND($K211<BL$5,(MONTH($K211)<>MONTH(BL$5))),$L211/26*AI211,$E211/26*AI211))))*-1 -> 0 | BM211: =(+IF($K211="",$E211/26*AJ211,IF(MONTH($K211)=MONTH(BM$5),$L211/26*AJ211,IF(AND($K211<BM$5,(MONTH($K211)<>MONTH(BM$5))),$L211/26*AJ211,$E211/26*AJ211))))*-1 -> 0 | BN211: =(+IF($K211="",$E211/26*AK211,IF(MONTH($K211)=MONTH(BN$5),$L211/26*AK211,IF(AND($K211<BN$5,(MONTH($K211)<>MONTH(BN$5))),$L211/26*AK211,$E211/26*AK211))))*-1 -> 0 | BO211: =(+IF($K211="",$E211/26*AL211,IF(MONTH($K211)=MONTH(BO$5),$L211/26*AL211,IF(AND($K211<BO$5,(MONTH($K211)<>MONTH(BO$5))),$L211/26*AL211,$E211/26*AL211))))*-1 -> 0 | BP211: =(+IF($K211="",$E211/26*AM211,IF(MONTH($K211)=MONTH(BP$5),$L211/26*AM211,IF(AND($K211<BP$5,(MONTH($K211)<>MONTH(BP$5))),$L211/26*AM211,$E211/26*AM211))))*-1 -> 0 | BQ211: =(+IF($K211="",$E211/26*AN211,IF(MONTH($K211)=MONTH(BQ$5),$L211/26*AN211,IF(AND($K211<BQ$5,(MONTH($K211)<>MONTH(BQ$5))),$L211/26*AN211,$E211/26*AN211))))*-1 -> 0 | ... BU211: =(+IF($K211="",$E211/26*AR211,IF(MONTH($K211)=MONTH(BU$5),$L211/26*AR211,IF(AND($K211<BU$5,(MONTH($K211)<>MONTH(BU$5))),$L211/26*AR211,$E211/26*AR211))))*-1 -> 0 | BV211: =+AU211+AV211+BI211 -> 209.95 | BX211: =+IF(AND($J211>BX$5,MONTH($J211<>BX$5)),0,+IF(AND($J211>BX$5,MONTH($J211=BX$5)),$E211/$R211*DAY($J211),IF(AND($O211<>"",$O211<BX$5),0,IF($K211="",$E211/$R211*S211,IF(MONTH($K211)=MONTH(BX$5),$L211/$R211*S211,IF(AND($K211<BX$5,(MONTH($K211)<>MONTH(BX$5))),$L211/$R211*S211,$E211/$R211*S211)))))) -> 10.833333 | BY211: =+IF(AND($J211>BY$5,MONTH($J211<>BY$5)),0,+IF(AND($J211>BY$5,MONTH($J211=BY$5)),$E211/$R211*DAY($J211),IF(AND($O211<>"",$O211<BY$5),0,IF($K211="",$E211/$R211*T211,IF(MONTH($K211)=MONTH(BY$5),$L211/$R211*T211,IF(AND($K211<BY$5,(MONTH($K211)<>MONTH(BY$5))),$L211/$R211*T211,$E211/$R211*T211)))))) -> 10.833333 | BZ211: =+IF(AND($J211>BZ$5,MONTH($J211<>BZ$5)),0,+IF(AND($J211>BZ$5,MONTH($J211=BZ$5)),$E211/$R211*DAY($J211),IF(AND($O211<>"",$O211<BZ$5),0,IF($K211="",$E211/$R211*U211,IF(MONTH($K211)=MONTH(BZ$5),$L211/$R211*U211,IF(AND($K211<BZ$5,(MONTH($K211)<>MONTH(BZ$5))),$L211/$R211*U211,$E211/$R211*U211)))))) -> 29.683333 | CA211: =+IF(AND($J211>CA$5,MONTH($J211<>CA$5)),0,+IF(AND($J211>CA$5,MONTH($J211=CA$5)),$E211/$R211*DAY($J211),IF(AND($O211<>"",$O211<CA$5),0,IF($K211="",$E211/$R211*V211,IF(MONTH($K211)=MONTH(CA$5),$L211/$R211*V211,IF(AND($K211<CA$5,(MONTH($K211)<>MONTH(CA$5))),$L211/$R211*V211,$E211/$R211*V211)))))) -> 29.683333 | CB211: =+IF(AND($J211>CB$5,MONTH($J211<>CB$5)),0,+IF(AND($J211>CB$5,MONTH($J211=CB$5)),$E211/$R211*DAY($J211),IF(AND($O211<>"",$O211<CB$5),0,IF($K211="",$E211/$R211*W211,IF(MONTH($K211)=MONTH(CB$5),$L211/$R211*W211,IF(AND($K211<CB$5,(MONTH($K211)<>MONTH(CB$5))),$L211/$R211*W211,$E211/$R211*W211)))))) -> 29.683333 | CC211: =+IF(AND($J211>CC$5,MONTH($J211<>CC$5)),0,+IF(AND($J211>CC$5,MONTH($J211=CC$5)),$E211/$R211*DAY($J211),IF(AND($O211<>"",$O211<CC$5),0,IF($K211="",$E211/$R211*X211,IF(MONTH($K211)=MONTH(CC$5),$L211/$R211*X211,IF(AND($K211<CC$5,(MONTH($K211)<>MONTH(CC$5))),$L211/$R211*X211,$E211/$R211*X211)))))) -> 29.683333 | CD211: =+IF(AND($J211>CD$5,MONTH($J211<>CD$5)),0,+IF(AND($J211>CD$5,MONTH($J211=CD$5)),$E211/$R211*DAY($J211),IF(AND($O211<>"",$O211<CD$5),0,IF($K211="",$E211/$R211*Y211,IF(MONTH($K211)=MONTH(CD$5),$L211/$R211*Y211,IF(AND($K211<CD$5,(MONTH($K211)<>MONTH(CD$5))),$L211/$R211*Y211,$E211/$R211*Y211)))))) -> 29.683333 | CE211: =+IF(AND($J211>CE$5,MONTH($J211<>CE$5)),0,+IF(AND($J211>CE$5,MONTH($J211=CE$5)),$E211/$R211*DAY($J211),IF(AND($O211<>"",$O211<CE$5),0,IF($K211="",$E211/$R211*Z211,IF(MONTH($K211)=MONTH(CE$5),$L211/$R211*Z211,IF(AND($K211<CE$5,(MONTH($K211)<>MONTH(CE$5))),$L211/$R211*Z211,$E211/$R211*Z211)))))) -> 29.683333 | ... CI211: =+IF(AND($J211>CI$5,MONTH($J211<>CI$5)),0,+IF(AND($J211>CI$5,MONTH($J211=CI$5)),$E211/$R211*DAY($J211),IF(AND($O211<>"",$O211<CI$5),0,IF($K211="",$E211/$R211*AD211,IF(MONTH($K211)=MONTH(CI$5),$L211/$R211*AD211,IF(AND($K211<CI$5,(MONTH($K211)<>MONTH(CI$5))),$L211/$R211*AD211,$E211/$R211*AD211)))))) -> 29.683333 | CJ211: =SUM(BX211:CI211) -> 318.5 | CK211: =+IF(P211<5,18,IF(AND(P211>=5,P211<10),19,IF(AND(P211>=10,P211<15),20,IF(AND(P211>=15,P211<20),21,0)))) -> 18 | CL211: =+CM211-CJ211 -> 37.7 | CM211: =IF(L211=0,E211,(L211-E211+E211)) -> 356.2
A212: 07294 | B212: SEKE PAMBU BARDELLY | C212: Electricien Maintance | D212: =+VLOOKUP(A212,'[1]BDD-Avk Tx'!B:CE,82,0) -> 810 | E212: 200.2 | G212: 45045 | H212: =+IF(YEAR(G212)<YEAR($H$5),$H$4,G212) -> 45647 | I212: =+VLOOKUP(A212,'[1]BDD-Avk Tx'!B:BZ,77,0) -> CDD | J212: =+IF(I212="CDI",H212,H212+0) -> 45647 | P212: =DATEDIF(G212,$AD$6,"m")/12 -> 2.5833333 | Q212: 0 | R212: =SUM(S212:AD212) -> 18 | S212: =+IF(AND(AND($O212="",$P212>=10,MONTH($G212)=MONTH(S$5))),1.5+2,+IF(AND(AND($O212="",$P212>=5,MONTH($G212)=MONTH(S$5))),1.5+1,+IF(AND(AND($P212=5,$O212="",MONTH($G212)=MONTH(S$5))),1.5,+IF(AND($H212>S$5,MONTH($H212)=MONTH(S$5)),1.5/30*(S$4-DAY($H212)),+IF(AND(MONTH($H212)<MONTH(S$5),$O212=""),1.5,+IF(AND($H212=$S$5,$O212=""),1.5,IF($O212<S$5,0,IF(MONTH($O212)=MONTH(S$5),1.5/30*($O212-S$5),1.5)))))))) -> 1.5 | T212: =+IF(AND(AND($O212="",$P212>=10,MONTH($G212)=MONTH(T$5))),1.5+2,+IF(AND(AND($O212="",$P212>=5,MONTH($G212)=MONTH(T$5))),1.5+1,+IF(AND(AND($P212=5,$O212="",MONTH($G212)=MONTH(T$5))),1.5,+IF(AND($H212>T$5,MONTH($H212)=MONTH(T$5)),1.5/30*(T$4-DAY($H212)),+IF(AND(MONTH($H212)<MONTH(T$5),$O212=""),1.5,+IF(AND($H212=$S$5,$O212=""),1.5,IF($O212<T$5,0,IF(MONTH($O212)=MONTH(T$5),1.5/30*($O212-T$5),1.5)))))))) -> 1.5 | U212: =+IF(AND(AND($O212="",$P212>=10,MONTH($G212)=MONTH(U$5))),1.5+2,+IF(AND(AND($O212="",$P212>=5,MONTH($G212)=MONTH(U$5))),1.5+1,+IF(AND(AND($P212=5,$O212="",MONTH($G212)=MONTH(U$5))),1.5,+IF(AND($H212>U$5,MONTH($H212)=MONTH(U$5)),1.5/30*(U$4-DAY($H212)),+IF(AND(MONTH($H212)<MONTH(U$5),$O212=""),1.5,+IF(AND($H212=$S$5,$O212=""),1.5,IF($O212<U$5,0,IF(MONTH($O212)=MONTH(U$5),1.5/30*($O212-U$5),1.5)))))))) -> 1.5 | V212: =+IF(AND(AND($O212="",$P212>=10,MONTH($G212)=MONTH(V$5))),1.5+2,+IF(AND(AND($O212="",$P212>=5,MONTH($G212)=MONTH(V$5))),1.5+1,+IF(AND(AND($P212=5,$O212="",MONTH($G212)=MONTH(V$5))),1.5,+IF(AND($H212>V$5,MONTH($H212)=MONTH(V$5)),1.5/30*(V$4-DAY($H212)),+IF(AND(MONTH($H212)<MONTH(V$5),$O212=""),1.5,+IF(AND($H212=$S$5,$O212=""),1.5,IF($O212<V$5,0,IF(MONTH($O212)=MONTH(V$5),1.5/30*($O212-V$5),1.5)))))))) -> 1.5 | W212: =+IF(AND(AND($O212="",$P212>=10,MONTH($G212)=MONTH(W$5))),1.5+2,+IF(AND(AND($O212="",$P212>=5,MONTH($G212)=MONTH(W$5))),1.5+1,+IF(AND(AND($P212=5,$O212="",MONTH($G212)=MONTH(W$5))),1.5,+IF(AND($H212>W$5,MONTH($H212)=MONTH(W$5)),1.5/30*(W$4-DAY($H212)),+IF(AND(MONTH($H212)<MONTH(W$5),$O212=""),1.5,+IF(AND($H212=$S$5,$O212=""),1.5,IF($O212<W$5,0,IF(MONTH($O212)=MONTH(W$5),1.5/30*($O212-W$5),1.5)))))))) -> 1.5 | X212: =+IF(AND(AND($O212="",$P212>=10,MONTH($G212)=MONTH(X$5))),1.5+2,+IF(AND(AND($O212="",$P212>=5,MONTH($G212)=MONTH(X$5))),1.5+1,+IF(AND(AND($P212=5,$O212="",MONTH($G212)=MONTH(X$5))),1.5,+IF(AND($H212>X$5,MONTH($H212)=MONTH(X$5)),1.5/30*(X$4-DAY($H212)),+IF(AND(MONTH($H212)<MONTH(X$5),$O212=""),1.5,+IF(AND($H212=$S$5,$O212=""),1.5,IF($O212<X$5,0,IF(MONTH($O212)=MONTH(X$5),1.5/30*($O212-X$5),1.5)))))))) -> 1.5 | Y212: =+IF(AND(AND($O212="",$P212>=10,MONTH($G212)=MONTH(Y$5))),1.5+2,+IF(AND(AND($O212="",$P212>=5,MONTH($G212)=MONTH(Y$5))),1.5+1,+IF(AND(AND($P212=5,$O212="",MONTH($G212)=MONTH(Y$5))),1.5,+IF(AND($H212>Y$5,MONTH($H212)=MONTH(Y$5)),1.5/30*(Y$4-DAY($H212)),+IF(AND(MONTH($H212)<MONTH(Y$5),$O212=""),1.5,+IF(AND($H212=$S$5,$O212=""),1.5,IF($O212<Y$5,0,IF(MONTH($O212)=MONTH(Y$5),1.5/30*($O212-Y$5),1.5)))))))) -> 1.5 | Z212: =+IF(AND(AND($O212="",$P212>=10,MONTH($G212)=MONTH(Z$5))),1.5+2,+IF(AND(AND($O212="",$P212>=5,MONTH($G212)=MONTH(Z$5))),1.5+1,+IF(AND(AND($P212=5,$O212="",MONTH($G212)=MONTH(Z$5))),1.5,+IF(AND($H212>Z$5,MONTH($H212)=MONTH(Z$5)),1.5/30*(Z$4-DAY($H212)),+IF(AND(MONTH($H212)<MONTH(Z$5),$O212=""),1.5,+IF(AND($H212=$S$5,$O212=""),1.5,IF($O212<Z$5,0,IF(MONTH($O212)=MONTH(Z$5),1.5/30*($O212-Z$5),1.5)))))))) -> 1.5 | ... AD212: =+IF(AND(AND($O212="",$P212>=10,MONTH($G212)=MONTH(AD$5))),1.5+2,+IF(AND(AND($O212="",$P212>=5,MONTH($G212)=MONTH(AD$5))),1.5+1,+IF(AND(AND($P212=5,$O212="",MONTH($G212)=MONTH(AD$5))),1.5,+IF(AND($H212>AD$5,MONTH($H212)=MONTH(AD$5)),1.5/30*(AD$4-DAY($H212)),+IF(AND(MONTH($H212)<MONTH(AD$5),$O212=""),1.5,+IF(AND($H212=$S$5,$O212=""),1.5,IF($O212<AD$5,0,IF(MONTH($O212)=MONTH(AD$5),1.5/30*($O212-AD$5),1.5)))))))) -> 1.5 | AF212: =SUM(AG212:AR212) -> 0 | AG212: 0 | AH212: 0 | AI212: 0 | AS212: =+Q212+R212-AF212 -> 18 | AU212: 0 | AV212: =SUM(AW212:BH212) -> 138.6 | AW212: =+IF($K212="",$E212/26*S212,IF(MONTH($K212)=MONTH(AW$5),$L212/26*S212,IF(AND($K212<AW$5,(MONTH($K212)<>MONTH(AW$5))),$L212/26*S212,$E212/26*S212))) -> 11.55 | AX212: =+IF($K212="",$E212/26*T212,IF(MONTH($K212)=MONTH(AX$5),$L212/26*T212,IF(AND($K212<AX$5,(MONTH($K212)<>MONTH(AX$5))),$L212/26*T212,$E212/26*T212))) -> 11.55 | AY212: =+IF($K212="",$E212/26*U212,IF(MONTH($K212)=MONTH(AY$5),$L212/26*U212,IF(AND($K212<AY$5,(MONTH($K212)<>MONTH(AY$5))),$L212/26*U212,$E212/26*U212))) -> 11.55 | AZ212: =+IF($K212="",$E212/26*V212,IF(MONTH($K212)=MONTH(AZ$5),$L212/26*V212,IF(AND($K212<AZ$5,(MONTH($K212)<>MONTH(AZ$5))),$L212/26*V212,$E212/26*V212))) -> 11.55 | BA212: =+IF($K212="",$E212/26*W212,IF(MONTH($K212)=MONTH(BA$5),$L212/26*W212,IF(AND($K212<BA$5,(MONTH($K212)<>MONTH(BA$5))),$L212/26*W212,$E212/26*W212))) -> 11.55 | BB212: =+IF($K212="",$E212/26*X212,IF(MONTH($K212)=MONTH(BB$5),$L212/26*X212,IF(AND($K212<BB$5,(MONTH($K212)<>MONTH(BB$5))),$L212/26*X212,$E212/26*X212))) -> 11.55 | BC212: =+IF($K212="",$E212/26*Y212,IF(MONTH($K212)=MONTH(BC$5),$L212/26*Y212,IF(AND($K212<BC$5,(MONTH($K212)<>MONTH(BC$5))),$L212/26*Y212,$E212/26*Y212))) -> 11.55 | BD212: =+IF($K212="",$E212/26*Z212,IF(MONTH($K212)=MONTH(BD$5),$L212/26*Z212,IF(AND($K212<BD$5,(MONTH($K212)<>MONTH(BD$5))),$L212/26*Z212,$E212/26*Z212))) -> 11.55 | ... BH212: =+IF($K212="",$E212/26*AD212,IF(MONTH($K212)=MONTH(BH$5),$L212/26*AD212,IF(AND($K212<BH$5,(MONTH($K212)<>MONTH(BH$5))),$L212/26*AD212,$E212/26*AD212))) -> 11.55 | BI212: =SUM(BJ212:BU212) -> 0 | BJ212: =(+IF($K212="",$E212/26*AG212,IF(MONTH($K212)=MONTH(BJ$5),$L212/26*AG212,IF(AND($K212<BJ$5,(MONTH($K212)<>MONTH(BJ$5))),$L212/26*AG212,$E212/26*AG212))))*-1 -> 0 | BK212: =(+IF($K212="",$E212/26*AH212,IF(MONTH($K212)=MONTH(BK$5),$L212/26*AH212,IF(AND($K212<BK$5,(MONTH($K212)<>MONTH(BK$5))),$L212/26*AH212,$E212/26*AH212))))*-1 -> 0 | BL212: =(+IF($K212="",$E212/26*AI212,IF(MONTH($K212)=MONTH(BL$5),$L212/26*AI212,IF(AND($K212<BL$5,(MONTH($K212)<>MONTH(BL$5))),$L212/26*AI212,$E212/26*AI212))))*-1 -> 0 | BM212: =(+IF($K212="",$E212/26*AJ212,IF(MONTH($K212)=MONTH(BM$5),$L212/26*AJ212,IF(AND($K212<BM$5,(MONTH($K212)<>MONTH(BM$5))),$L212/26*AJ212,$E212/26*AJ212))))*-1 -> 0 | BN212: =(+IF($K212="",$E212/26*AK212,IF(MONTH($K212)=MONTH(BN$5),$L212/26*AK212,IF(AND($K212<BN$5,(MONTH($K212)<>MONTH(BN$5))),$L212/26*AK212,$E212/26*AK212))))*-1 -> 0 | BO212: =(+IF($K212="",$E212/26*AL212,IF(MONTH($K212)=MONTH(BO$5),$L212/26*AL212,IF(AND($K212<BO$5,(MONTH($K212)<>MONTH(BO$5))),$L212/26*AL212,$E212/26*AL212))))*-1 -> 0 | BP212: =(+IF($K212="",$E212/26*AM212,IF(MONTH($K212)=MONTH(BP$5),$L212/26*AM212,IF(AND($K212<BP$5,(MONTH($K212)<>MONTH(BP$5))),$L212/26*AM212,$E212/26*AM212))))*-1 -> 0 | BQ212: =(+IF($K212="",$E212/26*AN212,IF(MONTH($K212)=MONTH(BQ$5),$L212/26*AN212,IF(AND($K212<BQ$5,(MONTH($K212)<>MONTH(BQ$5))),$L212/26*AN212,$E212/26*AN212))))*-1 -> 0 | ... BU212: =(+IF($K212="",$E212/26*AR212,IF(MONTH($K212)=MONTH(BU$5),$L212/26*AR212,IF(AND($K212<BU$5,(MONTH($K212)<>MONTH(BU$5))),$L212/26*AR212,$E212/26*AR212))))*-1 -> 0 | BV212: =+AU212+AV212+BI212 -> 138.6 | BX212: =+IF(AND($J212>BX$5,MONTH($J212<>BX$5)),0,+IF(AND($J212>BX$5,MONTH($J212=BX$5)),$E212/$R212*DAY($J212),IF(AND($O212<>"",$O212<BX$5),0,IF($K212="",$E212/$R212*S212,IF(MONTH($K212)=MONTH(BX$5),$L212/$R212*S212,IF(AND($K212<BX$5,(MONTH($K212)<>MONTH(BX$5))),$L212/$R212*S212,$E212/$R212*S212)))))) -> 16.683333 | BY212: =+IF(AND($J212>BY$5,MONTH($J212<>BY$5)),0,+IF(AND($J212>BY$5,MONTH($J212=BY$5)),$E212/$R212*DAY($J212),IF(AND($O212<>"",$O212<BY$5),0,IF($K212="",$E212/$R212*T212,IF(MONTH($K212)=MONTH(BY$5),$L212/$R212*T212,IF(AND($K212<BY$5,(MONTH($K212)<>MONTH(BY$5))),$L212/$R212*T212,$E212/$R212*T212)))))) -> 16.683333 | BZ212: =+IF(AND($J212>BZ$5,MONTH($J212<>BZ$5)),0,+IF(AND($J212>BZ$5,MONTH($J212=BZ$5)),$E212/$R212*DAY($J212),IF(AND($O212<>"",$O212<BZ$5),0,IF($K212="",$E212/$R212*U212,IF(MONTH($K212)=MONTH(BZ$5),$L212/$R212*U212,IF(AND($K212<BZ$5,(MONTH($K212)<>MONTH(BZ$5))),$L212/$R212*U212,$E212/$R212*U212)))))) -> 16.683333 | CA212: =+IF(AND($J212>CA$5,MONTH($J212<>CA$5)),0,+IF(AND($J212>CA$5,MONTH($J212=CA$5)),$E212/$R212*DAY($J212),IF(AND($O212<>"",$O212<CA$5),0,IF($K212="",$E212/$R212*V212,IF(MONTH($K212)=MONTH(CA$5),$L212/$R212*V212,IF(AND($K212<CA$5,(MONTH($K212)<>MONTH(CA$5))),$L212/$R212*V212,$E212/$R212*V212)))))) -> 16.683333 | CB212: =+IF(AND($J212>CB$5,MONTH($J212<>CB$5)),0,+IF(AND($J212>CB$5,MONTH($J212=CB$5)),$E212/$R212*DAY($J212),IF(AND($O212<>"",$O212<CB$5),0,IF($K212="",$E212/$R212*W212,IF(MONTH($K212)=MONTH(CB$5),$L212/$R212*W212,IF(AND($K212<CB$5,(MONTH($K212)<>MONTH(CB$5))),$L212/$R212*W212,$E212/$R212*W212)))))) -> 16.683333 | CC212: =+IF(AND($J212>CC$5,MONTH($J212<>CC$5)),0,+IF(AND($J212>CC$5,MONTH($J212=CC$5)),$E212/$R212*DAY($J212),IF(AND($O212<>"",$O212<CC$5),0,IF($K212="",$E212/$R212*X212,IF(MONTH($K212)=MONTH(CC$5),$L212/$R212*X212,IF(AND($K212<CC$5,(MONTH($K212)<>MONTH(CC$5))),$L212/$R212*X212,$E212/$R212*X212)))))) -> 16.683333 | CD212: =+IF(AND($J212>CD$5,MONTH($J212<>CD$5)),0,+IF(AND($J212>CD$5,MONTH($J212=CD$5)),$E212/$R212*DAY($J212),IF(AND($O212<>"",$O212<CD$5),0,IF($K212="",$E212/$R212*Y212,IF(MONTH($K212)=MONTH(CD$5),$L212/$R212*Y212,IF(AND($K212<CD$5,(MONTH($K212)<>MONTH(CD$5))),$L212/$R212*Y212,$E212/$R212*Y212)))))) -> 16.683333 | CE212: =+IF(AND($J212>CE$5,MONTH($J212<>CE$5)),0,+IF(AND($J212>CE$5,MONTH($J212=CE$5)),$E212/$R212*DAY($J212),IF(AND($O212<>"",$O212<CE$5),0,IF($K212="",$E212/$R212*Z212,IF(MONTH($K212)=MONTH(CE$5),$L212/$R212*Z212,IF(AND($K212<CE$5,(MONTH($K212)<>MONTH(CE$5))),$L212/$R212*Z212,$E212/$R212*Z212)))))) -> 16.683333 | ... CI212: =+IF(AND($J212>CI$5,MONTH($J212<>CI$5)),0,+IF(AND($J212>CI$5,MONTH($J212=CI$5)),$E212/$R212*DAY($J212),IF(AND($O212<>"",$O212<CI$5),0,IF($K212="",$E212/$R212*AD212,IF(MONTH($K212)=MONTH(CI$5),$L212/$R212*AD212,IF(AND($K212<CI$5,(MONTH($K212)<>MONTH(CI$5))),$L212/$R212*AD212,$E212/$R212*AD212)))))) -> 16.683333 | CJ212: =SUM(BX212:CI212) -> 200.2 | CK212: =+IF(P212<5,18,IF(AND(P212>=5,P212<10),19,IF(AND(P212>=10,P212<15),20,IF(AND(P212>=15,P212<20),21,0)))) -> 18 | CL212: =+CM212-CJ212 -> 0 | CM212: =IF(L212=0,E212,(L212-E212+E212)) -> 200.2
A213: 07295 | B213: MUNGWA ZOLANA CHRISTONE | C213: Commis de Cuisine | D213: =+VLOOKUP(A213,'[1]BDD-Avk Tx'!B:CE,82,0) -> 281 | E213: 130 | G213: 45051 | H213: =+IF(YEAR(G213)<YEAR($H$5),$H$4,G213) -> 45647 | I213: =+VLOOKUP(A213,'[1]BDD-Avk Tx'!B:BZ,77,0) -> CDD | J213: =+IF(I213="CDI",H213,H213+0) -> 45647 | P213: =DATEDIF(G213,$AD$6,"m")/12 -> 2.5833333 | Q213: 0.5 | R213: =SUM(S213:AD213) -> 18 | S213: =+IF(AND(AND($O213="",$P213>=10,MONTH($G213)=MONTH(S$5))),1.5+2,+IF(AND(AND($O213="",$P213>=5,MONTH($G213)=MONTH(S$5))),1.5+1,+IF(AND(AND($P213=5,$O213="",MONTH($G213)=MONTH(S$5))),1.5,+IF(AND($H213>S$5,MONTH($H213)=MONTH(S$5)),1.5/30*(S$4-DAY($H213)),+IF(AND(MONTH($H213)<MONTH(S$5),$O213=""),1.5,+IF(AND($H213=$S$5,$O213=""),1.5,IF($O213<S$5,0,IF(MONTH($O213)=MONTH(S$5),1.5/30*($O213-S$5),1.5)))))))) -> 1.5 | T213: =+IF(AND(AND($O213="",$P213>=10,MONTH($G213)=MONTH(T$5))),1.5+2,+IF(AND(AND($O213="",$P213>=5,MONTH($G213)=MONTH(T$5))),1.5+1,+IF(AND(AND($P213=5,$O213="",MONTH($G213)=MONTH(T$5))),1.5,+IF(AND($H213>T$5,MONTH($H213)=MONTH(T$5)),1.5/30*(T$4-DAY($H213)),+IF(AND(MONTH($H213)<MONTH(T$5),$O213=""),1.5,+IF(AND($H213=$S$5,$O213=""),1.5,IF($O213<T$5,0,IF(MONTH($O213)=MONTH(T$5),1.5/30*($O213-T$5),1.5)))))))) -> 1.5 | U213: =+IF(AND(AND($O213="",$P213>=10,MONTH($G213)=MONTH(U$5))),1.5+2,+IF(AND(AND($O213="",$P213>=5,MONTH($G213)=MONTH(U$5))),1.5+1,+IF(AND(AND($P213=5,$O213="",MONTH($G213)=MONTH(U$5))),1.5,+IF(AND($H213>U$5,MONTH($H213)=MONTH(U$5)),1.5/30*(U$4-DAY($H213)),+IF(AND(MONTH($H213)<MONTH(U$5),$O213=""),1.5,+IF(AND($H213=$S$5,$O213=""),1.5,IF($O213<U$5,0,IF(MONTH($O213)=MONTH(U$5),1.5/30*($O213-U$5),1.5)))))))) -> 1.5 | V213: =+IF(AND(AND($O213="",$P213>=10,MONTH($G213)=MONTH(V$5))),1.5+2,+IF(AND(AND($O213="",$P213>=5,MONTH($G213)=MONTH(V$5))),1.5+1,+IF(AND(AND($P213=5,$O213="",MONTH($G213)=MONTH(V$5))),1.5,+IF(AND($H213>V$5,MONTH($H213)=MONTH(V$5)),1.5/30*(V$4-DAY($H213)),+IF(AND(MONTH($H213)<MONTH(V$5),$O213=""),1.5,+IF(AND($H213=$S$5,$O213=""),1.5,IF($O213<V$5,0,IF(MONTH($O213)=MONTH(V$5),1.5/30*($O213-V$5),1.5)))))))) -> 1.5 | W213: =+IF(AND(AND($O213="",$P213>=10,MONTH($G213)=MONTH(W$5))),1.5+2,+IF(AND(AND($O213="",$P213>=5,MONTH($G213)=MONTH(W$5))),1.5+1,+IF(AND(AND($P213=5,$O213="",MONTH($G213)=MONTH(W$5))),1.5,+IF(AND($H213>W$5,MONTH($H213)=MONTH(W$5)),1.5/30*(W$4-DAY($H213)),+IF(AND(MONTH($H213)<MONTH(W$5),$O213=""),1.5,+IF(AND($H213=$S$5,$O213=""),1.5,IF($O213<W$5,0,IF(MONTH($O213)=MONTH(W$5),1.5/30*($O213-W$5),1.5)))))))) -> 1.5 | X213: =+IF(AND(AND($O213="",$P213>=10,MONTH($G213)=MONTH(X$5))),1.5+2,+IF(AND(AND($O213="",$P213>=5,MONTH($G213)=MONTH(X$5))),1.5+1,+IF(AND(AND($P213=5,$O213="",MONTH($G213)=MONTH(X$5))),1.5,+IF(AND($H213>X$5,MONTH($H213)=MONTH(X$5)),1.5/30*(X$4-DAY($H213)),+IF(AND(MONTH($H213)<MONTH(X$5),$O213=""),1.5,+IF(AND($H213=$S$5,$O213=""),1.5,IF($O213<X$5,0,IF(MONTH($O213)=MONTH(X$5),1.5/30*($O213-X$5),1.5)))))))) -> 1.5 | Y213: =+IF(AND(AND($O213="",$P213>=10,MONTH($G213)=MONTH(Y$5))),1.5+2,+IF(AND(AND($O213="",$P213>=5,MONTH($G213)=MONTH(Y$5))),1.5+1,+IF(AND(AND($P213=5,$O213="",MONTH($G213)=MONTH(Y$5))),1.5,+IF(AND($H213>Y$5,MONTH($H213)=MONTH(Y$5)),1.5/30*(Y$4-DAY($H213)),+IF(AND(MONTH($H213)<MONTH(Y$5),$O213=""),1.5,+IF(AND($H213=$S$5,$O213=""),1.5,IF($O213<Y$5,0,IF(MONTH($O213)=MONTH(Y$5),1.5/30*($O213-Y$5),1.5)))))))) -> 1.5 | Z213: =+IF(AND(AND($O213="",$P213>=10,MONTH($G213)=MONTH(Z$5))),1.5+2,+IF(AND(AND($O213="",$P213>=5,MONTH($G213)=MONTH(Z$5))),1.5+1,+IF(AND(AND($P213=5,$O213="",MONTH($G213)=MONTH(Z$5))),1.5,+IF(AND($H213>Z$5,MONTH($H213)=MONTH(Z$5)),1.5/30*(Z$4-DAY($H213)),+IF(AND(MONTH($H213)<MONTH(Z$5),$O213=""),1.5,+IF(AND($H213=$S$5,$O213=""),1.5,IF($O213<Z$5,0,IF(MONTH($O213)=MONTH(Z$5),1.5/30*($O213-Z$5),1.5)))))))) -> 1.5 | ... AD213: =+IF(AND(AND($O213="",$P213>=10,MONTH($G213)=MONTH(AD$5))),1.5+2,+IF(AND(AND($O213="",$P213>=5,MONTH($G213)=MONTH(AD$5))),1.5+1,+IF(AND(AND($P213=5,$O213="",MONTH($G213)=MONTH(AD$5))),1.5,+IF(AND($H213>AD$5,MONTH($H213)=MONTH(AD$5)),1.5/30*(AD$4-DAY($H213)),+IF(AND(MONTH($H213)<MONTH(AD$5),$O213=""),1.5,+IF(AND($H213=$S$5,$O213=""),1.5,IF($O213<AD$5,0,IF(MONTH($O213)=MONTH(AD$5),1.5/30*($O213-AD$5),1.5)))))))) -> 1.5 | AF213: =SUM(AG213:AR213) -> 18 | AG213: 5 | AH213: 13 | AI213: 0 | AS213: =+Q213+R213-AF213 -> 0.5 | AU213: 2.5 | AV213: =SUM(AW213:BH213) -> 90 | AW213: =+IF($K213="",$E213/26*S213,IF(MONTH($K213)=MONTH(AW$5),$L213/26*S213,IF(AND($K213<AW$5,(MONTH($K213)<>MONTH(AW$5))),$L213/26*S213,$E213/26*S213))) -> 7.5 | AX213: =+IF($K213="",$E213/26*T213,IF(MONTH($K213)=MONTH(AX$5),$L213/26*T213,IF(AND($K213<AX$5,(MONTH($K213)<>MONTH(AX$5))),$L213/26*T213,$E213/26*T213))) -> 7.5 | AY213: =+IF($K213="",$E213/26*U213,IF(MONTH($K213)=MONTH(AY$5),$L213/26*U213,IF(AND($K213<AY$5,(MONTH($K213)<>MONTH(AY$5))),$L213/26*U213,$E213/26*U213))) -> 7.5 | AZ213: =+IF($K213="",$E213/26*V213,IF(MONTH($K213)=MONTH(AZ$5),$L213/26*V213,IF(AND($K213<AZ$5,(MONTH($K213)<>MONTH(AZ$5))),$L213/26*V213,$E213/26*V213))) -> 7.5 | BA213: =+IF($K213="",$E213/26*W213,IF(MONTH($K213)=MONTH(BA$5),$L213/26*W213,IF(AND($K213<BA$5,(MONTH($K213)<>MONTH(BA$5))),$L213/26*W213,$E213/26*W213))) -> 7.5 | BB213: =+IF($K213="",$E213/26*X213,IF(MONTH($K213)=MONTH(BB$5),$L213/26*X213,IF(AND($K213<BB$5,(MONTH($K213)<>MONTH(BB$5))),$L213/26*X213,$E213/26*X213))) -> 7.5 | BC213: =+IF($K213="",$E213/26*Y213,IF(MONTH($K213)=MONTH(BC$5),$L213/26*Y213,IF(AND($K213<BC$5,(MONTH($K213)<>MONTH(BC$5))),$L213/26*Y213,$E213/26*Y213))) -> 7.5 | BD213: =+IF($K213="",$E213/26*Z213,IF(MONTH($K213)=MONTH(BD$5),$L213/26*Z213,IF(AND($K213<BD$5,(MONTH($K213)<>MONTH(BD$5))),$L213/26*Z213,$E213/26*Z213))) -> 7.5 | ... BH213: =+IF($K213="",$E213/26*AD213,IF(MONTH($K213)=MONTH(BH$5),$L213/26*AD213,IF(AND($K213<BH$5,(MONTH($K213)<>MONTH(BH$5))),$L213/26*AD213,$E213/26*AD213))) -> 7.5 | BI213: =SUM(BJ213:BU213) -> -90 | BJ213: =(+IF($K213="",$E213/26*AG213,IF(MONTH($K213)=MONTH(BJ$5),$L213/26*AG213,IF(AND($K213<BJ$5,(MONTH($K213)<>MONTH(BJ$5))),$L213/26*AG213,$E213/26*AG213))))*-1 -> -25 | BK213: =(+IF($K213="",$E213/26*AH213,IF(MONTH($K213)=MONTH(BK$5),$L213/26*AH213,IF(AND($K213<BK$5,(MONTH($K213)<>MONTH(BK$5))),$L213/26*AH213,$E213/26*AH213))))*-1 -> -65 | BL213: =(+IF($K213="",$E213/26*AI213,IF(MONTH($K213)=MONTH(BL$5),$L213/26*AI213,IF(AND($K213<BL$5,(MONTH($K213)<>MONTH(BL$5))),$L213/26*AI213,$E213/26*AI213))))*-1 -> 0 | BM213: =(+IF($K213="",$E213/26*AJ213,IF(MONTH($K213)=MONTH(BM$5),$L213/26*AJ213,IF(AND($K213<BM$5,(MONTH($K213)<>MONTH(BM$5))),$L213/26*AJ213,$E213/26*AJ213))))*-1 -> 0 | BN213: =(+IF($K213="",$E213/26*AK213,IF(MONTH($K213)=MONTH(BN$5),$L213/26*AK213,IF(AND($K213<BN$5,(MONTH($K213)<>MONTH(BN$5))),$L213/26*AK213,$E213/26*AK213))))*-1 -> 0 | BO213: =(+IF($K213="",$E213/26*AL213,IF(MONTH($K213)=MONTH(BO$5),$L213/26*AL213,IF(AND($K213<BO$5,(MONTH($K213)<>MONTH(BO$5))),$L213/26*AL213,$E213/26*AL213))))*-1 -> 0 | BP213: =(+IF($K213="",$E213/26*AM213,IF(MONTH($K213)=MONTH(BP$5),$L213/26*AM213,IF(AND($K213<BP$5,(MONTH($K213)<>MONTH(BP$5))),$L213/26*AM213,$E213/26*AM213))))*-1 -> 0 | BQ213: =(+IF($K213="",$E213/26*AN213,IF(MONTH($K213)=MONTH(BQ$5),$L213/26*AN213,IF(AND($K213<BQ$5,(MONTH($K213)<>MONTH(BQ$5))),$L213/26*AN213,$E213/26*AN213))))*-1 -> 0 | ... BU213: =(+IF($K213="",$E213/26*AR213,IF(MONTH($K213)=MONTH(BU$5),$L213/26*AR213,IF(AND($K213<BU$5,(MONTH($K213)<>MONTH(BU$5))),$L213/26*AR213,$E213/26*AR213))))*-1 -> 0 | BV213: =+AU213+AV213+BI213 -> 2.5 | BX213: =+IF(AND($J213>BX$5,MONTH($J213<>BX$5)),0,+IF(AND($J213>BX$5,MONTH($J213=BX$5)),$E213/$R213*DAY($J213),IF(AND($O213<>"",$O213<BX$5),0,IF($K213="",$E213/$R213*S213,IF(MONTH($K213)=MONTH(BX$5),$L213/$R213*S213,IF(AND($K213<BX$5,(MONTH($K213)<>MONTH(BX$5))),$L213/$R213*S213,$E213/$R213*S213)))))) -> 10.833333 | BY213: =+IF(AND($J213>BY$5,MONTH($J213<>BY$5)),0,+IF(AND($J213>BY$5,MONTH($J213=BY$5)),$E213/$R213*DAY($J213),IF(AND($O213<>"",$O213<BY$5),0,IF($K213="",$E213/$R213*T213,IF(MONTH($K213)=MONTH(BY$5),$L213/$R213*T213,IF(AND($K213<BY$5,(MONTH($K213)<>MONTH(BY$5))),$L213/$R213*T213,$E213/$R213*T213)))))) -> 10.833333 | BZ213: =+IF(AND($J213>BZ$5,MONTH($J213<>BZ$5)),0,+IF(AND($J213>BZ$5,MONTH($J213=BZ$5)),$E213/$R213*DAY($J213),IF(AND($O213<>"",$O213<BZ$5),0,IF($K213="",$E213/$R213*U213,IF(MONTH($K213)=MONTH(BZ$5),$L213/$R213*U213,IF(AND($K213<BZ$5,(MONTH($K213)<>MONTH(BZ$5))),$L213/$R213*U213,$E213/$R213*U213)))))) -> 10.833333 | CA213: =+IF(AND($J213>CA$5,MONTH($J213<>CA$5)),0,+IF(AND($J213>CA$5,MONTH($J213=CA$5)),$E213/$R213*DAY($J213),IF(AND($O213<>"",$O213<CA$5),0,IF($K213="",$E213/$R213*V213,IF(MONTH($K213)=MONTH(CA$5),$L213/$R213*V213,IF(AND($K213<CA$5,(MONTH($K213)<>MONTH(CA$5))),$L213/$R213*V213,$E213/$R213*V213)))))) -> 10.833333 | CB213: =+IF(AND($J213>CB$5,MONTH($J213<>CB$5)),0,+IF(AND($J213>CB$5,MONTH($J213=CB$5)),$E213/$R213*DAY($J213),IF(AND($O213<>"",$O213<CB$5),0,IF($K213="",$E213/$R213*W213,IF(MONTH($K213)=MONTH(CB$5),$L213/$R213*W213,IF(AND($K213<CB$5,(MONTH($K213)<>MONTH(CB$5))),$L213/$R213*W213,$E213/$R213*W213)))))) -> 10.833333 | CC213: =+IF(AND($J213>CC$5,MONTH($J213<>CC$5)),0,+IF(AND($J213>CC$5,MONTH($J213=CC$5)),$E213/$R213*DAY($J213),IF(AND($O213<>"",$O213<CC$5),0,IF($K213="",$E213/$R213*X213,IF(MONTH($K213)=MONTH(CC$5),$L213/$R213*X213,IF(AND($K213<CC$5,(MONTH($K213)<>MONTH(CC$5))),$L213/$R213*X213,$E213/$R213*X213)))))) -> 10.833333 | CD213: =+IF(AND($J213>CD$5,MONTH($J213<>CD$5)),0,+IF(AND($J213>CD$5,MONTH($J213=CD$5)),$E213/$R213*DAY($J213),IF(AND($O213<>"",$O213<CD$5),0,IF($K213="",$E213/$R213*Y213,IF(MONTH($K213)=MONTH(CD$5),$L213/$R213*Y213,IF(AND($K213<CD$5,(MONTH($K213)<>MONTH(CD$5))),$L213/$R213*Y213,$E213/$R213*Y213)))))) -> 10.833333 | CE213: =+IF(AND($J213>CE$5,MONTH($J213<>CE$5)),0,+IF(AND($J213>CE$5,MONTH($J213=CE$5)),$E213/$R213*DAY($J213),IF(AND($O213<>"",$O213<CE$5),0,IF($K213="",$E213/$R213*Z213,IF(MONTH($K213)=MONTH(CE$5),$L213/$R213*Z213,IF(AND($K213<CE$5,(MONTH($K213)<>MONTH(CE$5))),$L213/$R213*Z213,$E213/$R213*Z213)))))) -> 10.833333 | ... CI213: =+IF(AND($J213>CI$5,MONTH($J213<>CI$5)),0,+IF(AND($J213>CI$5,MONTH($J213=CI$5)),$E213/$R213*DAY($J213),IF(AND($O213<>"",$O213<CI$5),0,IF($K213="",$E213/$R213*AD213,IF(MONTH($K213)=MONTH(CI$5),$L213/$R213*AD213,IF(AND($K213<CI$5,(MONTH($K213)<>MONTH(CI$5))),$L213/$R213*AD213,$E213/$R213*AD213)))))) -> 10.833333 | CJ213: =SUM(BX213:CI213) -> 130 | CK213: =+IF(P213<5,18,IF(AND(P213>=5,P213<10),19,IF(AND(P213>=10,P213<15),20,IF(AND(P213>=15,P213<20),21,0)))) -> 18 | CL213: =+CM213-CJ213 -> 0 | CM213: =IF(L213=0,E213,(L213-E213+E213)) -> 130
A214: 07296 | B214: MIZUMI MUKAR BENEDICTE | C214: Receptionniste | D214: =+VLOOKUP(A214,'[1]BDD-Avk Tx'!B:CE,82,0) -> 120 | E214: 130 | G214: 45056 | H214: =+IF(YEAR(G214)<YEAR($H$5),$H$4,G214) -> 45647 | I214: =+VLOOKUP(A214,'[1]BDD-Avk Tx'!B:BZ,77,0) -> CDD | J214: =+IF(I214="CDI",H214,H214+0) -> 45647 | P214: =DATEDIF(G214,$AD$6,"m")/12 -> 2.5833333 | Q214: 2.5 | R214: =SUM(S214:AD214) -> 18 | S214: =+IF(AND(AND($O214="",$P214>=10,MONTH($G214)=MONTH(S$5))),1.5+2,+IF(AND(AND($O214="",$P214>=5,MONTH($G214)=MONTH(S$5))),1.5+1,+IF(AND(AND($P214=5,$O214="",MONTH($G214)=MONTH(S$5))),1.5,+IF(AND($H214>S$5,MONTH($H214)=MONTH(S$5)),1.5/30*(S$4-DAY($H214)),+IF(AND(MONTH($H214)<MONTH(S$5),$O214=""),1.5,+IF(AND($H214=$S$5,$O214=""),1.5,IF($O214<S$5,0,IF(MONTH($O214)=MONTH(S$5),1.5/30*($O214-S$5),1.5)))))))) -> 1.5 | T214: =+IF(AND(AND($O214="",$P214>=10,MONTH($G214)=MONTH(T$5))),1.5+2,+IF(AND(AND($O214="",$P214>=5,MONTH($G214)=MONTH(T$5))),1.5+1,+IF(AND(AND($P214=5,$O214="",MONTH($G214)=MONTH(T$5))),1.5,+IF(AND($H214>T$5,MONTH($H214)=MONTH(T$5)),1.5/30*(T$4-DAY($H214)),+IF(AND(MONTH($H214)<MONTH(T$5),$O214=""),1.5,+IF(AND($H214=$S$5,$O214=""),1.5,IF($O214<T$5,0,IF(MONTH($O214)=MONTH(T$5),1.5/30*($O214-T$5),1.5)))))))) -> 1.5 | U214: =+IF(AND(AND($O214="",$P214>=10,MONTH($G214)=MONTH(U$5))),1.5+2,+IF(AND(AND($O214="",$P214>=5,MONTH($G214)=MONTH(U$5))),1.5+1,+IF(AND(AND($P214=5,$O214="",MONTH($G214)=MONTH(U$5))),1.5,+IF(AND($H214>U$5,MONTH($H214)=MONTH(U$5)),1.5/30*(U$4-DAY($H214)),+IF(AND(MONTH($H214)<MONTH(U$5),$O214=""),1.5,+IF(AND($H214=$S$5,$O214=""),1.5,IF($O214<U$5,0,IF(MONTH($O214)=MONTH(U$5),1.5/30*($O214-U$5),1.5)))))))) -> 1.5 | V214: =+IF(AND(AND($O214="",$P214>=10,MONTH($G214)=MONTH(V$5))),1.5+2,+IF(AND(AND($O214="",$P214>=5,MONTH($G214)=MONTH(V$5))),1.5+1,+IF(AND(AND($P214=5,$O214="",MONTH($G214)=MONTH(V$5))),1.5,+IF(AND($H214>V$5,MONTH($H214)=MONTH(V$5)),1.5/30*(V$4-DAY($H214)),+IF(AND(MONTH($H214)<MONTH(V$5),$O214=""),1.5,+IF(AND($H214=$S$5,$O214=""),1.5,IF($O214<V$5,0,IF(MONTH($O214)=MONTH(V$5),1.5/30*($O214-V$5),1.5)))))))) -> 1.5 | W214: =+IF(AND(AND($O214="",$P214>=10,MONTH($G214)=MONTH(W$5))),1.5+2,+IF(AND(AND($O214="",$P214>=5,MONTH($G214)=MONTH(W$5))),1.5+1,+IF(AND(AND($P214=5,$O214="",MONTH($G214)=MONTH(W$5))),1.5,+IF(AND($H214>W$5,MONTH($H214)=MONTH(W$5)),1.5/30*(W$4-DAY($H214)),+IF(AND(MONTH($H214)<MONTH(W$5),$O214=""),1.5,+IF(AND($H214=$S$5,$O214=""),1.5,IF($O214<W$5,0,IF(MONTH($O214)=MONTH(W$5),1.5/30*($O214-W$5),1.5)))))))) -> 1.5 | X214: =+IF(AND(AND($O214="",$P214>=10,MONTH($G214)=MONTH(X$5))),1.5+2,+IF(AND(AND($O214="",$P214>=5,MONTH($G214)=MONTH(X$5))),1.5+1,+IF(AND(AND($P214=5,$O214="",MONTH($G214)=MONTH(X$5))),1.5,+IF(AND($H214>X$5,MONTH($H214)=MONTH(X$5)),1.5/30*(X$4-DAY($H214)),+IF(AND(MONTH($H214)<MONTH(X$5),$O214=""),1.5,+IF(AND($H214=$S$5,$O214=""),1.5,IF($O214<X$5,0,IF(MONTH($O214)=MONTH(X$5),1.5/30*($O214-X$5),1.5)))))))) -> 1.5 | Y214: =+IF(AND(AND($O214="",$P214>=10,MONTH($G214)=MONTH(Y$5))),1.5+2,+IF(AND(AND($O214="",$P214>=5,MONTH($G214)=MONTH(Y$5))),1.5+1,+IF(AND(AND($P214=5,$O214="",MONTH($G214)=MONTH(Y$5))),1.5,+IF(AND($H214>Y$5,MONTH($H214)=MONTH(Y$5)),1.5/30*(Y$4-DAY($H214)),+IF(AND(MONTH($H214)<MONTH(Y$5),$O214=""),1.5,+IF(AND($H214=$S$5,$O214=""),1.5,IF($O214<Y$5,0,IF(MONTH($O214)=MONTH(Y$5),1.5/30*($O214-Y$5),1.5)))))))) -> 1.5 | Z214: =+IF(AND(AND($O214="",$P214>=10,MONTH($G214)=MONTH(Z$5))),1.5+2,+IF(AND(AND($O214="",$P214>=5,MONTH($G214)=MONTH(Z$5))),1.5+1,+IF(AND(AND($P214=5,$O214="",MONTH($G214)=MONTH(Z$5))),1.5,+IF(AND($H214>Z$5,MONTH($H214)=MONTH(Z$5)),1.5/30*(Z$4-DAY($H214)),+IF(AND(MONTH($H214)<MONTH(Z$5),$O214=""),1.5,+IF(AND($H214=$S$5,$O214=""),1.5,IF($O214<Z$5,0,IF(MONTH($O214)=MONTH(Z$5),1.5/30*($O214-Z$5),1.5)))))))) -> 1.5 | ... AD214: =+IF(AND(AND($O214="",$P214>=10,MONTH($G214)=MONTH(AD$5))),1.5+2,+IF(AND(AND($O214="",$P214>=5,MONTH($G214)=MONTH(AD$5))),1.5+1,+IF(AND(AND($P214=5,$O214="",MONTH($G214)=MONTH(AD$5))),1.5,+IF(AND($H214>AD$5,MONTH($H214)=MONTH(AD$5)),1.5/30*(AD$4-DAY($H214)),+IF(AND(MONTH($H214)<MONTH(AD$5),$O214=""),1.5,+IF(AND($H214=$S$5,$O214=""),1.5,IF($O214<AD$5,0,IF(MONTH($O214)=MONTH(AD$5),1.5/30*($O214-AD$5),1.5)))))))) -> 1.5 | AF214: =SUM(AG214:AR214) -> 0 | AG214: 0 | AH214: 0 | AI214: 0 | AS214: =+Q214+R214-AF214 -> 20.5 | AU214: 12.5 | AV214: =SUM(AW214:BH214) -> 90 | AW214: =+IF($K214="",$E214/26*S214,IF(MONTH($K214)=MONTH(AW$5),$L214/26*S214,IF(AND($K214<AW$5,(MONTH($K214)<>MONTH(AW$5))),$L214/26*S214,$E214/26*S214))) -> 7.5 | AX214: =+IF($K214="",$E214/26*T214,IF(MONTH($K214)=MONTH(AX$5),$L214/26*T214,IF(AND($K214<AX$5,(MONTH($K214)<>MONTH(AX$5))),$L214/26*T214,$E214/26*T214))) -> 7.5 | AY214: =+IF($K214="",$E214/26*U214,IF(MONTH($K214)=MONTH(AY$5),$L214/26*U214,IF(AND($K214<AY$5,(MONTH($K214)<>MONTH(AY$5))),$L214/26*U214,$E214/26*U214))) -> 7.5 | AZ214: =+IF($K214="",$E214/26*V214,IF(MONTH($K214)=MONTH(AZ$5),$L214/26*V214,IF(AND($K214<AZ$5,(MONTH($K214)<>MONTH(AZ$5))),$L214/26*V214,$E214/26*V214))) -> 7.5 | BA214: =+IF($K214="",$E214/26*W214,IF(MONTH($K214)=MONTH(BA$5),$L214/26*W214,IF(AND($K214<BA$5,(MONTH($K214)<>MONTH(BA$5))),$L214/26*W214,$E214/26*W214))) -> 7.5 | BB214: =+IF($K214="",$E214/26*X214,IF(MONTH($K214)=MONTH(BB$5),$L214/26*X214,IF(AND($K214<BB$5,(MONTH($K214)<>MONTH(BB$5))),$L214/26*X214,$E214/26*X214))) -> 7.5 | BC214: =+IF($K214="",$E214/26*Y214,IF(MONTH($K214)=MONTH(BC$5),$L214/26*Y214,IF(AND($K214<BC$5,(MONTH($K214)<>MONTH(BC$5))),$L214/26*Y214,$E214/26*Y214))) -> 7.5 | BD214: =+IF($K214="",$E214/26*Z214,IF(MONTH($K214)=MONTH(BD$5),$L214/26*Z214,IF(AND($K214<BD$5,(MONTH($K214)<>MONTH(BD$5))),$L214/26*Z214,$E214/26*Z214))) -> 7.5 | ... BH214: =+IF($K214="",$E214/26*AD214,IF(MONTH($K214)=MONTH(BH$5),$L214/26*AD214,IF(AND($K214<BH$5,(MONTH($K214)<>MONTH(BH$5))),$L214/26*AD214,$E214/26*AD214))) -> 7.5 | BI214: =SUM(BJ214:BU214) -> 0 | BJ214: =(+IF($K214="",$E214/26*AG214,IF(MONTH($K214)=MONTH(BJ$5),$L214/26*AG214,IF(AND($K214<BJ$5,(MONTH($K214)<>MONTH(BJ$5))),$L214/26*AG214,$E214/26*AG214))))*-1 -> 0 | BK214: =(+IF($K214="",$E214/26*AH214,IF(MONTH($K214)=MONTH(BK$5),$L214/26*AH214,IF(AND($K214<BK$5,(MONTH($K214)<>MONTH(BK$5))),$L214/26*AH214,$E214/26*AH214))))*-1 -> 0 | BL214: =(+IF($K214="",$E214/26*AI214,IF(MONTH($K214)=MONTH(BL$5),$L214/26*AI214,IF(AND($K214<BL$5,(MONTH($K214)<>MONTH(BL$5))),$L214/26*AI214,$E214/26*AI214))))*-1 -> 0 | BM214: =(+IF($K214="",$E214/26*AJ214,IF(MONTH($K214)=MONTH(BM$5),$L214/26*AJ214,IF(AND($K214<BM$5,(MONTH($K214)<>MONTH(BM$5))),$L214/26*AJ214,$E214/26*AJ214))))*-1 -> 0 | BN214: =(+IF($K214="",$E214/26*AK214,IF(MONTH($K214)=MONTH(BN$5),$L214/26*AK214,IF(AND($K214<BN$5,(MONTH($K214)<>MONTH(BN$5))),$L214/26*AK214,$E214/26*AK214))))*-1 -> 0 | BO214: =(+IF($K214="",$E214/26*AL214,IF(MONTH($K214)=MONTH(BO$5),$L214/26*AL214,IF(AND($K214<BO$5,(MONTH($K214)<>MONTH(BO$5))),$L214/26*AL214,$E214/26*AL214))))*-1 -> 0 | BP214: =(+IF($K214="",$E214/26*AM214,IF(MONTH($K214)=MONTH(BP$5),$L214/26*AM214,IF(AND($K214<BP$5,(MONTH($K214)<>MONTH(BP$5))),$L214/26*AM214,$E214/26*AM214))))*-1 -> 0 | BQ214: =(+IF($K214="",$E214/26*AN214,IF(MONTH($K214)=MONTH(BQ$5),$L214/26*AN214,IF(AND($K214<BQ$5,(MONTH($K214)<>MONTH(BQ$5))),$L214/26*AN214,$E214/26*AN214))))*-1 -> 0 | ... BU214: =(+IF($K214="",$E214/26*AR214,IF(MONTH($K214)=MONTH(BU$5),$L214/26*AR214,IF(AND($K214<BU$5,(MONTH($K214)<>MONTH(BU$5))),$L214/26*AR214,$E214/26*AR214))))*-1 -> 0 | BV214: =+AU214+AV214+BI214 -> 102.5 | BX214: =+IF(AND($J214>BX$5,MONTH($J214<>BX$5)),0,+IF(AND($J214>BX$5,MONTH($J214=BX$5)),$E214/$R214*DAY($J214),IF(AND($O214<>"",$O214<BX$5),0,IF($K214="",$E214/$R214*S214,IF(MONTH($K214)=MONTH(BX$5),$L214/$R214*S214,IF(AND($K214<BX$5,(MONTH($K214)<>MONTH(BX$5))),$L214/$R214*S214,$E214/$R214*S214)))))) -> 10.833333 | BY214: =+IF(AND($J214>BY$5,MONTH($J214<>BY$5)),0,+IF(AND($J214>BY$5,MONTH($J214=BY$5)),$E214/$R214*DAY($J214),IF(AND($O214<>"",$O214<BY$5),0,IF($K214="",$E214/$R214*T214,IF(MONTH($K214)=MONTH(BY$5),$L214/$R214*T214,IF(AND($K214<BY$5,(MONTH($K214)<>MONTH(BY$5))),$L214/$R214*T214,$E214/$R214*T214)))))) -> 10.833333 | BZ214: =+IF(AND($J214>BZ$5,MONTH($J214<>BZ$5)),0,+IF(AND($J214>BZ$5,MONTH($J214=BZ$5)),$E214/$R214*DAY($J214),IF(AND($O214<>"",$O214<BZ$5),0,IF($K214="",$E214/$R214*U214,IF(MONTH($K214)=MONTH(BZ$5),$L214/$R214*U214,IF(AND($K214<BZ$5,(MONTH($K214)<>MONTH(BZ$5))),$L214/$R214*U214,$E214/$R214*U214)))))) -> 10.833333 | CA214: =+IF(AND($J214>CA$5,MONTH($J214<>CA$5)),0,+IF(AND($J214>CA$5,MONTH($J214=CA$5)),$E214/$R214*DAY($J214),IF(AND($O214<>"",$O214<CA$5),0,IF($K214="",$E214/$R214*V214,IF(MONTH($K214)=MONTH(CA$5),$L214/$R214*V214,IF(AND($K214<CA$5,(MONTH($K214)<>MONTH(CA$5))),$L214/$R214*V214,$E214/$R214*V214)))))) -> 10.833333 | CB214: =+IF(AND($J214>CB$5,MONTH($J214<>CB$5)),0,+IF(AND($J214>CB$5,MONTH($J214=CB$5)),$E214/$R214*DAY($J214),IF(AND($O214<>"",$O214<CB$5),0,IF($K214="",$E214/$R214*W214,IF(MONTH($K214)=MONTH(CB$5),$L214/$R214*W214,IF(AND($K214<CB$5,(MONTH($K214)<>MONTH(CB$5))),$L214/$R214*W214,$E214/$R214*W214)))))) -> 10.833333 | CC214: =+IF(AND($J214>CC$5,MONTH($J214<>CC$5)),0,+IF(AND($J214>CC$5,MONTH($J214=CC$5)),$E214/$R214*DAY($J214),IF(AND($O214<>"",$O214<CC$5),0,IF($K214="",$E214/$R214*X214,IF(MONTH($K214)=MONTH(CC$5),$L214/$R214*X214,IF(AND($K214<CC$5,(MONTH($K214)<>MONTH(CC$5))),$L214/$R214*X214,$E214/$R214*X214)))))) -> 10.833333 | CD214: =+IF(AND($J214>CD$5,MONTH($J214<>CD$5)),0,+IF(AND($J214>CD$5,MONTH($J214=CD$5)),$E214/$R214*DAY($J214),IF(AND($O214<>"",$O214<CD$5),0,IF($K214="",$E214/$R214*Y214,IF(MONTH($K214)=MONTH(CD$5),$L214/$R214*Y214,IF(AND($K214<CD$5,(MONTH($K214)<>MONTH(CD$5))),$L214/$R214*Y214,$E214/$R214*Y214)))))) -> 10.833333 | CE214: =+IF(AND($J214>CE$5,MONTH($J214<>CE$5)),0,+IF(AND($J214>CE$5,MONTH($J214=CE$5)),$E214/$R214*DAY($J214),IF(AND($O214<>"",$O214<CE$5),0,IF($K214="",$E214/$R214*Z214,IF(MONTH($K214)=MONTH(CE$5),$L214/$R214*Z214,IF(AND($K214<CE$5,(MONTH($K214)<>MONTH(CE$5))),$L214/$R214*Z214,$E214/$R214*Z214)))))) -> 10.833333 | ... CI214: =+IF(AND($J214>CI$5,MONTH($J214<>CI$5)),0,+IF(AND($J214>CI$5,MONTH($J214=CI$5)),$E214/$R214*DAY($J214),IF(AND($O214<>"",$O214<CI$5),0,IF($K214="",$E214/$R214*AD214,IF(MONTH($K214)=MONTH(CI$5),$L214/$R214*AD214,IF(AND($K214<CI$5,(MONTH($K214)<>MONTH(CI$5))),$L214/$R214*AD214,$E214/$R214*AD214)))))) -> 10.833333 | CJ214: =SUM(BX214:CI214) -> 130 | CK214: =+IF(P214<5,18,IF(AND(P214>=5,P214<10),19,IF(AND(P214>=10,P214<15),20,IF(AND(P214>=15,P214<20),21,0)))) -> 18 | CL214: =+CM214-CJ214 -> 0 | CM214: =IF(L214=0,E214,(L214-E214+E214)) -> 130
A215: 07297 | B215: LUBADIKA KWAYENO RODRICK | C215: Commis de Cuisine | D215: =+VLOOKUP(A215,'[1]BDD-Avk Tx'!B:CE,82,0) -> 281 | E215: 130 | G215: 45067 | H215: =+IF(YEAR(G215)<YEAR($H$5),$H$4,G215) -> 45647 | I215: =+VLOOKUP(A215,'[1]BDD-Avk Tx'!B:BZ,77,0) -> CDD | J215: =+IF(I215="CDI",H215,H215+0) -> 45647 | P215: =DATEDIF(G215,$AD$6,"m")/12 -> 2.5 | Q215: -0.5 | R215: =SUM(S215:AD215) -> 18 | S215: =+IF(AND(AND($O215="",$P215>=10,MONTH($G215)=MONTH(S$5))),1.5+2,+IF(AND(AND($O215="",$P215>=5,MONTH($G215)=MONTH(S$5))),1.5+1,+IF(AND(AND($P215=5,$O215="",MONTH($G215)=MONTH(S$5))),1.5,+IF(AND($H215>S$5,MONTH($H215)=MONTH(S$5)),1.5/30*(S$4-DAY($H215)),+IF(AND(MONTH($H215)<MONTH(S$5),$O215=""),1.5,+IF(AND($H215=$S$5,$O215=""),1.5,IF($O215<S$5,0,IF(MONTH($O215)=MONTH(S$5),1.5/30*($O215-S$5),1.5)))))))) -> 1.5 | T215: =+IF(AND(AND($O215="",$P215>=10,MONTH($G215)=MONTH(T$5))),1.5+2,+IF(AND(AND($O215="",$P215>=5,MONTH($G215)=MONTH(T$5))),1.5+1,+IF(AND(AND($P215=5,$O215="",MONTH($G215)=MONTH(T$5))),1.5,+IF(AND($H215>T$5,MONTH($H215)=MONTH(T$5)),1.5/30*(T$4-DAY($H215)),+IF(AND(MONTH($H215)<MONTH(T$5),$O215=""),1.5,+IF(AND($H215=$S$5,$O215=""),1.5,IF($O215<T$5,0,IF(MONTH($O215)=MONTH(T$5),1.5/30*($O215-T$5),1.5)))))))) -> 1.5 | U215: =+IF(AND(AND($O215="",$P215>=10,MONTH($G215)=MONTH(U$5))),1.5+2,+IF(AND(AND($O215="",$P215>=5,MONTH($G215)=MONTH(U$5))),1.5+1,+IF(AND(AND($P215=5,$O215="",MONTH($G215)=MONTH(U$5))),1.5,+IF(AND($H215>U$5,MONTH($H215)=MONTH(U$5)),1.5/30*(U$4-DAY($H215)),+IF(AND(MONTH($H215)<MONTH(U$5),$O215=""),1.5,+IF(AND($H215=$S$5,$O215=""),1.5,IF($O215<U$5,0,IF(MONTH($O215)=MONTH(U$5),1.5/30*($O215-U$5),1.5)))))))) -> 1.5 | V215: =+IF(AND(AND($O215="",$P215>=10,MONTH($G215)=MONTH(V$5))),1.5+2,+IF(AND(AND($O215="",$P215>=5,MONTH($G215)=MONTH(V$5))),1.5+1,+IF(AND(AND($P215=5,$O215="",MONTH($G215)=MONTH(V$5))),1.5,+IF(AND($H215>V$5,MONTH($H215)=MONTH(V$5)),1.5/30*(V$4-DAY($H215)),+IF(AND(MONTH($H215)<MONTH(V$5),$O215=""),1.5,+IF(AND($H215=$S$5,$O215=""),1.5,IF($O215<V$5,0,IF(MONTH($O215)=MONTH(V$5),1.5/30*($O215-V$5),1.5)))))))) -> 1.5 | W215: =+IF(AND(AND($O215="",$P215>=10,MONTH($G215)=MONTH(W$5))),1.5+2,+IF(AND(AND($O215="",$P215>=5,MONTH($G215)=MONTH(W$5))),1.5+1,+IF(AND(AND($P215=5,$O215="",MONTH($G215)=MONTH(W$5))),1.5,+IF(AND($H215>W$5,MONTH($H215)=MONTH(W$5)),1.5/30*(W$4-DAY($H215)),+IF(AND(MONTH($H215)<MONTH(W$5),$O215=""),1.5,+IF(AND($H215=$S$5,$O215=""),1.5,IF($O215<W$5,0,IF(MONTH($O215)=MONTH(W$5),1.5/30*($O215-W$5),1.5)))))))) -> 1.5 | X215: =+IF(AND(AND($O215="",$P215>=10,MONTH($G215)=MONTH(X$5))),1.5+2,+IF(AND(AND($O215="",$P215>=5,MONTH($G215)=MONTH(X$5))),1.5+1,+IF(AND(AND($P215=5,$O215="",MONTH($G215)=MONTH(X$5))),1.5,+IF(AND($H215>X$5,MONTH($H215)=MONTH(X$5)),1.5/30*(X$4-DAY($H215)),+IF(AND(MONTH($H215)<MONTH(X$5),$O215=""),1.5,+IF(AND($H215=$S$5,$O215=""),1.5,IF($O215<X$5,0,IF(MONTH($O215)=MONTH(X$5),1.5/30*($O215-X$5),1.5)))))))) -> 1.5 | Y215: =+IF(AND(AND($O215="",$P215>=10,MONTH($G215)=MONTH(Y$5))),1.5+2,+IF(AND(AND($O215="",$P215>=5,MONTH($G215)=MONTH(Y$5))),1.5+1,+IF(AND(AND($P215=5,$O215="",MONTH($G215)=MONTH(Y$5))),1.5,+IF(AND($H215>Y$5,MONTH($H215)=MONTH(Y$5)),1.5/30*(Y$4-DAY($H215)),+IF(AND(MONTH($H215)<MONTH(Y$5),$O215=""),1.5,+IF(AND($H215=$S$5,$O215=""),1.5,IF($O215<Y$5,0,IF(MONTH($O215)=MONTH(Y$5),1.5/30*($O215-Y$5),1.5)))))))) -> 1.5 | Z215: =+IF(AND(AND($O215="",$P215>=10,MONTH($G215)=MONTH(Z$5))),1.5+2,+IF(AND(AND($O215="",$P215>=5,MONTH($G215)=MONTH(Z$5))),1.5+1,+IF(AND(AND($P215=5,$O215="",MONTH($G215)=MONTH(Z$5))),1.5,+IF(AND($H215>Z$5,MONTH($H215)=MONTH(Z$5)),1.5/30*(Z$4-DAY($H215)),+IF(AND(MONTH($H215)<MONTH(Z$5),$O215=""),1.5,+IF(AND($H215=$S$5,$O215=""),1.5,IF($O215<Z$5,0,IF(MONTH($O215)=MONTH(Z$5),1.5/30*($O215-Z$5),1.5)))))))) -> 1.5 | ... AD215: =+IF(AND(AND($O215="",$P215>=10,MONTH($G215)=MONTH(AD$5))),1.5+2,+IF(AND(AND($O215="",$P215>=5,MONTH($G215)=MONTH(AD$5))),1.5+1,+IF(AND(AND($P215=5,$O215="",MONTH($G215)=MONTH(AD$5))),1.5,+IF(AND($H215>AD$5,MONTH($H215)=MONTH(AD$5)),1.5/30*(AD$4-DAY($H215)),+IF(AND(MONTH($H215)<MONTH(AD$5),$O215=""),1.5,+IF(AND($H215=$S$5,$O215=""),1.5,IF($O215<AD$5,0,IF(MONTH($O215)=MONTH(AD$5),1.5/30*($O215-AD$5),1.5)))))))) -> 1.5 | AF215: =SUM(AG215:AR215) -> 17 | AG215: 5 | AH215: 12 | AI215: 0 | AS215: =+Q215+R215-AF215 -> 0.5 | AU215: -2.5 | AV215: =SUM(AW215:BH215) -> 90 | AW215: =+IF($K215="",$E215/26*S215,IF(MONTH($K215)=MONTH(AW$5),$L215/26*S215,IF(AND($K215<AW$5,(MONTH($K215)<>MONTH(AW$5))),$L215/26*S215,$E215/26*S215))) -> 7.5 | AX215: =+IF($K215="",$E215/26*T215,IF(MONTH($K215)=MONTH(AX$5),$L215/26*T215,IF(AND($K215<AX$5,(MONTH($K215)<>MONTH(AX$5))),$L215/26*T215,$E215/26*T215))) -> 7.5 | AY215: =+IF($K215="",$E215/26*U215,IF(MONTH($K215)=MONTH(AY$5),$L215/26*U215,IF(AND($K215<AY$5,(MONTH($K215)<>MONTH(AY$5))),$L215/26*U215,$E215/26*U215))) -> 7.5 | AZ215: =+IF($K215="",$E215/26*V215,IF(MONTH($K215)=MONTH(AZ$5),$L215/26*V215,IF(AND($K215<AZ$5,(MONTH($K215)<>MONTH(AZ$5))),$L215/26*V215,$E215/26*V215))) -> 7.5 | BA215: =+IF($K215="",$E215/26*W215,IF(MONTH($K215)=MONTH(BA$5),$L215/26*W215,IF(AND($K215<BA$5,(MONTH($K215)<>MONTH(BA$5))),$L215/26*W215,$E215/26*W215))) -> 7.5 | BB215: =+IF($K215="",$E215/26*X215,IF(MONTH($K215)=MONTH(BB$5),$L215/26*X215,IF(AND($K215<BB$5,(MONTH($K215)<>MONTH(BB$5))),$L215/26*X215,$E215/26*X215))) -> 7.5 | BC215: =+IF($K215="",$E215/26*Y215,IF(MONTH($K215)=MONTH(BC$5),$L215/26*Y215,IF(AND($K215<BC$5,(MONTH($K215)<>MONTH(BC$5))),$L215/26*Y215,$E215/26*Y215))) -> 7.5 | BD215: =+IF($K215="",$E215/26*Z215,IF(MONTH($K215)=MONTH(BD$5),$L215/26*Z215,IF(AND($K215<BD$5,(MONTH($K215)<>MONTH(BD$5))),$L215/26*Z215,$E215/26*Z215))) -> 7.5 | ... BH215: =+IF($K215="",$E215/26*AD215,IF(MONTH($K215)=MONTH(BH$5),$L215/26*AD215,IF(AND($K215<BH$5,(MONTH($K215)<>MONTH(BH$5))),$L215/26*AD215,$E215/26*AD215))) -> 7.5 | BI215: =SUM(BJ215:BU215) -> -85 | BJ215: =(+IF($K215="",$E215/26*AG215,IF(MONTH($K215)=MONTH(BJ$5),$L215/26*AG215,IF(AND($K215<BJ$5,(MONTH($K215)<>MONTH(BJ$5))),$L215/26*AG215,$E215/26*AG215))))*-1 -> -25 | BK215: =(+IF($K215="",$E215/26*AH215,IF(MONTH($K215)=MONTH(BK$5),$L215/26*AH215,IF(AND($K215<BK$5,(MONTH($K215)<>MONTH(BK$5))),$L215/26*AH215,$E215/26*AH215))))*-1 -> -60 | BL215: =(+IF($K215="",$E215/26*AI215,IF(MONTH($K215)=MONTH(BL$5),$L215/26*AI215,IF(AND($K215<BL$5,(MONTH($K215)<>MONTH(BL$5))),$L215/26*AI215,$E215/26*AI215))))*-1 -> 0 | BM215: =(+IF($K215="",$E215/26*AJ215,IF(MONTH($K215)=MONTH(BM$5),$L215/26*AJ215,IF(AND($K215<BM$5,(MONTH($K215)<>MONTH(BM$5))),$L215/26*AJ215,$E215/26*AJ215))))*-1 -> 0 | BN215: =(+IF($K215="",$E215/26*AK215,IF(MONTH($K215)=MONTH(BN$5),$L215/26*AK215,IF(AND($K215<BN$5,(MONTH($K215)<>MONTH(BN$5))),$L215/26*AK215,$E215/26*AK215))))*-1 -> 0 | BO215: =(+IF($K215="",$E215/26*AL215,IF(MONTH($K215)=MONTH(BO$5),$L215/26*AL215,IF(AND($K215<BO$5,(MONTH($K215)<>MONTH(BO$5))),$L215/26*AL215,$E215/26*AL215))))*-1 -> 0 | BP215: =(+IF($K215="",$E215/26*AM215,IF(MONTH($K215)=MONTH(BP$5),$L215/26*AM215,IF(AND($K215<BP$5,(MONTH($K215)<>MONTH(BP$5))),$L215/26*AM215,$E215/26*AM215))))*-1 -> 0 | BQ215: =(+IF($K215="",$E215/26*AN215,IF(MONTH($K215)=MONTH(BQ$5),$L215/26*AN215,IF(AND($K215<BQ$5,(MONTH($K215)<>MONTH(BQ$5))),$L215/26*AN215,$E215/26*AN215))))*-1 -> 0 | ... BU215: =(+IF($K215="",$E215/26*AR215,IF(MONTH($K215)=MONTH(BU$5),$L215/26*AR215,IF(AND($K215<BU$5,(MONTH($K215)<>MONTH(BU$5))),$L215/26*AR215,$E215/26*AR215))))*-1 -> 0 | BV215: =+AU215+AV215+BI215 -> 2.5 | BX215: =+IF(AND($J215>BX$5,MONTH($J215<>BX$5)),0,+IF(AND($J215>BX$5,MONTH($J215=BX$5)),$E215/$R215*DAY($J215),IF(AND($O215<>"",$O215<BX$5),0,IF($K215="",$E215/$R215*S215,IF(MONTH($K215)=MONTH(BX$5),$L215/$R215*S215,IF(AND($K215<BX$5,(MONTH($K215)<>MONTH(BX$5))),$L215/$R215*S215,$E215/$R215*S215)))))) -> 10.833333 | BY215: =+IF(AND($J215>BY$5,MONTH($J215<>BY$5)),0,+IF(AND($J215>BY$5,MONTH($J215=BY$5)),$E215/$R215*DAY($J215),IF(AND($O215<>"",$O215<BY$5),0,IF($K215="",$E215/$R215*T215,IF(MONTH($K215)=MONTH(BY$5),$L215/$R215*T215,IF(AND($K215<BY$5,(MONTH($K215)<>MONTH(BY$5))),$L215/$R215*T215,$E215/$R215*T215)))))) -> 10.833333 | BZ215: =+IF(AND($J215>BZ$5,MONTH($J215<>BZ$5)),0,+IF(AND($J215>BZ$5,MONTH($J215=BZ$5)),$E215/$R215*DAY($J215),IF(AND($O215<>"",$O215<BZ$5),0,IF($K215="",$E215/$R215*U215,IF(MONTH($K215)=MONTH(BZ$5),$L215/$R215*U215,IF(AND($K215<BZ$5,(MONTH($K215)<>MONTH(BZ$5))),$L215/$R215*U215,$E215/$R215*U215)))))) -> 10.833333 | CA215: =+IF(AND($J215>CA$5,MONTH($J215<>CA$5)),0,+IF(AND($J215>CA$5,MONTH($J215=CA$5)),$E215/$R215*DAY($J215),IF(AND($O215<>"",$O215<CA$5),0,IF($K215="",$E215/$R215*V215,IF(MONTH($K215)=MONTH(CA$5),$L215/$R215*V215,IF(AND($K215<CA$5,(MONTH($K215)<>MONTH(CA$5))),$L215/$R215*V215,$E215/$R215*V215)))))) -> 10.833333 | CB215: =+IF(AND($J215>CB$5,MONTH($J215<>CB$5)),0,+IF(AND($J215>CB$5,MONTH($J215=CB$5)),$E215/$R215*DAY($J215),IF(AND($O215<>"",$O215<CB$5),0,IF($K215="",$E215/$R215*W215,IF(MONTH($K215)=MONTH(CB$5),$L215/$R215*W215,IF(AND($K215<CB$5,(MONTH($K215)<>MONTH(CB$5))),$L215/$R215*W215,$E215/$R215*W215)))))) -> 10.833333 | CC215: =+IF(AND($J215>CC$5,MONTH($J215<>CC$5)),0,+IF(AND($J215>CC$5,MONTH($J215=CC$5)),$E215/$R215*DAY($J215),IF(AND($O215<>"",$O215<CC$5),0,IF($K215="",$E215/$R215*X215,IF(MONTH($K215)=MONTH(CC$5),$L215/$R215*X215,IF(AND($K215<CC$5,(MONTH($K215)<>MONTH(CC$5))),$L215/$R215*X215,$E215/$R215*X215)))))) -> 10.833333 | CD215: =+IF(AND($J215>CD$5,MONTH($J215<>CD$5)),0,+IF(AND($J215>CD$5,MONTH($J215=CD$5)),$E215/$R215*DAY($J215),IF(AND($O215<>"",$O215<CD$5),0,IF($K215="",$E215/$R215*Y215,IF(MONTH($K215)=MONTH(CD$5),$L215/$R215*Y215,IF(AND($K215<CD$5,(MONTH($K215)<>MONTH(CD$5))),$L215/$R215*Y215,$E215/$R215*Y215)))))) -> 10.833333 | CE215: =+IF(AND($J215>CE$5,MONTH($J215<>CE$5)),0,+IF(AND($J215>CE$5,MONTH($J215=CE$5)),$E215/$R215*DAY($J215),IF(AND($O215<>"",$O215<CE$5),0,IF($K215="",$E215/$R215*Z215,IF(MONTH($K215)=MONTH(CE$5),$L215/$R215*Z215,IF(AND($K215<CE$5,(MONTH($K215)<>MONTH(CE$5))),$L215/$R215*Z215,$E215/$R215*Z215)))))) -> 10.833333 | ... CI215: =+IF(AND($J215>CI$5,MONTH($J215<>CI$5)),0,+IF(AND($J215>CI$5,MONTH($J215=CI$5)),$E215/$R215*DAY($J215),IF(AND($O215<>"",$O215<CI$5),0,IF($K215="",$E215/$R215*AD215,IF(MONTH($K215)=MONTH(CI$5),$L215/$R215*AD215,IF(AND($K215<CI$5,(MONTH($K215)<>MONTH(CI$5))),$L215/$R215*AD215,$E215/$R215*AD215)))))) -> 10.833333 | CJ215: =SUM(BX215:CI215) -> 130 | CK215: =+IF(P215<5,18,IF(AND(P215>=5,P215<10),19,IF(AND(P215>=10,P215<15),20,IF(AND(P215>=15,P215<20),21,0)))) -> 18 | CL215: =+CM215-CJ215 -> 0 | CM215: =IF(L215=0,E215,(L215-E215+E215)) -> 130
A216: 07299 | B216: BOYAKA ITALE ARMAND | C216: Technicien Frigoriste | D216: =+VLOOKUP(A216,'[1]BDD-Avk Tx'!B:CE,82,0) -> 810 | E216: 172.9 | G216: 45093 | H216: =+IF(YEAR(G216)<YEAR($H$5),$H$4,G216) -> 45647 | I216: =+VLOOKUP(A216,'[1]BDD-Avk Tx'!B:BZ,77,0) -> CDD | J216: =+IF(I216="CDI",H216,H216+0) -> 45647 | P216: =DATEDIF(G216,$AD$6,"m")/12 -> 2.5 | Q216: 0 | R216: =SUM(S216:AD216) -> 18 | S216: =+IF(AND(AND($O216="",$P216>=10,MONTH($G216)=MONTH(S$5))),1.5+2,+IF(AND(AND($O216="",$P216>=5,MONTH($G216)=MONTH(S$5))),1.5+1,+IF(AND(AND($P216=5,$O216="",MONTH($G216)=MONTH(S$5))),1.5,+IF(AND($H216>S$5,MONTH($H216)=MONTH(S$5)),1.5/30*(S$4-DAY($H216)),+IF(AND(MONTH($H216)<MONTH(S$5),$O216=""),1.5,+IF(AND($H216=$S$5,$O216=""),1.5,IF($O216<S$5,0,IF(MONTH($O216)=MONTH(S$5),1.5/30*($O216-S$5),1.5)))))))) -> 1.5 | T216: =+IF(AND(AND($O216="",$P216>=10,MONTH($G216)=MONTH(T$5))),1.5+2,+IF(AND(AND($O216="",$P216>=5,MONTH($G216)=MONTH(T$5))),1.5+1,+IF(AND(AND($P216=5,$O216="",MONTH($G216)=MONTH(T$5))),1.5,+IF(AND($H216>T$5,MONTH($H216)=MONTH(T$5)),1.5/30*(T$4-DAY($H216)),+IF(AND(MONTH($H216)<MONTH(T$5),$O216=""),1.5,+IF(AND($H216=$S$5,$O216=""),1.5,IF($O216<T$5,0,IF(MONTH($O216)=MONTH(T$5),1.5/30*($O216-T$5),1.5)))))))) -> 1.5 | U216: =+IF(AND(AND($O216="",$P216>=10,MONTH($G216)=MONTH(U$5))),1.5+2,+IF(AND(AND($O216="",$P216>=5,MONTH($G216)=MONTH(U$5))),1.5+1,+IF(AND(AND($P216=5,$O216="",MONTH($G216)=MONTH(U$5))),1.5,+IF(AND($H216>U$5,MONTH($H216)=MONTH(U$5)),1.5/30*(U$4-DAY($H216)),+IF(AND(MONTH($H216)<MONTH(U$5),$O216=""),1.5,+IF(AND($H216=$S$5,$O216=""),1.5,IF($O216<U$5,0,IF(MONTH($O216)=MONTH(U$5),1.5/30*($O216-U$5),1.5)))))))) -> 1.5 | V216: =+IF(AND(AND($O216="",$P216>=10,MONTH($G216)=MONTH(V$5))),1.5+2,+IF(AND(AND($O216="",$P216>=5,MONTH($G216)=MONTH(V$5))),1.5+1,+IF(AND(AND($P216=5,$O216="",MONTH($G216)=MONTH(V$5))),1.5,+IF(AND($H216>V$5,MONTH($H216)=MONTH(V$5)),1.5/30*(V$4-DAY($H216)),+IF(AND(MONTH($H216)<MONTH(V$5),$O216=""),1.5,+IF(AND($H216=$S$5,$O216=""),1.5,IF($O216<V$5,0,IF(MONTH($O216)=MONTH(V$5),1.5/30*($O216-V$5),1.5)))))))) -> 1.5 | W216: =+IF(AND(AND($O216="",$P216>=10,MONTH($G216)=MONTH(W$5))),1.5+2,+IF(AND(AND($O216="",$P216>=5,MONTH($G216)=MONTH(W$5))),1.5+1,+IF(AND(AND($P216=5,$O216="",MONTH($G216)=MONTH(W$5))),1.5,+IF(AND($H216>W$5,MONTH($H216)=MONTH(W$5)),1.5/30*(W$4-DAY($H216)),+IF(AND(MONTH($H216)<MONTH(W$5),$O216=""),1.5,+IF(AND($H216=$S$5,$O216=""),1.5,IF($O216<W$5,0,IF(MONTH($O216)=MONTH(W$5),1.5/30*($O216-W$5),1.5)))))))) -> 1.5 | X216: =+IF(AND(AND($O216="",$P216>=10,MONTH($G216)=MONTH(X$5))),1.5+2,+IF(AND(AND($O216="",$P216>=5,MONTH($G216)=MONTH(X$5))),1.5+1,+IF(AND(AND($P216=5,$O216="",MONTH($G216)=MONTH(X$5))),1.5,+IF(AND($H216>X$5,MONTH($H216)=MONTH(X$5)),1.5/30*(X$4-DAY($H216)),+IF(AND(MONTH($H216)<MONTH(X$5),$O216=""),1.5,+IF(AND($H216=$S$5,$O216=""),1.5,IF($O216<X$5,0,IF(MONTH($O216)=MONTH(X$5),1.5/30*($O216-X$5),1.5)))))))) -> 1.5 | Y216: =+IF(AND(AND($O216="",$P216>=10,MONTH($G216)=MONTH(Y$5))),1.5+2,+IF(AND(AND($O216="",$P216>=5,MONTH($G216)=MONTH(Y$5))),1.5+1,+IF(AND(AND($P216=5,$O216="",MONTH($G216)=MONTH(Y$5))),1.5,+IF(AND($H216>Y$5,MONTH($H216)=MONTH(Y$5)),1.5/30*(Y$4-DAY($H216)),+IF(AND(MONTH($H216)<MONTH(Y$5),$O216=""),1.5,+IF(AND($H216=$S$5,$O216=""),1.5,IF($O216<Y$5,0,IF(MONTH($O216)=MONTH(Y$5),1.5/30*($O216-Y$5),1.5)))))))) -> 1.5 | Z216: =+IF(AND(AND($O216="",$P216>=10,MONTH($G216)=MONTH(Z$5))),1.5+2,+IF(AND(AND($O216="",$P216>=5,MONTH($G216)=MONTH(Z$5))),1.5+1,+IF(AND(AND($P216=5,$O216="",MONTH($G216)=MONTH(Z$5))),1.5,+IF(AND($H216>Z$5,MONTH($H216)=MONTH(Z$5)),1.5/30*(Z$4-DAY($H216)),+IF(AND(MONTH($H216)<MONTH(Z$5),$O216=""),1.5,+IF(AND($H216=$S$5,$O216=""),1.5,IF($O216<Z$5,0,IF(MONTH($O216)=MONTH(Z$5),1.5/30*($O216-Z$5),1.5)))))))) -> 1.5 | ... AD216: =+IF(AND(AND($O216="",$P216>=10,MONTH($G216)=MONTH(AD$5))),1.5+2,+IF(AND(AND($O216="",$P216>=5,MONTH($G216)=MONTH(AD$5))),1.5+1,+IF(AND(AND($P216=5,$O216="",MONTH($G216)=MONTH(AD$5))),1.5,+IF(AND($H216>AD$5,MONTH($H216)=MONTH(AD$5)),1.5/30*(AD$4-DAY($H216)),+IF(AND(MONTH($H216)<MONTH(AD$5),$O216=""),1.5,+IF(AND($H216=$S$5,$O216=""),1.5,IF($O216<AD$5,0,IF(MONTH($O216)=MONTH(AD$5),1.5/30*($O216-AD$5),1.5)))))))) -> 1.5 | AF216: =SUM(AG216:AR216) -> 1 | AG216: 0 | AH216: 0 | AI216: 1 | AS216: =+Q216+R216-AF216 -> 17 | AU216: 0 | AV216: =SUM(AW216:BH216) -> 119.7 | AW216: =+IF($K216="",$E216/26*S216,IF(MONTH($K216)=MONTH(AW$5),$L216/26*S216,IF(AND($K216<AW$5,(MONTH($K216)<>MONTH(AW$5))),$L216/26*S216,$E216/26*S216))) -> 9.975 | AX216: =+IF($K216="",$E216/26*T216,IF(MONTH($K216)=MONTH(AX$5),$L216/26*T216,IF(AND($K216<AX$5,(MONTH($K216)<>MONTH(AX$5))),$L216/26*T216,$E216/26*T216))) -> 9.975 | AY216: =+IF($K216="",$E216/26*U216,IF(MONTH($K216)=MONTH(AY$5),$L216/26*U216,IF(AND($K216<AY$5,(MONTH($K216)<>MONTH(AY$5))),$L216/26*U216,$E216/26*U216))) -> 9.975 | AZ216: =+IF($K216="",$E216/26*V216,IF(MONTH($K216)=MONTH(AZ$5),$L216/26*V216,IF(AND($K216<AZ$5,(MONTH($K216)<>MONTH(AZ$5))),$L216/26*V216,$E216/26*V216))) -> 9.975 | BA216: =+IF($K216="",$E216/26*W216,IF(MONTH($K216)=MONTH(BA$5),$L216/26*W216,IF(AND($K216<BA$5,(MONTH($K216)<>MONTH(BA$5))),$L216/26*W216,$E216/26*W216))) -> 9.975 | BB216: =+IF($K216="",$E216/26*X216,IF(MONTH($K216)=MONTH(BB$5),$L216/26*X216,IF(AND($K216<BB$5,(MONTH($K216)<>MONTH(BB$5))),$L216/26*X216,$E216/26*X216))) -> 9.975 | BC216: =+IF($K216="",$E216/26*Y216,IF(MONTH($K216)=MONTH(BC$5),$L216/26*Y216,IF(AND($K216<BC$5,(MONTH($K216)<>MONTH(BC$5))),$L216/26*Y216,$E216/26*Y216))) -> 9.975 | BD216: =+IF($K216="",$E216/26*Z216,IF(MONTH($K216)=MONTH(BD$5),$L216/26*Z216,IF(AND($K216<BD$5,(MONTH($K216)<>MONTH(BD$5))),$L216/26*Z216,$E216/26*Z216))) -> 9.975 | ... BH216: =+IF($K216="",$E216/26*AD216,IF(MONTH($K216)=MONTH(BH$5),$L216/26*AD216,IF(AND($K216<BH$5,(MONTH($K216)<>MONTH(BH$5))),$L216/26*AD216,$E216/26*AD216))) -> 9.975 | BI216: =SUM(BJ216:BU216) -> -6.65 | BJ216: =(+IF($K216="",$E216/26*AG216,IF(MONTH($K216)=MONTH(BJ$5),$L216/26*AG216,IF(AND($K216<BJ$5,(MONTH($K216)<>MONTH(BJ$5))),$L216/26*AG216,$E216/26*AG216))))*-1 -> 0 | BK216: =(+IF($K216="",$E216/26*AH216,IF(MONTH($K216)=MONTH(BK$5),$L216/26*AH216,IF(AND($K216<BK$5,(MONTH($K216)<>MONTH(BK$5))),$L216/26*AH216,$E216/26*AH216))))*-1 -> 0 | BL216: =(+IF($K216="",$E216/26*AI216,IF(MONTH($K216)=MONTH(BL$5),$L216/26*AI216,IF(AND($K216<BL$5,(MONTH($K216)<>MONTH(BL$5))),$L216/26*AI216,$E216/26*AI216))))*-1 -> -6.65 | BM216: =(+IF($K216="",$E216/26*AJ216,IF(MONTH($K216)=MONTH(BM$5),$L216/26*AJ216,IF(AND($K216<BM$5,(MONTH($K216)<>MONTH(BM$5))),$L216/26*AJ216,$E216/26*AJ216))))*-1 -> 0 | BN216: =(+IF($K216="",$E216/26*AK216,IF(MONTH($K216)=MONTH(BN$5),$L216/26*AK216,IF(AND($K216<BN$5,(MONTH($K216)<>MONTH(BN$5))),$L216/26*AK216,$E216/26*AK216))))*-1 -> 0 | BO216: =(+IF($K216="",$E216/26*AL216,IF(MONTH($K216)=MONTH(BO$5),$L216/26*AL216,IF(AND($K216<BO$5,(MONTH($K216)<>MONTH(BO$5))),$L216/26*AL216,$E216/26*AL216))))*-1 -> 0 | BP216: =(+IF($K216="",$E216/26*AM216,IF(MONTH($K216)=MONTH(BP$5),$L216/26*AM216,IF(AND($K216<BP$5,(MONTH($K216)<>MONTH(BP$5))),$L216/26*AM216,$E216/26*AM216))))*-1 -> 0 | BQ216: =(+IF($K216="",$E216/26*AN216,IF(MONTH($K216)=MONTH(BQ$5),$L216/26*AN216,IF(AND($K216<BQ$5,(MONTH($K216)<>MONTH(BQ$5))),$L216/26*AN216,$E216/26*AN216))))*-1 -> 0 | ... BU216: =(+IF($K216="",$E216/26*AR216,IF(MONTH($K216)=MONTH(BU$5),$L216/26*AR216,IF(AND($K216<BU$5,(MONTH($K216)<>MONTH(BU$5))),$L216/26*AR216,$E216/26*AR216))))*-1 -> 0 | BV216: =+AU216+AV216+BI216 -> 113.05 | BX216: =+IF(AND($J216>BX$5,MONTH($J216<>BX$5)),0,+IF(AND($J216>BX$5,MONTH($J216=BX$5)),$E216/$R216*DAY($J216),IF(AND($O216<>"",$O216<BX$5),0,IF($K216="",$E216/$R216*S216,IF(MONTH($K216)=MONTH(BX$5),$L216/$R216*S216,IF(AND($K216<BX$5,(MONTH($K216)<>MONTH(BX$5))),$L216/$R216*S216,$E216/$R216*S216)))))) -> 14.408333 | BY216: =+IF(AND($J216>BY$5,MONTH($J216<>BY$5)),0,+IF(AND($J216>BY$5,MONTH($J216=BY$5)),$E216/$R216*DAY($J216),IF(AND($O216<>"",$O216<BY$5),0,IF($K216="",$E216/$R216*T216,IF(MONTH($K216)=MONTH(BY$5),$L216/$R216*T216,IF(AND($K216<BY$5,(MONTH($K216)<>MONTH(BY$5))),$L216/$R216*T216,$E216/$R216*T216)))))) -> 14.408333 | BZ216: =+IF(AND($J216>BZ$5,MONTH($J216<>BZ$5)),0,+IF(AND($J216>BZ$5,MONTH($J216=BZ$5)),$E216/$R216*DAY($J216),IF(AND($O216<>"",$O216<BZ$5),0,IF($K216="",$E216/$R216*U216,IF(MONTH($K216)=MONTH(BZ$5),$L216/$R216*U216,IF(AND($K216<BZ$5,(MONTH($K216)<>MONTH(BZ$5))),$L216/$R216*U216,$E216/$R216*U216)))))) -> 14.408333 | CA216: =+IF(AND($J216>CA$5,MONTH($J216<>CA$5)),0,+IF(AND($J216>CA$5,MONTH($J216=CA$5)),$E216/$R216*DAY($J216),IF(AND($O216<>"",$O216<CA$5),0,IF($K216="",$E216/$R216*V216,IF(MONTH($K216)=MONTH(CA$5),$L216/$R216*V216,IF(AND($K216<CA$5,(MONTH($K216)<>MONTH(CA$5))),$L216/$R216*V216,$E216/$R216*V216)))))) -> 14.408333 | CB216: =+IF(AND($J216>CB$5,MONTH($J216<>CB$5)),0,+IF(AND($J216>CB$5,MONTH($J216=CB$5)),$E216/$R216*DAY($J216),IF(AND($O216<>"",$O216<CB$5),0,IF($K216="",$E216/$R216*W216,IF(MONTH($K216)=MONTH(CB$5),$L216/$R216*W216,IF(AND($K216<CB$5,(MONTH($K216)<>MONTH(CB$5))),$L216/$R216*W216,$E216/$R216*W216)))))) -> 14.408333 | CC216: =+IF(AND($J216>CC$5,MONTH($J216<>CC$5)),0,+IF(AND($J216>CC$5,MONTH($J216=CC$5)),$E216/$R216*DAY($J216),IF(AND($O216<>"",$O216<CC$5),0,IF($K216="",$E216/$R216*X216,IF(MONTH($K216)=MONTH(CC$5),$L216/$R216*X216,IF(AND($K216<CC$5,(MONTH($K216)<>MONTH(CC$5))),$L216/$R216*X216,$E216/$R216*X216)))))) -> 14.408333 | CD216: =+IF(AND($J216>CD$5,MONTH($J216<>CD$5)),0,+IF(AND($J216>CD$5,MONTH($J216=CD$5)),$E216/$R216*DAY($J216),IF(AND($O216<>"",$O216<CD$5),0,IF($K216="",$E216/$R216*Y216,IF(MONTH($K216)=MONTH(CD$5),$L216/$R216*Y216,IF(AND($K216<CD$5,(MONTH($K216)<>MONTH(CD$5))),$L216/$R216*Y216,$E216/$R216*Y216)))))) -> 14.408333 | CE216: =+IF(AND($J216>CE$5,MONTH($J216<>CE$5)),0,+IF(AND($J216>CE$5,MONTH($J216=CE$5)),$E216/$R216*DAY($J216),IF(AND($O216<>"",$O216<CE$5),0,IF($K216="",$E216/$R216*Z216,IF(MONTH($K216)=MONTH(CE$5),$L216/$R216*Z216,IF(AND($K216<CE$5,(MONTH($K216)<>MONTH(CE$5))),$L216/$R216*Z216,$E216/$R216*Z216)))))) -> 14.408333 | ... CI216: =+IF(AND($J216>CI$5,MONTH($J216<>CI$5)),0,+IF(AND($J216>CI$5,MONTH($J216=CI$5)),$E216/$R216*DAY($J216),IF(AND($O216<>"",$O216<CI$5),0,IF($K216="",$E216/$R216*AD216,IF(MONTH($K216)=MONTH(CI$5),$L216/$R216*AD216,IF(AND($K216<CI$5,(MONTH($K216)<>MONTH(CI$5))),$L216/$R216*AD216,$E216/$R216*AD216)))))) -> 14.408333 | CJ216: =SUM(BX216:CI216) -> 172.9 | CK216: =+IF(P216<5,18,IF(AND(P216>=5,P216<10),19,IF(AND(P216>=10,P216<15),20,IF(AND(P216>=15,P216<20),21,0)))) -> 18 | CL216: =+CM216-CJ216 -> 0 | CM216: =IF(L216=0,E216,(L216-E216+E216)) -> 172.9
